Workbook

Sheet Direcional Expansão
A1: PCA (ANÁLISE DE COMPONENTE PRINCIPAL) - 3 componentes
A2: Cód | B2: Município | C2: UF | D2: N° FSJ | E2: Ass. por ambos | F2: Aquisição | G2: Ampliação | H2: Assinado por proprietário | I2: Contratos | J2: Venda > 500k | K2: Média Faturamento | L2: %Share | M2: Demanda | N2: População | O2: Porte da cidade | P2: REGIÃO GEOGRÁFICA IMEDIATA | Q2: REGIÃO GEOGRÁFICA INTERMEDIÁRIA | R2: Taxa Crescimento Pop | S2: Taxa Crescimento Dom | T2: Concorrência | U2: Lojas Cabem | V2: PIB | W2: Renda Média Domiciliar (SM) | X2: Fator 1 | Y2: Fator 2 | Z2: Fator 3 | AA2: Ranking | AB2: Status | AC2: Região Imediata
A3: 410690 | B3: Curitiba | C3: PR | D3: 4 | E3: =COUNTIFS('Contratos assinados '!F:F,'Direcional Expansão'!B3,'Contratos assinados '!J:J, "Assinado por ambos") -> 0 | F3: =COUNTIFS('Contratos assinados '!F:F,'Direcional Expansão'!B3,'Contratos assinados '!J:J,"Aquisição") -> 0 | G3: =COUNTIFS('Contratos assinados '!F:F,'Direcional Expansão'!B3,'Contratos assinados '!J:J,"Ampliação") -> 0 | H3: =COUNTIFS('Contratos assinados '!F:F,'Direcional Expansão'!B3,'Contratos assinados '!J:J,"Assinado por proprietário") -> 0 | I3: =SUM(E3:H3) -> 0 | J3: =IF(D3=0, "-", COUNTIFS('Base Lojas'!B:B, A3, 'Base Lojas'!I:I, ">500000")/D3) -> 0.5 | K3: 529473.24 | L3: 0.006059215 | M3: 3.4953256e+08 | N3: 1773733 | O3: =_xlfn.XLOOKUP(A3,Cidades!A:A,Cidades!D:D) -> Maior que 200k | P3: =_xlfn.XLOOKUP(A3,'[1]1° RAIZ'!$A:$A,'[1]1° RAIZ'!$AH:$AH) -> Curitiba | Q3: =_xlfn.XLOOKUP(A3,'[1]1° RAIZ'!$A:$A,'[1]1° RAIZ'!$AE:$AE) -> Curitiba | R3: 1.1734469e-05 | S3: 0.0061701967 | T3: 760 | U3: 113 | V3: 59976.102 | W3: 7.4815934 | X3: 23.530133 | Y3: -6.6132887 | Z3: -1.4440723 | AA3: 8.9042361 | AB3: =IF(B3="Capão do Leão","Erro IBGE", IF(AND(U3<=0,M3<=2000000),"Mercado insuficiente", IF(U3<=0,"Limite de expansão", IF(K3<500000,"Performance", IF(M3<=2000000,"Mercado insuficiente","Expansão") ) ) ) ) -> Expansão | AC3: =IF(P3=B3,"Oportunidade","Validar") -> Oportunidade
A4: 420910 | B4: Joinville | C4: SC | D4: 4 | E4: =COUNTIFS('Contratos assinados '!F:F,'Direcional Expansão'!B4,'Contratos assinados '!J:J, "Assinado por ambos") -> 0 | F4: =COUNTIFS('Contratos assinados '!F:F,'Direcional Expansão'!B4,'Contratos assinados '!J:J,"Aquisição") -> 0 | G4: =COUNTIFS('Contratos assinados '!F:F,'Direcional Expansão'!B4,'Contratos assinados '!J:J,"Ampliação") -> 0 | H4: =COUNTIFS('Contratos assinados '!F:F,'Direcional Expansão'!B4,'Contratos assinados '!J:J,"Assinado por proprietário") -> 0 | I4: =SUM(E4:H4) -> 0 | J4: =IF(D4=0, "-", COUNTIFS('Base Lojas'!B:B, A4, 'Base Lojas'!G:G, ">500000")/D4) -> 0.5 | K4: 473206.54 | L4: 0.016675383 | M4: 1.1351021e+08 | N4: 616323 | O4: =_xlfn.XLOOKUP(A4,Cidades!A:A,Cidades!D:D) -> Maior que 200k | P4: =_xlfn.XLOOKUP(A4,'[1]1° RAIZ'!$A:$A,'[1]1° RAIZ'!$AH:$AH) -> Joinville | Q4: =_xlfn.XLOOKUP(A4,'[1]1° RAIZ'!$A:$A,'[1]1° RAIZ'!$AE:$AE) -> Joinville | R4: 0.00013873741 | S4: 0.015512934 | T4: 228 | U4: 36 | V4: 75898.327 | W4: 5.6415158 | X4: 7.5371564 | Y4: -1.1918205 | Z4: -0.53373233 | AA4: 2.9774401 | AB4: =IF(B4="Capão do Leão","Erro IBGE", IF(AND(U4<=0,M4<=2000000),"Mercado insuficiente", IF(U4<=0,"Limite de expansão", IF(K4<500000,"Performance", IF(M4<=2000000,"Mercado insuficiente","Expansão") ) ) ) ) -> Performance | AC4: =IF(P4=B4,"Oportunidade","Validar") -> Oportunidade
A5: 411990 | B5: Ponta Grossa | C5: PR | D5: 0 | E5: =COUNTIFS('Contratos assinados '!F:F,'Direcional Expansão'!B5,'Contratos assinados '!J:J, "Assinado por ambos") -> 0 | F5: =COUNTIFS('Contratos assinados '!F:F,'Direcional Expansão'!B5,'Contratos assinados '!J:J,"Aquisição") -> 0 | G5: =COUNTIFS('Contratos assinados '!F:F,'Direcional Expansão'!B5,'Contratos assinados '!J:J,"Ampliação") -> 0 | H5: =COUNTIFS('Contratos assinados '!F:F,'Direcional Expansão'!B5,'Contratos assinados '!J:J,"Assinado por proprietário") -> 0 | I5: =SUM(E5:H5) -> 0 | J5: =IF(D5=0, "-", COUNTIFS('Base Lojas'!B:B, A5, 'Base Lojas'!I:I, ">500000")/D5) -> - | K5: - | L5: 0 | M5: 52309124 | N5: 358367 | O5: =_xlfn.XLOOKUP(A5,Cidades!A:A,Cidades!D:D) -> Maior que 200k | P5: =_xlfn.XLOOKUP(A5,'[1]1° RAIZ'!$A:$A,'[1]1° RAIZ'!$AH:$AH) -> Ponta Grossa | Q5: =_xlfn.XLOOKUP(A5,'[1]1° RAIZ'!$A:$A,'[1]1° RAIZ'!$AE:$AE) -> Ponta Grossa | R5: 0.00010790575 | S5: 0.015582368 | T5: 109 | U5: 23 | V5: 58329.645 | W5: 4.495249 | X5: 3.9681546 | Y5: -0.78599628 | Z5: -0.73897544 | AA5: 1.4924571 | AB5: =IF(B5="Capão do Leão","Erro IBGE", IF(AND(U5<=0,M5<=2000000),"Mercado insuficiente", IF(U5<=0,"Limite de expansão", IF(K5<500000,"Performance", IF(M5<=2000000,"Mercado insuficiente","Expansão") ) ) ) ) -> Expansão | AC5: =IF(P5=B5,"Oportunidade","Validar") -> Oportunidade
A6: 412550 | B6: São José dos Pinhais | C6: PR | D6: 0 | E6: =COUNTIFS('Contratos assinados '!F:F,'Direcional Expansão'!B6,'Contratos assinados '!J:J, "Assinado por ambos") -> 0 | F6: =COUNTIFS('Contratos assinados '!F:F,'Direcional Expansão'!B6,'Contratos assinados '!J:J,"Aquisição") -> 0 | G6: =COUNTIFS('Contratos assinados '!F:F,'Direcional Expansão'!B6,'Contratos assinados '!J:J,"Ampliação") -> 0 | H6: =COUNTIFS('Contratos assinados '!F:F,'Direcional Expansão'!B6,'Contratos assinados '!J:J,"Assinado por proprietário") -> 0 | I6: =SUM(E6:H6) -> 0 | J6: =IF(D6=0, "-", COUNTIFS('Base Lojas'!B:B, A6, 'Base Lojas'!I:I, ">500000")/D6) -> - | K6: - | L6: 0 | M6: 45151280 | N6: 329222 | O6: =_xlfn.XLOOKUP(A6,Cidades!A:A,Cidades!D:D) -> Maior que 200k | P6: =_xlfn.XLOOKUP(A6,'[1]1° RAIZ'!$A:$A,'[1]1° RAIZ'!$AH:$AH) -> Curitiba | Q6: =_xlfn.XLOOKUP(A6,'[1]1° RAIZ'!$A:$A,'[1]1° RAIZ'!$AE:$AE) -> Curitiba | R6: 0.00017280257 | S6: 0.020583707 | T6: 129 | U6: 21 | V6: 86698.641 | W6: 4.3486417 | X6: 3.8143556 | Y6: -0.36303554 | Z6: -0.40662252 | AA6: 1.5257804 | AB6: =IF(B6="Capão do Leão","Erro IBGE", IF(AND(U6<=0,M6<=2000000),"Mercado insuficiente", IF(U6<=0,"Limite de expansão", IF(K6<500000,"Performance", IF(M6<=2000000,"Mercado insuficiente","Expansão") ) ) ) ) -> Expansão | AC6: =IF(P6=B6,"Oportunidade","Validar") -> Validar
A7: 411370 | B7: Londrina | C7: PR | D7: 16 | E7: =COUNTIFS('Contratos assinados '!F:F,'Direcional Expansão'!B7,'Contratos assinados '!J:J, "Assinado por ambos") -> 0 | F7: =COUNTIFS('Contratos assinados '!F:F,'Direcional Expansão'!B7,'Contratos assinados '!J:J,"Aquisição") -> 0 | G7: =COUNTIFS('Contratos assinados '!F:F,'Direcional Expansão'!B7,'Contratos assinados '!J:J,"Ampliação") -> 0 | H7: =COUNTIFS('Contratos assinados '!F:F,'Direcional Expansão'!B7,'Contratos assinados '!J:J,"Assinado por proprietário") -> 0 | I7: =SUM(E7:H7) -> 0 | J7: =IF(D7=0, "-", COUNTIFS('Base Lojas'!B:B, A7, 'Base Lojas'!G:G, ">500000")/D7) -> 0.3125 | K7: 450156.55 | L7: 0.076176118 | M7: 94550694 | N7: 555937 | O7: =_xlfn.XLOOKUP(A7,Cidades!A:A,Cidades!D:D) -> Maior que 200k | P7: =_xlfn.XLOOKUP(A7,'[1]1° RAIZ'!$A:$A,'[1]1° RAIZ'!$AH:$AH) -> Londrina | Q7: =_xlfn.XLOOKUP(A7,'[1]1° RAIZ'!$A:$A,'[1]1° RAIZ'!$AE:$AE) -> Londrina | R7: 7.1674423e-05 | S7: 0.010994379 | T7: 183 | U7: 20 | V7: 45612.287 | W7: 5.186494 | X7: 5.724654 | Y7: -1.0124124 | Z7: -0.3783049 | AA7: 2.2491 | AB7: =IF(B7="Capão do Leão","Erro IBGE", IF(AND(U7<=0,M7<=2000000),"Mercado insuficiente", IF(U7<=0,"Limite de expansão", IF(K7<500000,"Performance", IF(M7<=2000000,"Mercado insuficiente","Expansão") ) ) ) ) -> Performance | AC7: =IF(P7=B7,"Oportunidade","Validar") -> Oportunidade
A8: 420540 | B8: Florianópolis | C8: SC | D8: 18 | E8: =COUNTIFS('Contratos assinados '!F:F,'Direcional Expansão'!B8,'Contratos assinados '!J:J, "Assinado por ambos") -> 0 | F8: =COUNTIFS('Contratos assinados '!F:F,'Direcional Expansão'!B8,'Contratos assinados '!J:J,"Aquisição") -> 0 | G8: =COUNTIFS('Contratos assinados '!F:F,'Direcional Expansão'!B8,'Contratos assinados '!J:J,"Ampliação") -> 0 | H8: =COUNTIFS('Contratos assinados '!F:F,'Direcional Expansão'!B8,'Contratos assinados '!J:J,"Assinado por proprietário") -> 0 | I8: =SUM(E8:H8) -> 0 | J8: =IF(D8=0, "-", COUNTIFS('Base Lojas'!B:B, A8, 'Base Lojas'!I:I, ">500000")/D8) -> 0.77777778 | K8: 884907.8 | L8: 0.12015389 | M8: 1.3256616e+08 | N8: 537213 | O8: =_xlfn.XLOOKUP(A8,Cidades!A:A,Cidades!D:D) -> Maior que 200k | P8: =_xlfn.XLOOKUP(A8,'[1]1° RAIZ'!$A:$A,'[1]1° RAIZ'!$AH:$AH) -> Florianópolis | Q8: =_xlfn.XLOOKUP(A8,'[1]1° RAIZ'!$A:$A,'[1]1° RAIZ'!$AE:$AE) -> Florianópolis | R8: 0.00018890029 | S8: 0.020340133 | T8: 237 | U8: 17 | V8: 44854.646 | W8: 8.0222292 | X8: 6.879443 | Y8: 0.53207887 | Z8: -0.33951717 | AA8: 2.9676422 | AB8: =IF(B8="Capão do Leão","Erro IBGE", IF(AND(U8<=0,M8<=2000000),"Mercado insuficiente", IF(U8<=0,"Limite de expansão", IF(K8<500000,"Performance", IF(M8<=2000000,"Mercado insuficiente","Expansão") ) ) ) ) -> Expansão | AC8: =IF(P8=B8,"Oportunidade","Validar") -> Oportunidade
A9: 420240 | B9: Blumenau | C9: SC | D9: 6 | E9: =COUNTIFS('Contratos assinados '!F:F,'Direcional Expansão'!B9,'Contratos assinados '!J:J, "Assinado por ambos") -> 1 | F9: =COUNTIFS('Contratos assinados '!F:F,'Direcional Expansão'!B9,'Contratos assinados '!J:J,"Aquisição") -> 0 | G9: =COUNTIFS('Contratos assinados '!F:F,'Direcional Expansão'!B9,'Contratos assinados '!J:J,"Ampliação") -> 0 | H9: =COUNTIFS('Contratos assinados '!F:F,'Direcional Expansão'!B9,'Contratos assinados '!J:J,"Assinado por proprietário") -> 0 | I9: =SUM(E9:H9) -> 1 | J9: =IF(D9=0, "-", COUNTIFS('Base Lojas'!B:B, A9, 'Base Lojas'!G:G, ">500000")/D9) -> 0.16666667 | K9: 399569.23 | L9: 0.030600313 | M9: 78346106 | N9: 361261 | O9: =_xlfn.XLOOKUP(A9,Cidades!A:A,Cidades!D:D) -> Maior que 200k | P9: =_xlfn.XLOOKUP(A9,'[1]1° RAIZ'!$A:$A,'[1]1° RAIZ'!$AH:$AH) -> Blumenau | Q9: =_xlfn.XLOOKUP(A9,'[1]1° RAIZ'!$A:$A,'[1]1° RAIZ'!$AE:$AE) -> Blumenau | R9: 0.00012038587 | S9: 0.014892859 | T9: 134 | U9: 17 | V9: 59879.071 | W9: 5.9650006 | X9: 4.416656 | Y9: 0.034937689 | Z9: -0.42486282 | AA9: 1.8374896 | AB9: =IF(B9="Capão do Leão","Erro IBGE", IF(AND(U9<=0,M9<=2000000),"Mercado insuficiente", IF(U9<=0,"Limite de expansão", IF(K9<500000,"Performance", IF(M9<=2000000,"Mercado insuficiente","Expansão") ) ) ) ) -> Performance | AC9: =IF(P9=B9,"Oportunidade","Validar") -> Oportunidade
A10: 410480 | B10: Cascavel | C10: PR | D10: 6 | E10: =COUNTIFS('Contratos assinados '!F:F,'Direcional Expansão'!B10,'Contratos assinados '!J:J, "Assinado por ambos") -> 0 | F10: =COUNTIFS('Contratos assinados '!F:F,'Direcional Expansão'!B10,'Contratos assinados '!J:J,"Aquisição") -> 0 | G10: =COUNTIFS('Contratos assinados '!F:F,'Direcional Expansão'!B10,'Contratos assinados '!J:J,"Ampliação") -> 0 | H10: =COUNTIFS('Contratos assinados '!F:F,'Direcional Expansão'!B10,'Contratos assinados '!J:J,"Assinado por proprietário") -> 0 | I10: =SUM(E10:H10) -> 0 | J10: =IF(D10=0, "-", COUNTIFS('Base Lojas'!B:B, A10, 'Base Lojas'!G:G, ">500000")/D10) -> 0.33333333 | K10: 499028.02 | L10: 0.051856357 | M10: 57739655 | N10: 348051 | O10: =_xlfn.XLOOKUP(A10,Cidades!A:A,Cidades!D:D) -> Maior que 200k | P10: =_xlfn.XLOOKUP(A10,'[1]1° RAIZ'!$A:$A,'[1]1° RAIZ'!$AH:$AH) -> Cascavel | Q10: =_xlfn.XLOOKUP(A10,'[1]1° RAIZ'!$A:$A,'[1]1° RAIZ'!$AE:$AE) -> Cascavel | R10: 0.00015172098 | S10: 0.019428703 | T10: 129 | U10: 17 | V10: 48193.639 | W10: 4.8722281 | X10: 3.8938653 | Y10: -0.39791193 | Z10: -0.68214471 | AA10: 1.5231674 | AB10: =IF(B10="Capão do Leão","Erro IBGE", IF(AND(U10<=0,M10<=2000000),"Mercado insuficiente", IF(U10<=0,"Limite de expansão", IF(K10<500000,"Performance", IF(M10<=2000000,"Mercado insuficiente","Expansão") ) ) ) ) -> Performance | AC10: =IF(P10=B10,"Oportunidade","Validar") -> Oportunidade
A11: 410580 | B11: Colombo | C11: PR | D11: 0 | E11: =COUNTIFS('Contratos assinados '!F:F,'Direcional Expansão'!B11,'Contratos assinados '!J:J, "Assinado por ambos") -> 0 | F11: =COUNTIFS('Contratos assinados '!F:F,'Direcional Expansão'!B11,'Contratos assinados '!J:J,"Aquisição") -> 0 | G11: =COUNTIFS('Contratos assinados '!F:F,'Direcional Expansão'!B11,'Contratos assinados '!J:J,"Ampliação") -> 0 | H11: =COUNTIFS('Contratos assinados '!F:F,'Direcional Expansão'!B11,'Contratos assinados '!J:J,"Assinado por proprietário") -> 0 | I11: =SUM(E11:H11) -> 0 | J11: =IF(D11=0, "-", COUNTIFS('Base Lojas'!B:B, A11, 'Base Lojas'!I:I, ">500000")/D11) -> - | K11: - | L11: 0 | M11: 29870151 | N11: 232056 | O11: =_xlfn.XLOOKUP(A11,Cidades!A:A,Cidades!D:D) -> Maior que 200k | P11: =_xlfn.XLOOKUP(A11,'[1]1° RAIZ'!$A:$A,'[1]1° RAIZ'!$AH:$AH) -> Curitiba | Q11: =_xlfn.XLOOKUP(A11,'[1]1° RAIZ'!$A:$A,'[1]1° RAIZ'!$AE:$AE) -> Curitiba | R11: 6.6032292e-05 | S11: 0.011526628 | T11: 74 | U11: 15 | V11: 26402.994 | W11: 3.5680095 | X11: 2.3689253 | Y11: -1.1012465 | Z11: -1.0623745 | AA11: 0.72908048 | AB11: =IF(B11="Capão do Leão","Erro IBGE", IF(AND(U11<=0,M11<=2000000),"Mercado insuficiente", IF(U11<=0,"Limite de expansão", IF(K11<500000,"Performance", IF(M11<=2000000,"Mercado insuficiente","Expansão") ) ) ) ) -> Expansão | AC11: =IF(P11=B11,"Oportunidade","Validar") -> Validar
A12: 411520 | B12: Maringá | C12: PR | D12: 16 | E12: =COUNTIFS('Contratos assinados '!F:F,'Direcional Expansão'!B12,'Contratos assinados '!J:J, "Assinado por ambos") -> 1 | F12: =COUNTIFS('Contratos assinados '!F:F,'Direcional Expansão'!B12,'Contratos assinados '!J:J,"Aquisição") -> 0 | G12: =COUNTIFS('Contratos assinados '!F:F,'Direcional Expansão'!B12,'Contratos assinados '!J:J,"Ampliação") -> 0 | H12: =COUNTIFS('Contratos assinados '!F:F,'Direcional Expansão'!B12,'Contratos assinados '!J:J,"Assinado por proprietário") -> 0 | I12: =SUM(E12:H12) -> 1 | J12: =IF(D12=0, "-", COUNTIFS('Base Lojas'!B:B, A12, 'Base Lojas'!G:G, ">500000")/D12) -> 0.1875 | K12: 368659.03 | L12: 0.080085143 | M12: 73653417 | N12: 409657 | O12: =_xlfn.XLOOKUP(A12,Cidades!A:A,Cidades!D:D) -> Maior que 200k | P12: =_xlfn.XLOOKUP(A12,'[1]1° RAIZ'!$A:$A,'[1]1° RAIZ'!$AH:$AH) -> Maringá | Q12: =_xlfn.XLOOKUP(A12,'[1]1° RAIZ'!$A:$A,'[1]1° RAIZ'!$AE:$AE) -> Maringá | R12: 0.00010614147 | S12: 0.014936784 | T12: 152 | U12: 11 | V12: 59294.088 | W12: 5.7430176 | X12: 4.2750996 | Y12: 0.088244137 | Z12: -0.10896035 | AA12: 1.820941 | AB12: =IF(B12="Capão do Leão","Erro IBGE", IF(AND(U12<=0,M12<=2000000),"Mercado insuficiente", IF(U12<=0,"Limite de expansão", IF(K12<500000,"Performance", IF(M12<=2000000,"Mercado insuficiente","Expansão") ) ) ) ) -> Performance | AC12: =IF(P12=B12,"Oportunidade","Validar") -> Oportunidade
A13: 421660 | B13: São José | C13: SC | D13: 7 | E13: =COUNTIFS('Contratos assinados '!F:F,'Direcional Expansão'!B13,'Contratos assinados '!J:J, "Assinado por ambos") -> 1 | F13: =COUNTIFS('Contratos assinados '!F:F,'Direcional Expansão'!B13,'Contratos assinados '!J:J,"Aquisição") -> 0 | G13: =COUNTIFS('Contratos assinados '!F:F,'Direcional Expansão'!B13,'Contratos assinados '!J:J,"Ampliação") -> 0 | H13: =COUNTIFS('Contratos assinados '!F:F,'Direcional Expansão'!B13,'Contratos assinados '!J:J,"Assinado por proprietário") -> 0 | I13: =SUM(E13:H13) -> 1 | J13: =IF(D13=0, "-", COUNTIFS('Base Lojas'!B:B, A13, 'Base Lojas'!G:G, ">500000")/D13) -> 0.42857143 | K13: 477121.93 | L13: 0.058758649 | M13: 56840203 | N13: 270295 | O13: =_xlfn.XLOOKUP(A13,Cidades!A:A,Cidades!D:D) -> Maior que 200k | P13: =_xlfn.XLOOKUP(A13,'[1]1° RAIZ'!$A:$A,'[1]1° RAIZ'!$AH:$AH) -> Florianópolis | Q13: =_xlfn.XLOOKUP(A13,'[1]1° RAIZ'!$A:$A,'[1]1° RAIZ'!$AE:$AE) -> Florianópolis | R13: 0.00019414248 | S13: 0.021606297 | T13: 100 | U13: 10 | V13: 52385.161 | W13: 5.4429226 | X13: 3.0875136 | Y13: 0.39455517 | Z13: -0.53957272 | AA13: 1.3101021 | AB13: =IF(B13="Capão do Leão","Erro IBGE", IF(AND(U13<=0,M13<=2000000),"Mercado insuficiente", IF(U13<=0,"Limite de expansão", IF(K13<500000,"Performance", IF(M13<=2000000,"Mercado insuficiente","Expansão") ) ) ) ) -> Performance | AC13: =IF(P13=B13,"Oportunidade","Validar") -> Validar
A14: 410940 | B14: Guarapuava | C14: PR | D14: 2 | E14: =COUNTIFS('Contratos assinados '!F:F,'Direcional Expansão'!B14,'Contratos assinados '!J:J, "Assinado por ambos") -> 1 | F14: =COUNTIFS('Contratos assinados '!F:F,'Direcional Expansão'!B14,'Contratos assinados '!J:J,"Aquisição") -> 0 | G14: =COUNTIFS('Contratos assinados '!F:F,'Direcional Expansão'!B14,'Contratos assinados '!J:J,"Ampliação") -> 0 | H14: =COUNTIFS('Contratos assinados '!F:F,'Direcional Expansão'!B14,'Contratos assinados '!J:J,"Assinado por proprietário") -> 0 | I14: =SUM(E14:H14) -> 1 | J14: =IF(D14=0, "-", COUNTIFS('Base Lojas'!B:B, A14, 'Base Lojas'!I:I, ">500000")/D14) -> 0.5 | K14: 516079.9 | L14: 0.042569286 | M14: 24246585 | N14: 182093 | O14: =_xlfn.XLOOKUP(A14,Cidades!A:A,Cidades!D:D) -> Entre 150k e 200k | P14: =_xlfn.XLOOKUP(A14,'[1]1° RAIZ'!$A:$A,'[1]1° RAIZ'!$AH:$AH) -> Guarapuava | Q14: =_xlfn.XLOOKUP(A14,'[1]1° RAIZ'!$A:$A,'[1]1° RAIZ'!$AE:$AE) -> Guarapuava | R14: 6.4634999e-05 | S14: 0.010953216 | T14: 65 | U14: 10 | V14: 49171.471 | W14: 3.871627 | X14: 1.8233473 | Y14: -0.42327467 | Z14: -0.45826001 | AA14: 0.66328436 | AB14: =IF(B14="Capão do Leão","Erro IBGE", IF(AND(U14<=0,M14<=2000000),"Mercado insuficiente", IF(U14<=0,"Limite de expansão", IF(K14<500000,"Performance", IF(M14<=2000000,"Mercado insuficiente","Expansão") ) ) ) ) -> Expansão | AC14: =IF(P14=B14,"Oportunidade","Validar") -> Oportunidade
A15: 420820 | B15: Itajaí | C15: SC | D15: 8 | E15: =COUNTIFS('Contratos assinados '!F:F,'Direcional Expansão'!B15,'Contratos assinados '!J:J, "Assinado por ambos") -> 0 | F15: =COUNTIFS('Contratos assinados '!F:F,'Direcional Expansão'!B15,'Contratos assinados '!J:J,"Aquisição") -> 0 | G15: =COUNTIFS('Contratos assinados '!F:F,'Direcional Expansão'!B15,'Contratos assinados '!J:J,"Ampliação") -> 1 | H15: =COUNTIFS('Contratos assinados '!F:F,'Direcional Expansão'!B15,'Contratos assinados '!J:J,"Assinado por proprietário") -> 0 | I15: =SUM(E15:H15) -> 1 | J15: =IF(D15=0, "-", COUNTIFS('Base Lojas'!B:B, A15, 'Base Lojas'!I:I, ">500000")/D15) -> 0.75 | K15: 639106.45 | L15: 0.10154863 | M15: 50348798 | N15: 264054 | O15: =_xlfn.XLOOKUP(A15,Cidades!A:A,Cidades!D:D) -> Maior que 200k | P15: =_xlfn.XLOOKUP(A15,'[1]1° RAIZ'!$A:$A,'[1]1° RAIZ'!$AH:$AH) -> Itajaí | Q15: =_xlfn.XLOOKUP(A15,'[1]1° RAIZ'!$A:$A,'[1]1° RAIZ'!$AE:$AE) -> Blumenau | R15: 0.00028439155 | S15: 0.027286013 | T15: 105 | U15: 9 | V15: 181166.23 | W15: 5.0486227 | X15: 2.9610387 | Y15: 1.7575112 | Z15: 1.4836989 | AA15: 1.6834055 | AB15: =IF(B15="Capão do Leão","Erro IBGE", IF(AND(U15<=0,M15<=2000000),"Mercado insuficiente", IF(U15<=0,"Limite de expansão", IF(K15<500000,"Performance", IF(M15<=2000000,"Mercado insuficiente","Expansão") ) ) ) ) -> Expansão | AC15: =IF(P15=B15,"Oportunidade","Validar") -> Oportunidade
A16: 420420 | B16: Chapecó | C16: SC | D16: 7 | E16: =COUNTIFS('Contratos assinados '!F:F,'Direcional Expansão'!B16,'Contratos assinados '!J:J, "Assinado por ambos") -> 0 | F16: =COUNTIFS('Contratos assinados '!F:F,'Direcional Expansão'!B16,'Contratos assinados '!J:J,"Aquisição") -> 0 | G16: =COUNTIFS('Contratos assinados '!F:F,'Direcional Expansão'!B16,'Contratos assinados '!J:J,"Ampliação") -> 0 | H16: =COUNTIFS('Contratos assinados '!F:F,'Direcional Expansão'!B16,'Contratos assinados '!J:J,"Assinado por proprietário") -> 0 | I16: =SUM(E16:H16) -> 0 | J16: =IF(D16=0, "-", COUNTIFS('Base Lojas'!B:B, A16, 'Base Lojas'!I:I, ">500000")/D16) -> 0.57142857 | K16: 501567.47 | L16: 0.079815749 | M16: 43988465 | N16: 254781 | O16: =_xlfn.XLOOKUP(A16,Cidades!A:A,Cidades!D:D) -> Maior que 200k | P16: =_xlfn.XLOOKUP(A16,'[1]1° RAIZ'!$A:$A,'[1]1° RAIZ'!$AH:$AH) -> Chapecó | Q16: =_xlfn.XLOOKUP(A16,'[1]1° RAIZ'!$A:$A,'[1]1° RAIZ'!$AE:$AE) -> Chapecó | R16: 0.00025540503 | S16: 0.02501592 | T16: 100 | U16: 9 | V16: 54201.449 | W16: 4.9208035 | X16: 2.735713 | Y16: 0.4019574 | Z16: -0.57833914 | AA16: 1.1569171 | AB16: =IF(B16="Capão do Leão","Erro IBGE", IF(AND(U16<=0,M16<=2000000),"Mercado insuficiente", IF(U16<=0,"Limite de expansão", IF(K16<500000,"Performance", IF(M16<=2000000,"Mercado insuficiente","Expansão") ) ) ) ) -> Expansão | AC16: =IF(P16=B16,"Oportunidade","Validar") -> Oportunidade
A17: 420890 | B17: Jaraguá do Sul | C17: SC | D17: 3 | E17: =COUNTIFS('Contratos assinados '!F:F,'Direcional Expansão'!B17,'Contratos assinados '!J:J, "Assinado por ambos") -> 0 | F17: =COUNTIFS('Contratos assinados '!F:F,'Direcional Expansão'!B17,'Contratos assinados '!J:J,"Aquisição") -> 0 | G17: =COUNTIFS('Contratos assinados '!F:F,'Direcional Expansão'!B17,'Contratos assinados '!J:J,"Ampliação") -> 0 | H17: =COUNTIFS('Contratos assinados '!F:F,'Direcional Expansão'!B17,'Contratos assinados '!J:J,"Assinado por proprietário") -> 0 | I17: =SUM(E17:H17) -> 0 | J17: =IF(D17=0, "-", COUNTIFS('Base Lojas'!B:B, A17, 'Base Lojas'!G:G, ">500000")/D17) -> 0.33333333 | K17: 459276.87 | L17: 0.040100084 | M17: 34359794 | N17: 182660 | O17: =_xlfn.XLOOKUP(A17,Cidades!A:A,Cidades!D:D) -> Entre 150k e 200k | P17: =_xlfn.XLOOKUP(A17,'[1]1° RAIZ'!$A:$A,'[1]1° RAIZ'!$AH:$AH) -> Joinville | Q17: =_xlfn.XLOOKUP(A17,'[1]1° RAIZ'!$A:$A,'[1]1° RAIZ'!$AE:$AE) -> Joinville | R17: 0.00018894934 | S17: 0.019594958 | T17: 92 | U17: 9 | V17: 67610.974 | W17: 5.4838698 | X17: 2.3618351 | Y17: 0.74617975 | Z17: -0.38126763 | AA17: 1.0697355 | AB17: =IF(B17="Capão do Leão","Erro IBGE", IF(AND(U17<=0,M17<=2000000),"Mercado insuficiente", IF(U17<=0,"Limite de expansão", IF(K17<500000,"Performance", IF(M17<=2000000,"Mercado insuficiente","Expansão") ) ) ) ) -> Performance | AC17: =IF(P17=B17,"Oportunidade","Validar") -> Validar
A18: 410180 | B18: Araucária | C18: PR | D18: 1 | E18: =COUNTIFS('Contratos assinados '!F:F,'Direcional Expansão'!B18,'Contratos assinados '!J:J, "Assinado por ambos") -> 0 | F18: =COUNTIFS('Contratos assinados '!F:F,'Direcional Expansão'!B18,'Contratos assinados '!J:J,"Aquisição") -> 0 | G18: =COUNTIFS('Contratos assinados '!F:F,'Direcional Expansão'!B18,'Contratos assinados '!J:J,"Ampliação") -> 0 | H18: =COUNTIFS('Contratos assinados '!F:F,'Direcional Expansão'!B18,'Contratos assinados '!J:J,"Assinado por proprietário") -> 0 | I18: =SUM(E18:H18) -> 0 | J18: =IF(D18=0, "-", COUNTIFS('Base Lojas'!B:B, A18, 'Base Lojas'!I:I, ">500000")/D18) -> 1 | K18: 511004.74 | L18: 0.024332456 | M18: 21000952 | N18: 151666 | O18: =_xlfn.XLOOKUP(A18,Cidades!A:A,Cidades!D:D) -> Entre 150k e 200k | P18: =_xlfn.XLOOKUP(A18,'[1]1° RAIZ'!$A:$A,'[1]1° RAIZ'!$AH:$AH) -> Curitiba | Q18: =_xlfn.XLOOKUP(A18,'[1]1° RAIZ'!$A:$A,'[1]1° RAIZ'!$AE:$AE) -> Curitiba | R18: 0.00018697202 | S18: 0.022555882 | T18: 40 | U18: 9 | V18: 174727.8 | W18: 4.2958383 | X18: 1.5297908 | Y18: 1.4227987 | Z18: 1.2175216 | AA18: 0.99529999 | AB18: =IF(B18="Capão do Leão","Erro IBGE", IF(AND(U18<=0,M18<=2000000),"Mercado insuficiente", IF(U18<=0,"Limite de expansão", IF(K18<500000,"Performance", IF(M18<=2000000,"Mercado insuficiente","Expansão") ) ) ) ) -> Expansão | AC18: =IF(P18=B18,"Oportunidade","Validar") -> Validar
A19: 421190 | B19: Palhoça | C19: SC | D19: 5 | E19: =COUNTIFS('Contratos assinados '!F:F,'Direcional Expansão'!B19,'Contratos assinados '!J:J, "Assinado por ambos") -> 1 | F19: =COUNTIFS('Contratos assinados '!F:F,'Direcional Expansão'!B19,'Contratos assinados '!J:J,"Aquisição") -> 0 | G19: =COUNTIFS('Contratos assinados '!F:F,'Direcional Expansão'!B19,'Contratos assinados '!J:J,"Ampliação") -> 0 | H19: =COUNTIFS('Contratos assinados '!F:F,'Direcional Expansão'!B19,'Contratos assinados '!J:J,"Assinado por proprietário") -> 0 | I19: =SUM(E19:H19) -> 1 | J19: =IF(D19=0, "-", COUNTIFS('Base Lojas'!B:B, A19, 'Base Lojas'!G:G, ">500000")/D19) -> 0.4 | K19: 493436.91 | L19: 0.064238482 | M19: 38406644 | N19: 222598 | O19: =_xlfn.XLOOKUP(A19,Cidades!A:A,Cidades!D:D) -> Maior que 200k | P19: =_xlfn.XLOOKUP(A19,'[1]1° RAIZ'!$A:$A,'[1]1° RAIZ'!$AH:$AH) -> Florianópolis | Q19: =_xlfn.XLOOKUP(A19,'[1]1° RAIZ'!$A:$A,'[1]1° RAIZ'!$AE:$AE) -> Florianópolis | R19: 0.00037927329 | S19: 0.03776951 | T19: 76 | U19: 9 | V19: 36199.948 | W19: 4.2944095 | X19: 2.2931288 | Y19: 0.30369951 | Z19: -1.2451161 | AA19: 0.87816468 | AB19: =IF(B19="Capão do Leão","Erro IBGE", IF(AND(U19<=0,M19<=2000000),"Mercado insuficiente", IF(U19<=0,"Limite de expansão", IF(K19<500000,"Performance", IF(M19<=2000000,"Mercado insuficiente","Expansão") ) ) ) ) -> Performance | AC19: =IF(P19=B19,"Oportunidade","Validar") -> Validar
A20: 411820 | B20: Paranaguá | C20: PR | D20: 0 | E20: =COUNTIFS('Contratos assinados '!F:F,'Direcional Expansão'!B20,'Contratos assinados '!J:J, "Assinado por ambos") -> 0 | F20: =COUNTIFS('Contratos assinados '!F:F,'Direcional Expansão'!B20,'Contratos assinados '!J:J,"Aquisição") -> 0 | G20: =COUNTIFS('Contratos assinados '!F:F,'Direcional Expansão'!B20,'Contratos assinados '!J:J,"Ampliação") -> 0 | H20: =COUNTIFS('Contratos assinados '!F:F,'Direcional Expansão'!B20,'Contratos assinados '!J:J,"Assinado por proprietário") -> 0 | I20: =SUM(E20:H20) -> 0 | J20: =IF(D20=0, "-", COUNTIFS('Base Lojas'!B:B, A20, 'Base Lojas'!I:I, ">500000")/D20) -> - | K20: - | L20: 0 | M20: 19242219 | N20: 145829 | O20: =_xlfn.XLOOKUP(A20,Cidades!A:A,Cidades!D:D) -> Entre 100k e 150k | P20: =_xlfn.XLOOKUP(A20,'[1]1° RAIZ'!$A:$A,'[1]1° RAIZ'!$AH:$AH) -> Paranaguá | Q20: =_xlfn.XLOOKUP(A20,'[1]1° RAIZ'!$A:$A,'[1]1° RAIZ'!$AE:$AE) -> Curitiba | R20: 2.8951945e-05 | S20: 0.008228996 | T20: 42 | U20: 9 | V20: 102167.39 | W20: 4.1460404 | X20: 1.4326877 | Y20: 0.24780078 | Z20: 0.33226947 | AA20: 0.68375401 | AB20: =IF(B20="Capão do Leão","Erro IBGE", IF(AND(U20<=0,M20<=2000000),"Mercado insuficiente", IF(U20<=0,"Limite de expansão", IF(K20<500000,"Performance", IF(M20<=2000000,"Mercado insuficiente","Expansão") ) ) ) ) -> Expansão | AC20: =IF(P20=B20,"Oportunidade","Validar") -> Oportunidade
A21: 410420 | B21: Campo Largo | C21: PR | D21: 1 | E21: =COUNTIFS('Contratos assinados '!F:F,'Direcional Expansão'!B21,'Contratos assinados '!J:J, "Assinado por ambos") -> 0 | F21: =COUNTIFS('Contratos assinados '!F:F,'Direcional Expansão'!B21,'Contratos assinados '!J:J,"Aquisição") -> 0 | G21: =COUNTIFS('Contratos assinados '!F:F,'Direcional Expansão'!B21,'Contratos assinados '!J:J,"Ampliação") -> 0 | H21: =COUNTIFS('Contratos assinados '!F:F,'Direcional Expansão'!B21,'Contratos assinados '!J:J,"Assinado por proprietário") -> 0 | I21: =SUM(E21:H21) -> 0 | J21: =IF(D21=0, "-", COUNTIFS('Base Lojas'!B:B, A21, 'Base Lojas'!G:G, ">500000")/D21) -> 0 | K21: 301953.03 | L21: 0.015641302 | M21: 19304852 | N21: 136327 | O21: =_xlfn.XLOOKUP(A21,Cidades!A:A,Cidades!D:D) -> Entre 100k e 150k | P21: =_xlfn.XLOOKUP(A21,'[1]1° RAIZ'!$A:$A,'[1]1° RAIZ'!$AH:$AH) -> Curitiba | Q21: =_xlfn.XLOOKUP(A21,'[1]1° RAIZ'!$A:$A,'[1]1° RAIZ'!$AE:$AE) -> Curitiba | R21: 0.00014896606 | S21: 0.01998374 | T21: 43 | U21: 9 | V21: 44646.152 | W21: 3.8373474 | X21: 1.3776875 | Y21: -0.16186841 | Z21: -0.828746 | AA21: 0.46881749 | AB21: =IF(B21="Capão do Leão","Erro IBGE", IF(AND(U21<=0,M21<=2000000),"Mercado insuficiente", IF(U21<=0,"Limite de expansão", IF(K21<500000,"Performance", IF(M21<=2000000,"Mercado insuficiente","Expansão") ) ) ) ) -> Performance | AC21: =IF(P21=B21,"Oportunidade","Validar") -> Validar
A22: 410830 | B22: Foz do Iguaçu | C22: PR | D22: 10 | E22: =COUNTIFS('Contratos assinados '!F:F,'Direcional Expansão'!B22,'Contratos assinados '!J:J, "Assinado por ambos") -> 0 | F22: =COUNTIFS('Contratos assinados '!F:F,'Direcional Expansão'!B22,'Contratos assinados '!J:J,"Aquisição") -> 0 | G22: =COUNTIFS('Contratos assinados '!F:F,'Direcional Expansão'!B22,'Contratos assinados '!J:J,"Ampliação") -> 0 | H22: =COUNTIFS('Contratos assinados '!F:F,'Direcional Expansão'!B22,'Contratos assinados '!J:J,"Assinado por proprietário") -> 0 | I22: =SUM(E22:H22) -> 0 | J22: =IF(D22=0, "-", COUNTIFS('Base Lojas'!B:B, A22, 'Base Lojas'!G:G, ">500000")/D22) -> 0.3 | K22: 452232.31 | L22: 0.11863706 | M22: 38118976 | N22: 285415 | O22: =_xlfn.XLOOKUP(A22,Cidades!A:A,Cidades!D:D) -> Maior que 200k | P22: =_xlfn.XLOOKUP(A22,'[1]1° RAIZ'!$A:$A,'[1]1° RAIZ'!$AH:$AH) -> Foz do Iguaçu | Q22: =_xlfn.XLOOKUP(A22,'[1]1° RAIZ'!$A:$A,'[1]1° RAIZ'!$AE:$AE) -> Cascavel | R22: 8.3772374e-05 | S22: 0.012008413 | T22: 145 | U22: 8 | V22: 71722.668 | W22: 4.2109551 | X22: 2.9407416 | Y22: -0.18157163 | Z22: 0.22555935 | AA22: 1.2520177 | AB22: =IF(B22="Capão do Leão","Erro IBGE", IF(AND(U22<=0,M22<=2000000),"Mercado insuficiente", IF(U22<=0,"Limite de expansão", IF(K22<500000,"Performance", IF(M22<=2000000,"Mercado insuficiente","Expansão") ) ) ) ) -> Performance | AC22: =IF(P22=B22,"Oportunidade","Validar") -> Oportunidade
A23: 410765 | B23: Fazenda Rio Grande | C23: PR | D23: 1 | E23: =COUNTIFS('Contratos assinados '!F:F,'Direcional Expansão'!B23,'Contratos assinados '!J:J, "Assinado por ambos") -> 0 | F23: =COUNTIFS('Contratos assinados '!F:F,'Direcional Expansão'!B23,'Contratos assinados '!J:J,"Aquisição") -> 0 | G23: =COUNTIFS('Contratos assinados '!F:F,'Direcional Expansão'!B23,'Contratos assinados '!J:J,"Ampliação") -> 0 | H23: =COUNTIFS('Contratos assinados '!F:F,'Direcional Expansão'!B23,'Contratos assinados '!J:J,"Assinado por proprietário") -> 0 | I23: =SUM(E23:H23) -> 0 | J23: =IF(D23=0, "-", COUNTIFS('Base Lojas'!B:B, A23, 'Base Lojas'!G:G, ">500000")/D23) -> 0 | K23: 335285.31 | L23: 0.018299132 | M23: 18322470 | N23: 148873 | O23: =_xlfn.XLOOKUP(A23,Cidades!A:A,Cidades!D:D) -> Entre 100k e 150k | P23: =_xlfn.XLOOKUP(A23,'[1]1° RAIZ'!$A:$A,'[1]1° RAIZ'!$AH:$AH) -> Curitiba | Q23: =_xlfn.XLOOKUP(A23,'[1]1° RAIZ'!$A:$A,'[1]1° RAIZ'!$AE:$AE) -> Curitiba | R23: 0.0004725152 | S23: 0.049679155 | T23: 55 | U23: 8 | V23: 22385.599 | W23: 3.6620235 | X23: 1.4618287 | Y23: 0.28013873 | Z23: -1.9088332 | AA23: 0.44496718 | AB23: =IF(B23="Capão do Leão","Erro IBGE", IF(AND(U23<=0,M23<=2000000),"Mercado insuficiente", IF(U23<=0,"Limite de expansão", IF(K23<500000,"Performance", IF(M23<=2000000,"Mercado insuficiente","Expansão") ) ) ) ) -> Performance | AC23: =IF(P23=B23,"Oportunidade","Validar") -> Validar
A24: 420460 | B24: Criciúma | C24: SC | D24: 7 | E24: =COUNTIFS('Contratos assinados '!F:F,'Direcional Expansão'!B24,'Contratos assinados '!J:J, "Assinado por ambos") -> 1 | F24: =COUNTIFS('Contratos assinados '!F:F,'Direcional Expansão'!B24,'Contratos assinados '!J:J,"Aquisição") -> 0 | G24: =COUNTIFS('Contratos assinados '!F:F,'Direcional Expansão'!B24,'Contratos assinados '!J:J,"Ampliação") -> 0 | H24: =COUNTIFS('Contratos assinados '!F:F,'Direcional Expansão'!B24,'Contratos assinados '!J:J,"Assinado por proprietário") -> 0 | I24: =SUM(E24:H24) -> 1 | J24: =IF(D24=0, "-", COUNTIFS('Base Lojas'!B:B, A24, 'Base Lojas'!G:G, ">500000")/D24) -> 0.42857143 | K24: 444973.28 | L24: 0.086056193 | M24: 36195105 | N24: 214493 | O24: =_xlfn.XLOOKUP(A24,Cidades!A:A,Cidades!D:D) -> Maior que 200k | P24: =_xlfn.XLOOKUP(A24,'[1]1° RAIZ'!$A:$A,'[1]1° RAIZ'!$AH:$AH) -> Criciúma | Q24: =_xlfn.XLOOKUP(A24,'[1]1° RAIZ'!$A:$A,'[1]1° RAIZ'!$AE:$AE) -> Criciúma | R24: 8.4627871e-05 | S24: 0.011365324 | T24: 115 | U24: 7 | V24: 49553.49 | W24: 5.1604455 | X24: 2.5032418 | Y24: 0.20832849 | Z24: -0.22901546 | AA24: 1.0699215 | AB24: =IF(B24="Capão do Leão","Erro IBGE", IF(AND(U24<=0,M24<=2000000),"Mercado insuficiente", IF(U24<=0,"Limite de expansão", IF(K24<500000,"Performance", IF(M24<=2000000,"Mercado insuficiente","Expansão") ) ) ) ) -> Performance | AC24: =IF(P24=B24,"Oportunidade","Validar") -> Oportunidade
A25: 411915 | B25: Pinhais | C25: PR | D25: 1 | E25: =COUNTIFS('Contratos assinados '!F:F,'Direcional Expansão'!B25,'Contratos assinados '!J:J, "Assinado por ambos") -> 0 | F25: =COUNTIFS('Contratos assinados '!F:F,'Direcional Expansão'!B25,'Contratos assinados '!J:J,"Aquisição") -> 0 | G25: =COUNTIFS('Contratos assinados '!F:F,'Direcional Expansão'!B25,'Contratos assinados '!J:J,"Ampliação") -> 0 | H25: =COUNTIFS('Contratos assinados '!F:F,'Direcional Expansão'!B25,'Contratos assinados '!J:J,"Assinado por proprietário") -> 0 | I25: =SUM(E25:H25) -> 0 | J25: =IF(D25=0, "-", COUNTIFS('Base Lojas'!B:B, A25, 'Base Lojas'!G:G, ">500000")/D25) -> 0 | K25: 294273.62 | L25: 0.016034958 | M25: 18352005 | N25: 127019 | O25: =_xlfn.XLOOKUP(A25,Cidades!A:A,Cidades!D:D) -> Entre 100k e 150k | P25: =_xlfn.XLOOKUP(A25,'[1]1° RAIZ'!$A:$A,'[1]1° RAIZ'!$AH:$AH) -> Curitiba | Q25: =_xlfn.XLOOKUP(A25,'[1]1° RAIZ'!$A:$A,'[1]1° RAIZ'!$AE:$AE) -> Curitiba | R25: 6.2304791e-05 | S25: 0.012242356 | T25: 48 | U25: 7 | V25: 67892.111 | W25: 4.5990474 | X25: 1.349847 | Y25: 0.31558757 | Z25: -0.20687327 | AA25: 0.59668061 | AB25: =IF(B25="Capão do Leão","Erro IBGE", IF(AND(U25<=0,M25<=2000000),"Mercado insuficiente", IF(U25<=0,"Limite de expansão", IF(K25<500000,"Performance", IF(M25<=2000000,"Mercado insuficiente","Expansão") ) ) ) ) -> Performance | AC25: =IF(P25=B25,"Oportunidade","Validar") -> Validar
A26: 430060 | B26: Alvorada | C26: RS | D26: 5 | E26: =COUNTIFS('Contratos assinados '!F:F,'Direcional Expansão'!B26,'Contratos assinados '!J:J, "Assinado por ambos") -> 0 | F26: =COUNTIFS('Contratos assinados '!F:F,'Direcional Expansão'!B26,'Contratos assinados '!J:J,"Aquisição") -> 0 | G26: =COUNTIFS('Contratos assinados '!F:F,'Direcional Expansão'!B26,'Contratos assinados '!J:J,"Ampliação") -> 0 | H26: =COUNTIFS('Contratos assinados '!F:F,'Direcional Expansão'!B26,'Contratos assinados '!J:J,"Assinado por proprietário") -> 0 | I26: =SUM(E26:H26) -> 0 | J26: =IF(D26=0, "-", COUNTIFS('Base Lojas'!B:B, A26, 'Base Lojas'!G:G, ">500000")/D26) -> 0.4 | K26: 490164.9 | L26: 0.07999 | M26: 30639136 | N26: 187315 | O26: =_xlfn.XLOOKUP(A26,Cidades!A:A,Cidades!D:D) -> Entre 150k e 200k | P26: =_xlfn.XLOOKUP(A26,'[1]1° RAIZ'!$A:$A,'[1]1° RAIZ'!$AH:$AH) -> Porto Alegre | Q26: =_xlfn.XLOOKUP(A26,'[1]1° RAIZ'!$A:$A,'[1]1° RAIZ'!$AE:$AE) -> Porto Alegre | R26: -3.3699364e-05 | S26: 0.0017537069 | T26: 55 | U26: 7 | V26: 18997.492 | W26: 3.064344 | X26: 1.5643552 | Y26: -1.216041 | Z26: -0.51207539 | AA26: 0.43273097 | AB26: =IF(B26="Capão do Leão","Erro IBGE", IF(AND(U26<=0,M26<=2000000),"Mercado insuficiente", IF(U26<=0,"Limite de expansão", IF(K26<500000,"Performance", IF(M26<=2000000,"Mercado insuficiente","Expansão") ) ) ) ) -> Performance | AC26: =IF(P26=B26,"Oportunidade","Validar") -> Validar
A27: 410040 | B27: Almirante Tamandaré | C27: PR | D27: 0 | E27: =COUNTIFS('Contratos assinados '!F:F,'Direcional Expansão'!B27,'Contratos assinados '!J:J, "Assinado por ambos") -> 0 | F27: =COUNTIFS('Contratos assinados '!F:F,'Direcional Expansão'!B27,'Contratos assinados '!J:J,"Aquisição") -> 0 | G27: =COUNTIFS('Contratos assinados '!F:F,'Direcional Expansão'!B27,'Contratos assinados '!J:J,"Ampliação") -> 0 | H27: =COUNTIFS('Contratos assinados '!F:F,'Direcional Expansão'!B27,'Contratos assinados '!J:J,"Assinado por proprietário") -> 0 | I27: =SUM(E27:H27) -> 0 | J27: =IF(D27=0, "-", COUNTIFS('Base Lojas'!B:B, A27, 'Base Lojas'!I:I, ">500000")/D27) -> - | K27: - | L27: 0 | M27: 15513832 | N27: 119825 | O27: =_xlfn.XLOOKUP(A27,Cidades!A:A,Cidades!D:D) -> Entre 100k e 150k | P27: =_xlfn.XLOOKUP(A27,'[1]1° RAIZ'!$A:$A,'[1]1° RAIZ'!$AH:$AH) -> Curitiba | Q27: =_xlfn.XLOOKUP(A27,'[1]1° RAIZ'!$A:$A,'[1]1° RAIZ'!$AE:$AE) -> Curitiba | R27: 0.00011521836 | S27: 0.015322248 | T27: 24 | U27: 7 | V27: 17286.061 | W27: 3.436899 | X27: 0.936455 | Y27: -0.60054971 | Z27: -1.2010642 | AA27: 0.17525693 | AB27: =IF(B27="Capão do Leão","Erro IBGE", IF(AND(U27<=0,M27<=2000000),"Mercado insuficiente", IF(U27<=0,"Limite de expansão", IF(K27<500000,"Performance", IF(M27<=2000000,"Mercado insuficiente","Expansão") ) ) ) ) -> Expansão | AC27: =IF(P27=B27,"Oportunidade","Validar") -> Validar
A28: 411950 | B28: Piraquara | C28: PR | D28: 0 | E28: =COUNTIFS('Contratos assinados '!F:F,'Direcional Expansão'!B28,'Contratos assinados '!J:J, "Assinado por ambos") -> 0 | F28: =COUNTIFS('Contratos assinados '!F:F,'Direcional Expansão'!B28,'Contratos assinados '!J:J,"Aquisição") -> 0 | G28: =COUNTIFS('Contratos assinados '!F:F,'Direcional Expansão'!B28,'Contratos assinados '!J:J,"Ampliação") -> 0 | H28: =COUNTIFS('Contratos assinados '!F:F,'Direcional Expansão'!B28,'Contratos assinados '!J:J,"Assinado por proprietário") -> 0 | I28: =SUM(E28:H28) -> 0 | J28: =IF(D28=0, "-", COUNTIFS('Base Lojas'!B:B, A28, 'Base Lojas'!I:I, ">500000")/D28) -> - | K28: - | L28: 0 | M28: 13534010 | N28: 118730 | O28: =_xlfn.XLOOKUP(A28,Cidades!A:A,Cidades!D:D) -> Entre 100k e 150k | P28: =_xlfn.XLOOKUP(A28,'[1]1° RAIZ'!$A:$A,'[1]1° RAIZ'!$AH:$AH) -> Curitiba | Q28: =_xlfn.XLOOKUP(A28,'[1]1° RAIZ'!$A:$A,'[1]1° RAIZ'!$AE:$AE) -> Curitiba | R28: 0.00018731505 | S28: 0.021167385 | T28: 30 | U28: 7 | V28: 13696.242 | W28: 3.0673407 | X28: 0.91408895 | Y28: -0.66560603 | Z28: -1.4283861 | AA28: 0.13041566 | AB28: =IF(B28="Capão do Leão","Erro IBGE", IF(AND(U28<=0,M28<=2000000),"Mercado insuficiente", IF(U28<=0,"Limite de expansão", IF(K28<500000,"Performance", IF(M28<=2000000,"Mercado insuficiente","Expansão") ) ) ) ) -> Expansão | AC28: =IF(P28=B28,"Oportunidade","Validar") -> Validar
A29: 412770 | B29: Toledo | C29: PR | D29: 4 | E29: =COUNTIFS('Contratos assinados '!F:F,'Direcional Expansão'!B29,'Contratos assinados '!J:J, "Assinado por ambos") -> 0 | F29: =COUNTIFS('Contratos assinados '!F:F,'Direcional Expansão'!B29,'Contratos assinados '!J:J,"Aquisição") -> 0 | G29: =COUNTIFS('Contratos assinados '!F:F,'Direcional Expansão'!B29,'Contratos assinados '!J:J,"Ampliação") -> 0 | H29: =COUNTIFS('Contratos assinados '!F:F,'Direcional Expansão'!B29,'Contratos assinados '!J:J,"Assinado por proprietário") -> 0 | I29: =SUM(E29:H29) -> 0 | J29: =IF(D29=0, "-", COUNTIFS('Base Lojas'!B:B, A29, 'Base Lojas'!I:I, ">500000")/D29) -> 0.75 | K29: 716649.98 | L29: 0.1224696 | M29: 23406623 | N29: 150470 | O29: =_xlfn.XLOOKUP(A29,Cidades!A:A,Cidades!D:D) -> Entre 150k e 200k | P29: =_xlfn.XLOOKUP(A29,'[1]1° RAIZ'!$A:$A,'[1]1° RAIZ'!$AH:$AH) -> Toledo | Q29: =_xlfn.XLOOKUP(A29,'[1]1° RAIZ'!$A:$A,'[1]1° RAIZ'!$AE:$AE) -> Cascavel | R29: 0.00017981152 | S29: 0.020328581 | T29: 79 | U29: 6 | V29: 52230.744 | W29: 4.2036522 | X29: 1.6689317 | Y29: 0.2588927 | Z29: -0.31793843 | AA29: 0.71173209 | AB29: =IF(B29="Capão do Leão","Erro IBGE", IF(AND(U29<=0,M29<=2000000),"Mercado insuficiente", IF(U29<=0,"Limite de expansão", IF(K29<500000,"Performance", IF(M29<=2000000,"Mercado insuficiente","Expansão") ) ) ) ) -> Expansão | AC29: =IF(P29=B29,"Oportunidade","Validar") -> Oportunidade
A30: 421870 | B30: Tubarão | C30: SC | D30: 1 | E30: =COUNTIFS('Contratos assinados '!F:F,'Direcional Expansão'!B30,'Contratos assinados '!J:J, "Assinado por ambos") -> 0 | F30: =COUNTIFS('Contratos assinados '!F:F,'Direcional Expansão'!B30,'Contratos assinados '!J:J,"Aquisição") -> 0 | G30: =COUNTIFS('Contratos assinados '!F:F,'Direcional Expansão'!B30,'Contratos assinados '!J:J,"Ampliação") -> 0 | H30: =COUNTIFS('Contratos assinados '!F:F,'Direcional Expansão'!B30,'Contratos assinados '!J:J,"Assinado por proprietário") -> 0 | I30: =SUM(E30:H30) -> 0 | J30: =IF(D30=0, "-", COUNTIFS('Base Lojas'!B:B, A30, 'Base Lojas'!G:G, ">500000")/D30) -> 0 | K30: 205659.28 | L30: 0.0097120071 | M30: 21175775 | N30: 110088 | O30: =_xlfn.XLOOKUP(A30,Cidades!A:A,Cidades!D:D) -> Entre 100k e 150k | P30: =_xlfn.XLOOKUP(A30,'[1]1° RAIZ'!$A:$A,'[1]1° RAIZ'!$AH:$AH) -> Tubarão | Q30: =_xlfn.XLOOKUP(A30,'[1]1° RAIZ'!$A:$A,'[1]1° RAIZ'!$AE:$AE) -> Criciúma | R30: 9.5589631e-05 | S30: 0.012052181 | T30: 66 | U30: 6 | V30: 46288.18 | W30: 5.0774551 | X30: 1.4827911 | Y30: 0.37417524 | Z30: -0.599389 | AA30: 0.61692088 | AB30: =IF(B30="Capão do Leão","Erro IBGE", IF(AND(U30<=0,M30<=2000000),"Mercado insuficiente", IF(U30<=0,"Limite de expansão", IF(K30<500000,"Performance", IF(M30<=2000000,"Mercado insuficiente","Expansão") ) ) ) ) -> Performance | AC30: =IF(P30=B30,"Oportunidade","Validar") -> Oportunidade
A31: 411850 | B31: Pato Branco | C31: PR | D31: 0 | E31: =COUNTIFS('Contratos assinados '!F:F,'Direcional Expansão'!B31,'Contratos assinados '!J:J, "Assinado por ambos") -> 0 | F31: =COUNTIFS('Contratos assinados '!F:F,'Direcional Expansão'!B31,'Contratos assinados '!J:J,"Aquisição") -> 0 | G31: =COUNTIFS('Contratos assinados '!F:F,'Direcional Expansão'!B31,'Contratos assinados '!J:J,"Ampliação") -> 0 | H31: =COUNTIFS('Contratos assinados '!F:F,'Direcional Expansão'!B31,'Contratos assinados '!J:J,"Assinado por proprietário") -> 0 | I31: =SUM(E31:H31) -> 0 | J31: =IF(D31=0, "-", COUNTIFS('Base Lojas'!B:B, A31, 'Base Lojas'!I:I, ">500000")/D31) -> - | K31: - | L31: 0 | M31: 14520214 | N31: 91836 | O31: =_xlfn.XLOOKUP(A31,Cidades!A:A,Cidades!D:D) -> Entre 50k e 100k | P31: =_xlfn.XLOOKUP(A31,'[1]1° RAIZ'!$A:$A,'[1]1° RAIZ'!$AH:$AH) -> Pato Branco | Q31: =_xlfn.XLOOKUP(A31,'[1]1° RAIZ'!$A:$A,'[1]1° RAIZ'!$AE:$AE) -> Cascavel | R31: 0.00018489708 | S31: 0.0217162 | T31: 39 | U31: 6 | V31: 52187.733 | W31: 4.8692033 | X31: 1.0990737 | Y31: 0.64686753 | Z31: -0.77770716 | AA31: 0.47239709 | AB31: =IF(B31="Capão do Leão","Erro IBGE", IF(AND(U31<=0,M31<=2000000),"Mercado insuficiente", IF(U31<=0,"Limite de expansão", IF(K31<500000,"Performance", IF(M31<=2000000,"Mercado insuficiente","Expansão") ) ) ) ) -> Expansão | AC31: =IF(P31=B31,"Oportunidade","Validar") -> Oportunidade
A32: 420290 | B32: Brusque | C32: SC | D32: 4 | E32: =COUNTIFS('Contratos assinados '!F:F,'Direcional Expansão'!B32,'Contratos assinados '!J:J, "Assinado por ambos") -> 0 | F32: =COUNTIFS('Contratos assinados '!F:F,'Direcional Expansão'!B32,'Contratos assinados '!J:J,"Aquisição") -> 0 | G32: =COUNTIFS('Contratos assinados '!F:F,'Direcional Expansão'!B32,'Contratos assinados '!J:J,"Ampliação") -> 0 | H32: =COUNTIFS('Contratos assinados '!F:F,'Direcional Expansão'!B32,'Contratos assinados '!J:J,"Assinado por proprietário") -> 0 | I32: =SUM(E32:H32) -> 0 | J32: =IF(D32=0, "-", COUNTIFS('Base Lojas'!B:B, A32, 'Base Lojas'!G:G, ">500000")/D32) -> 0 | K32: 328465.1 | L32: 0.049682323 | M32: 26445229 | N32: 141385 | O32: =_xlfn.XLOOKUP(A32,Cidades!A:A,Cidades!D:D) -> Entre 100k e 150k | P32: =_xlfn.XLOOKUP(A32,'[1]1° RAIZ'!$A:$A,'[1]1° RAIZ'!$AH:$AH) -> Brusque | Q32: =_xlfn.XLOOKUP(A32,'[1]1° RAIZ'!$A:$A,'[1]1° RAIZ'!$AE:$AE) -> Blumenau | R32: 0.00022780454 | S32: 0.022209263 | T32: 61 | U32: 5 | V32: 62954.384 | W32: 5.524978 | X32: 1.6498962 | Y32: 1.0920018 | Z32: -0.44529381 | AA32: 0.80900299 | AB32: =IF(B32="Capão do Leão","Erro IBGE", IF(AND(U32<=0,M32<=2000000),"Mercado insuficiente", IF(U32<=0,"Limite de expansão", IF(K32<500000,"Performance", IF(M32<=2000000,"Mercado insuficiente","Expansão") ) ) ) ) -> Performance | AC32: =IF(P32=B32,"Oportunidade","Validar") -> Oportunidade
A33: 420930 | B33: Lages | C33: SC | D33: 5 | E33: =COUNTIFS('Contratos assinados '!F:F,'Direcional Expansão'!B33,'Contratos assinados '!J:J, "Assinado por ambos") -> 0 | F33: =COUNTIFS('Contratos assinados '!F:F,'Direcional Expansão'!B33,'Contratos assinados '!J:J,"Aquisição") -> 0 | G33: =COUNTIFS('Contratos assinados '!F:F,'Direcional Expansão'!B33,'Contratos assinados '!J:J,"Ampliação") -> 0 | H33: =COUNTIFS('Contratos assinados '!F:F,'Direcional Expansão'!B33,'Contratos assinados '!J:J,"Assinado por proprietário") -> 0 | I33: =SUM(E33:H33) -> 0 | J33: =IF(D33=0, "-", COUNTIFS('Base Lojas'!B:B, A33, 'Base Lojas'!G:G, ">500000")/D33) -> 0.4 | K33: 490487.46 | L33: 0.091539245 | M33: 26791103 | N33: 164981 | O33: =_xlfn.XLOOKUP(A33,Cidades!A:A,Cidades!D:D) -> Entre 150k e 200k | P33: =_xlfn.XLOOKUP(A33,'[1]1° RAIZ'!$A:$A,'[1]1° RAIZ'!$AH:$AH) -> Lages | Q33: =_xlfn.XLOOKUP(A33,'[1]1° RAIZ'!$A:$A,'[1]1° RAIZ'!$AE:$AE) -> Lages | R33: 3.950944e-05 | S33: 0.0075488934 | T33: 115 | U33: 5 | V33: 42716.182 | W33: 4.3835907 | X33: 1.987601 | Y33: -0.18906524 | Z33: -0.21258802 | AA33: 0.79499537 | AB33: =IF(B33="Capão do Leão","Erro IBGE", IF(AND(U33<=0,M33<=2000000),"Mercado insuficiente", IF(U33<=0,"Limite de expansão", IF(K33<500000,"Performance", IF(M33<=2000000,"Mercado insuficiente","Expansão") ) ) ) ) -> Performance | AC33: =IF(P33=B33,"Oportunidade","Validar") -> Oportunidade
A34: 412710 | B34: Telêmaco Borba | C34: PR | D34: 0 | E34: =COUNTIFS('Contratos assinados '!F:F,'Direcional Expansão'!B34,'Contratos assinados '!J:J, "Assinado por ambos") -> 0 | F34: =COUNTIFS('Contratos assinados '!F:F,'Direcional Expansão'!B34,'Contratos assinados '!J:J,"Aquisição") -> 0 | G34: =COUNTIFS('Contratos assinados '!F:F,'Direcional Expansão'!B34,'Contratos assinados '!J:J,"Ampliação") -> 0 | H34: =COUNTIFS('Contratos assinados '!F:F,'Direcional Expansão'!B34,'Contratos assinados '!J:J,"Assinado por proprietário") -> 0 | I34: =SUM(E34:H34) -> 0 | J34: =IF(D34=0, "-", COUNTIFS('Base Lojas'!B:B, A34, 'Base Lojas'!I:I, ">500000")/D34) -> - | K34: - | L34: 0 | M34: 9914555.7 | N34: 75042 | O34: =_xlfn.XLOOKUP(A34,Cidades!A:A,Cidades!D:D) -> Entre 50k e 100k | P34: =_xlfn.XLOOKUP(A34,'[1]1° RAIZ'!$A:$A,'[1]1° RAIZ'!$AH:$AH) -> Telêmaco Borba | Q34: =_xlfn.XLOOKUP(A34,'[1]1° RAIZ'!$A:$A,'[1]1° RAIZ'!$AE:$AE) -> Ponta Grossa | R34: 5.4994585e-05 | S34: 0.009125936 | T34: 30 | U34: 5 | V34: 71362.289 | W34: 3.6791284 | X34: 0.68350388 | Y34: 0.024108936 | Z34: -0.16464125 | AA34: 0.27576468 | AB34: =IF(B34="Capão do Leão","Erro IBGE", IF(AND(U34<=0,M34<=2000000),"Mercado insuficiente", IF(U34<=0,"Limite de expansão", IF(K34<500000,"Performance", IF(M34<=2000000,"Mercado insuficiente","Expansão") ) ) ) ) -> Expansão | AC34: =IF(P34=B34,"Oportunidade","Validar") -> Oportunidade
A35: 420200 | B35: Balneário Camboriú | C35: SC | D35: 5 | E35: =COUNTIFS('Contratos assinados '!F:F,'Direcional Expansão'!B35,'Contratos assinados '!J:J, "Assinado por ambos") -> 1 | F35: =COUNTIFS('Contratos assinados '!F:F,'Direcional Expansão'!B35,'Contratos assinados '!J:J,"Aquisição") -> 0 | G35: =COUNTIFS('Contratos assinados '!F:F,'Direcional Expansão'!B35,'Contratos assinados '!J:J,"Ampliação") -> 1 | H35: =COUNTIFS('Contratos assinados '!F:F,'Direcional Expansão'!B35,'Contratos assinados '!J:J,"Assinado por proprietário") -> 0 | I35: =SUM(E35:H35) -> 2 | J35: =IF(D35=0, "-", COUNTIFS('Base Lojas'!B:B, A35, 'Base Lojas'!I:I, ">500000")/D35) -> 0.4 | K35: 806616.68 | L35: 0.11471087 | M35: 35158687 | N35: 139155 | O35: =_xlfn.XLOOKUP(A35,Cidades!A:A,Cidades!D:D) -> Entre 100k e 150k | P35: =_xlfn.XLOOKUP(A35,'[1]1° RAIZ'!$A:$A,'[1]1° RAIZ'!$AH:$AH) -> Itajaí | Q35: =_xlfn.XLOOKUP(A35,'[1]1° RAIZ'!$A:$A,'[1]1° RAIZ'!$AE:$AE) -> Blumenau | R35: 0.00019610339 | S35: 0.019889433 | T35: 65 | U35: 4 | V35: 54378.59 | W35: 6.9553493 | X35: 1.9334723 | Y35: 1.7233716 | Z35: -0.24266623 | AA35: 1.0437839 | AB35: =IF(B35="Capão do Leão","Erro IBGE", IF(AND(U35<=0,M35<=2000000),"Mercado insuficiente", IF(U35<=0,"Limite de expansão", IF(K35<500000,"Performance", IF(M35<=2000000,"Mercado insuficiente","Expansão") ) ) ) ) -> Expansão | AC35: =IF(P35=B35,"Oportunidade","Validar") -> Validar
A36: 432300 | B36: Viamão | C36: RS | D36: 10 | E36: =COUNTIFS('Contratos assinados '!F:F,'Direcional Expansão'!B36,'Contratos assinados '!J:J, "Assinado por ambos") -> 0 | F36: =COUNTIFS('Contratos assinados '!F:F,'Direcional Expansão'!B36,'Contratos assinados '!J:J,"Aquisição") -> 0 | G36: =COUNTIFS('Contratos assinados '!F:F,'Direcional Expansão'!B36,'Contratos assinados '!J:J,"Ampliação") -> 0 | H36: =COUNTIFS('Contratos assinados '!F:F,'Direcional Expansão'!B36,'Contratos assinados '!J:J,"Assinado por proprietário") -> 0 | I36: =SUM(E36:H36) -> 0 | J36: =IF(D36=0, "-", COUNTIFS('Base Lojas'!B:B, A36, 'Base Lojas'!I:I, ">500000")/D36) -> 0.7 | K36: 570796.94 | L36: 0.15236613 | M36: 37462192 | N36: 224116 | O36: =_xlfn.XLOOKUP(A36,Cidades!A:A,Cidades!D:D) -> Maior que 200k | P36: =_xlfn.XLOOKUP(A36,'[1]1° RAIZ'!$A:$A,'[1]1° RAIZ'!$AH:$AH) -> Porto Alegre | Q36: =_xlfn.XLOOKUP(A36,'[1]1° RAIZ'!$A:$A,'[1]1° RAIZ'!$AE:$AE) -> Porto Alegre | R36: -5.0088274e-05 | S36: 0.00022813512 | T36: 70 | U36: 4 | V36: 20862.851 | W36: 3.515079 | X36: 1.7963636 | Y36: -0.92158162 | Z36: -0.1053324 | AA36: 0.6203581 | AB36: =IF(B36="Capão do Leão","Erro IBGE", IF(AND(U36<=0,M36<=2000000),"Mercado insuficiente", IF(U36<=0,"Limite de expansão", IF(K36<500000,"Performance", IF(M36<=2000000,"Mercado insuficiente","Expansão") ) ) ) ) -> Expansão | AC36: =IF(P36=B36,"Oportunidade","Validar") -> Validar
A37: 421480 | B37: Rio do Sul | C37: SC | D37: 0 | E37: =COUNTIFS('Contratos assinados '!F:F,'Direcional Expansão'!B37,'Contratos assinados '!J:J, "Assinado por ambos") -> 0 | F37: =COUNTIFS('Contratos assinados '!F:F,'Direcional Expansão'!B37,'Contratos assinados '!J:J,"Aquisição") -> 0 | G37: =COUNTIFS('Contratos assinados '!F:F,'Direcional Expansão'!B37,'Contratos assinados '!J:J,"Ampliação") -> 0 | H37: =COUNTIFS('Contratos assinados '!F:F,'Direcional Expansão'!B37,'Contratos assinados '!J:J,"Assinado por proprietário") -> 0 | I37: =SUM(E37:H37) -> 0 | J37: =IF(D37=0, "-", COUNTIFS('Base Lojas'!B:B, A37, 'Base Lojas'!I:I, ">500000")/D37) -> - | K37: - | L37: 0 | M37: 15402738 | N37: 72587 | O37: =_xlfn.XLOOKUP(A37,Cidades!A:A,Cidades!D:D) -> Entre 50k e 100k | P37: =_xlfn.XLOOKUP(A37,'[1]1° RAIZ'!$A:$A,'[1]1° RAIZ'!$AH:$AH) -> Rio do Sul | Q37: =_xlfn.XLOOKUP(A37,'[1]1° RAIZ'!$A:$A,'[1]1° RAIZ'!$AE:$AE) -> Blumenau | R37: 0.00013217669 | S37: 0.016087152 | T37: 42 | U37: 4 | V37: 53526.937 | W37: 5.3408019 | X37: 1.0136017 | Y37: 0.83875508 | Z37: -0.58173168 | AA37: 0.4859897 | AB37: =IF(B37="Capão do Leão","Erro IBGE", IF(AND(U37<=0,M37<=2000000),"Mercado insuficiente", IF(U37<=0,"Limite de expansão", IF(K37<500000,"Performance", IF(M37<=2000000,"Mercado insuficiente","Expansão") ) ) ) ) -> Expansão | AC37: =IF(P37=B37,"Oportunidade","Validar") -> Oportunidade
A38: 410430 | B38: Campo Mourão | C38: PR | D38: 2 | E38: =COUNTIFS('Contratos assinados '!F:F,'Direcional Expansão'!B38,'Contratos assinados '!J:J, "Assinado por ambos") -> 0 | F38: =COUNTIFS('Contratos assinados '!F:F,'Direcional Expansão'!B38,'Contratos assinados '!J:J,"Aquisição") -> 0 | G38: =COUNTIFS('Contratos assinados '!F:F,'Direcional Expansão'!B38,'Contratos assinados '!J:J,"Ampliação") -> 0 | H38: =COUNTIFS('Contratos assinados '!F:F,'Direcional Expansão'!B38,'Contratos assinados '!J:J,"Assinado por proprietário") -> 0 | I38: =SUM(E38:H38) -> 0 | J38: =IF(D38=0, "-", COUNTIFS('Base Lojas'!B:B, A38, 'Base Lojas'!I:I, ">500000")/D38) -> 0.5 | K38: 501535.03 | L38: 0.066502735 | M38: 15083140 | N38: 99432 | O38: =_xlfn.XLOOKUP(A38,Cidades!A:A,Cidades!D:D) -> Entre 50k e 100k | P38: =_xlfn.XLOOKUP(A38,'[1]1° RAIZ'!$A:$A,'[1]1° RAIZ'!$AH:$AH) -> Campo Mourão | Q38: =_xlfn.XLOOKUP(A38,'[1]1° RAIZ'!$A:$A,'[1]1° RAIZ'!$AE:$AE) -> Maringá | R38: 0.00010071336 | S38: 0.014473581 | T38: 43 | U38: 4 | V38: 55545.374 | W38: 4.0864536 | X38: 0.94905437 | Y38: 0.22828438 | Z38: -0.26698713 | AA38: 0.40656196 | AB38: =IF(B38="Capão do Leão","Erro IBGE", IF(AND(U38<=0,M38<=2000000),"Mercado insuficiente", IF(U38<=0,"Limite de expansão", IF(K38<500000,"Performance", IF(M38<=2000000,"Mercado insuficiente","Expansão") ) ) ) ) -> Expansão | AC38: =IF(P38=B38,"Oportunidade","Validar") -> Oportunidade
A39: 420590 | B39: Gaspar | C39: SC | D39: 0 | E39: =COUNTIFS('Contratos assinados '!F:F,'Direcional Expansão'!B39,'Contratos assinados '!J:J, "Assinado por ambos") -> 0 | F39: =COUNTIFS('Contratos assinados '!F:F,'Direcional Expansão'!B39,'Contratos assinados '!J:J,"Aquisição") -> 0 | G39: =COUNTIFS('Contratos assinados '!F:F,'Direcional Expansão'!B39,'Contratos assinados '!J:J,"Ampliação") -> 0 | H39: =COUNTIFS('Contratos assinados '!F:F,'Direcional Expansão'!B39,'Contratos assinados '!J:J,"Assinado por proprietário") -> 0 | I39: =SUM(E39:H39) -> 0 | J39: =IF(D39=0, "-", COUNTIFS('Base Lojas'!B:B, A39, 'Base Lojas'!I:I, ">500000")/D39) -> - | K39: - | L39: 0 | M39: 13722462 | N39: 72570 | O39: =_xlfn.XLOOKUP(A39,Cidades!A:A,Cidades!D:D) -> Entre 50k e 100k | P39: =_xlfn.XLOOKUP(A39,'[1]1° RAIZ'!$A:$A,'[1]1° RAIZ'!$AH:$AH) -> Blumenau | Q39: =_xlfn.XLOOKUP(A39,'[1]1° RAIZ'!$A:$A,'[1]1° RAIZ'!$AE:$AE) -> Blumenau | R39: 0.00017445268 | S39: 0.019226369 | T39: 30 | U39: 4 | V39: 59599.866 | W39: 4.8103239 | X39: 0.83352119 | Y39: 0.76046429 | Z39: -0.58562713 | AA39: 0.39758321 | AB39: =IF(B39="Capão do Leão","Erro IBGE", IF(AND(U39<=0,M39<=2000000),"Mercado insuficiente", IF(U39<=0,"Limite de expansão", IF(K39<500000,"Performance", IF(M39<=2000000,"Mercado insuficiente","Expansão") ) ) ) ) -> Expansão | AC39: =IF(P39=B39,"Oportunidade","Validar") -> Validar
A40: 421580 | B40: São Bento do Sul | C40: SC | D40: 1 | E40: =COUNTIFS('Contratos assinados '!F:F,'Direcional Expansão'!B40,'Contratos assinados '!J:J, "Assinado por ambos") -> 0 | F40: =COUNTIFS('Contratos assinados '!F:F,'Direcional Expansão'!B40,'Contratos assinados '!J:J,"Aquisição") -> 0 | G40: =COUNTIFS('Contratos assinados '!F:F,'Direcional Expansão'!B40,'Contratos assinados '!J:J,"Ampliação") -> 0 | H40: =COUNTIFS('Contratos assinados '!F:F,'Direcional Expansão'!B40,'Contratos assinados '!J:J,"Assinado por proprietário") -> 0 | I40: =SUM(E40:H40) -> 0 | J40: =IF(D40=0, "-", COUNTIFS('Base Lojas'!B:B, A40, 'Base Lojas'!I:I, ">500000")/D40) -> 1 | K40: 512968.37 | L40: 0.037645221 | M40: 13626387 | N40: 83275 | O40: =_xlfn.XLOOKUP(A40,Cidades!A:A,Cidades!D:D) -> Entre 50k e 100k | P40: =_xlfn.XLOOKUP(A40,'[1]1° RAIZ'!$A:$A,'[1]1° RAIZ'!$AH:$AH) -> São Bento do Sul - Rio Negrinho | Q40: =_xlfn.XLOOKUP(A40,'[1]1° RAIZ'!$A:$A,'[1]1° RAIZ'!$AE:$AE) -> Joinville | R40: 8.2934794e-05 | S40: 0.010469137 | T40: 29 | U40: 4 | V40: 60201.782 | W40: 4.5119363 | X40: 0.8119954 | Y40: 0.44217743 | Z40: -0.2334116 | AA40: 0.38281201 | AB40: =IF(B40="Capão do Leão","Erro IBGE", IF(AND(U40<=0,M40<=2000000),"Mercado insuficiente", IF(U40<=0,"Limite de expansão", IF(K40<500000,"Performance", IF(M40<=2000000,"Mercado insuficiente","Expansão") ) ) ) ) -> Expansão | AC40: =IF(P40=B40,"Oportunidade","Validar") -> Validar
A41: 420230 | B41: Biguaçu | C41: SC | D41: 1 | E41: =COUNTIFS('Contratos assinados '!F:F,'Direcional Expansão'!B41,'Contratos assinados '!J:J, "Assinado por ambos") -> 0 | F41: =COUNTIFS('Contratos assinados '!F:F,'Direcional Expansão'!B41,'Contratos assinados '!J:J,"Aquisição") -> 0 | G41: =COUNTIFS('Contratos assinados '!F:F,'Direcional Expansão'!B41,'Contratos assinados '!J:J,"Ampliação") -> 0 | H41: =COUNTIFS('Contratos assinados '!F:F,'Direcional Expansão'!B41,'Contratos assinados '!J:J,"Assinado por proprietário") -> 0 | I41: =SUM(E41:H41) -> 0 | J41: =IF(D41=0, "-", COUNTIFS('Base Lojas'!B:B, A41, 'Base Lojas'!I:I, ">500000")/D41) -> 1 | K41: 585500.34 | L41: 0.047204778 | M41: 12403413 | N41: 76773 | O41: =_xlfn.XLOOKUP(A41,Cidades!A:A,Cidades!D:D) -> Entre 50k e 100k | P41: =_xlfn.XLOOKUP(A41,'[1]1° RAIZ'!$A:$A,'[1]1° RAIZ'!$AH:$AH) -> Florianópolis | Q41: =_xlfn.XLOOKUP(A41,'[1]1° RAIZ'!$A:$A,'[1]1° RAIZ'!$AE:$AE) -> Florianópolis | R41: 0.00021482493 | S41: 0.024773486 | T41: 23 | U41: 4 | V41: 35795.643 | W41: 3.8421526 | X41: 0.65656665 | Y41: 0.23090534 | Z41: -0.92760609 | AA41: 0.20695604 | AB41: =IF(B41="Capão do Leão","Erro IBGE", IF(AND(U41<=0,M41<=2000000),"Mercado insuficiente", IF(U41<=0,"Limite de expansão", IF(K41<500000,"Performance", IF(M41<=2000000,"Mercado insuficiente","Expansão") ) ) ) ) -> Expansão | AC41: =IF(P41=B41,"Oportunidade","Validar") -> Validar
A42: 410490 | B42: Castro | C42: PR | D42: 0 | E42: =COUNTIFS('Contratos assinados '!F:F,'Direcional Expansão'!B42,'Contratos assinados '!J:J, "Assinado por ambos") -> 1 | F42: =COUNTIFS('Contratos assinados '!F:F,'Direcional Expansão'!B42,'Contratos assinados '!J:J,"Aquisição") -> 0 | G42: =COUNTIFS('Contratos assinados '!F:F,'Direcional Expansão'!B42,'Contratos assinados '!J:J,"Ampliação") -> 0 | H42: =COUNTIFS('Contratos assinados '!F:F,'Direcional Expansão'!B42,'Contratos assinados '!J:J,"Assinado por proprietário") -> 0 | I42: =SUM(E42:H42) -> 1 | J42: =IF(D42=0, "-", COUNTIFS('Base Lojas'!B:B, A42, 'Base Lojas'!I:I, ">500000")/D42) -> - | K42: - | L42: 0 | M42: 9100246.2 | N42: 73044 | O42: =_xlfn.XLOOKUP(A42,Cidades!A:A,Cidades!D:D) -> Entre 50k e 100k | P42: =_xlfn.XLOOKUP(A42,'[1]1° RAIZ'!$A:$A,'[1]1° RAIZ'!$AH:$AH) -> Ponta Grossa | Q42: =_xlfn.XLOOKUP(A42,'[1]1° RAIZ'!$A:$A,'[1]1° RAIZ'!$AE:$AE) -> Ponta Grossa | R42: 6.5712076e-05 | S42: 0.011488115 | T42: 25 | U42: 4 | V42: 54005.395 | W42: 3.407239 | X42: 0.53073304 | Y42: -0.19473098 | Z42: -0.46102892 | AA42: 0.14536638 | AB42: =IF(B42="Capão do Leão","Erro IBGE", IF(AND(U42<=0,M42<=2000000),"Mercado insuficiente", IF(U42<=0,"Limite de expansão", IF(K42<500000,"Performance", IF(M42<=2000000,"Mercado insuficiente","Expansão") ) ) ) ) -> Expansão | AC42: =IF(P42=B42,"Oportunidade","Validar") -> Validar
A43: 421620 | B43: São Francisco do Sul | C43: SC | D43: 0 | E43: =COUNTIFS('Contratos assinados '!F:F,'Direcional Expansão'!B43,'Contratos assinados '!J:J, "Assinado por ambos") -> 1 | F43: =COUNTIFS('Contratos assinados '!F:F,'Direcional Expansão'!B43,'Contratos assinados '!J:J,"Aquisição") -> 0 | G43: =COUNTIFS('Contratos assinados '!F:F,'Direcional Expansão'!B43,'Contratos assinados '!J:J,"Ampliação") -> 0 | H43: =COUNTIFS('Contratos assinados '!F:F,'Direcional Expansão'!B43,'Contratos assinados '!J:J,"Assinado por proprietário") -> 0 | I43: =SUM(E43:H43) -> 1 | J43: =IF(D43=0, "-", COUNTIFS('Base Lojas'!B:B, A43, 'Base Lojas'!I:I, ">500000")/D43) -> - | K43: - | L43: 0 | M43: 8252173.5 | N43: 52674 | O43: =_xlfn.XLOOKUP(A43,Cidades!A:A,Cidades!D:D) -> Entre 50k e 100k | P43: =_xlfn.XLOOKUP(A43,'[1]1° RAIZ'!$A:$A,'[1]1° RAIZ'!$AH:$AH) -> Joinville | Q43: =_xlfn.XLOOKUP(A43,'[1]1° RAIZ'!$A:$A,'[1]1° RAIZ'!$AE:$AE) -> Joinville | R43: 0.00016519242 | S43: 0.018520365 | T43: 23 | U43: 3 | V43: 168642.29 | W43: 3.9590918 | X43: 0.49924451 | Y43: 1.4797466 | Z43: 1.1822281 | AA43: 0.56057896 | AB43: =IF(B43="Capão do Leão","Erro IBGE", IF(AND(U43<=0,M43<=2000000),"Mercado insuficiente", IF(U43<=0,"Limite de expansão", IF(K43<500000,"Performance", IF(M43<=2000000,"Mercado insuficiente","Expansão") ) ) ) ) -> Expansão | AC43: =IF(P43=B43,"Oportunidade","Validar") -> Validar
A44: 410150 | B44: Arapongas | C44: PR | D44: 4 | E44: =COUNTIFS('Contratos assinados '!F:F,'Direcional Expansão'!B44,'Contratos assinados '!J:J, "Assinado por ambos") -> 0 | F44: =COUNTIFS('Contratos assinados '!F:F,'Direcional Expansão'!B44,'Contratos assinados '!J:J,"Aquisição") -> 0 | G44: =COUNTIFS('Contratos assinados '!F:F,'Direcional Expansão'!B44,'Contratos assinados '!J:J,"Ampliação") -> 0 | H44: =COUNTIFS('Contratos assinados '!F:F,'Direcional Expansão'!B44,'Contratos assinados '!J:J,"Assinado por proprietário") -> 0 | I44: =SUM(E44:H44) -> 0 | J44: =IF(D44=0, "-", COUNTIFS('Base Lojas'!B:B, A44, 'Base Lojas'!I:I, ">500000")/D44) -> 0.75 | K44: 788656.4 | L44: 0.18596729 | M44: 16963336 | N44: 119138 | O44: =_xlfn.XLOOKUP(A44,Cidades!A:A,Cidades!D:D) -> Entre 100k e 150k | P44: =_xlfn.XLOOKUP(A44,'[1]1° RAIZ'!$A:$A,'[1]1° RAIZ'!$AH:$AH) -> Londrina | Q44: =_xlfn.XLOOKUP(A44,'[1]1° RAIZ'!$A:$A,'[1]1° RAIZ'!$AE:$AE) -> Londrina | R44: 0.00010387791 | S44: 0.014334252 | T44: 39 | U44: 3 | V44: 44594.278 | W44: 4.1987978 | X44: 0.98118364 | Y44: 0.34545532 | Z44: -0.013044911 | AA44: 0.46610158 | AB44: =IF(B44="Capão do Leão","Erro IBGE", IF(AND(U44<=0,M44<=2000000),"Mercado insuficiente", IF(U44<=0,"Limite de expansão", IF(K44<500000,"Performance", IF(M44<=2000000,"Mercado insuficiente","Expansão") ) ) ) ) -> Expansão | AC44: =IF(P44=B44,"Oportunidade","Validar") -> Validar
A45: 412810 | B45: Umuarama | C45: PR | D45: 4 | E45: =COUNTIFS('Contratos assinados '!F:F,'Direcional Expansão'!B45,'Contratos assinados '!J:J, "Assinado por ambos") -> 0 | F45: =COUNTIFS('Contratos assinados '!F:F,'Direcional Expansão'!B45,'Contratos assinados '!J:J,"Aquisição") -> 0 | G45: =COUNTIFS('Contratos assinados '!F:F,'Direcional Expansão'!B45,'Contratos assinados '!J:J,"Ampliação") -> 0 | H45: =COUNTIFS('Contratos assinados '!F:F,'Direcional Expansão'!B45,'Contratos assinados '!J:J,"Assinado por proprietário") -> 0 | I45: =SUM(E45:H45) -> 0 | J45: =IF(D45=0, "-", COUNTIFS('Base Lojas'!B:B, A45, 'Base Lojas'!G:G, ">500000")/D45) -> 0.25 | K45: 391546.84 | L45: 0.089952597 | M45: 17411252 | N45: 117095 | O45: =_xlfn.XLOOKUP(A45,Cidades!A:A,Cidades!D:D) -> Entre 100k e 150k | P45: =_xlfn.XLOOKUP(A45,'[1]1° RAIZ'!$A:$A,'[1]1° RAIZ'!$AH:$AH) -> Umuarama | Q45: =_xlfn.XLOOKUP(A45,'[1]1° RAIZ'!$A:$A,'[1]1° RAIZ'!$AE:$AE) -> Maringá | R45: 0.00011658272 | S45: 0.014438821 | T45: 48 | U45: 3 | V45: 37476.402 | W45: 4.1369796 | X45: 1.0284412 | Y45: 0.12214916 | Z45: -0.47122706 | AA45: 0.40177744 | AB45: =IF(B45="Capão do Leão","Erro IBGE", IF(AND(U45<=0,M45<=2000000),"Mercado insuficiente", IF(U45<=0,"Limite de expansão", IF(K45<500000,"Performance", IF(M45<=2000000,"Mercado insuficiente","Expansão") ) ) ) ) -> Performance | AC45: =IF(P45=B45,"Oportunidade","Validar") -> Oportunidade
A46: 410840 | B46: Francisco Beltrão | C46: PR | D46: 3 | E46: =COUNTIFS('Contratos assinados '!F:F,'Direcional Expansão'!B46,'Contratos assinados '!J:J, "Assinado por ambos") -> 0 | F46: =COUNTIFS('Contratos assinados '!F:F,'Direcional Expansão'!B46,'Contratos assinados '!J:J,"Aquisição") -> 0 | G46: =COUNTIFS('Contratos assinados '!F:F,'Direcional Expansão'!B46,'Contratos assinados '!J:J,"Ampliação") -> 0 | H46: =COUNTIFS('Contratos assinados '!F:F,'Direcional Expansão'!B46,'Contratos assinados '!J:J,"Assinado por proprietário") -> 0 | I46: =SUM(E46:H46) -> 0 | J46: =IF(D46=0, "-", COUNTIFS('Base Lojas'!B:B, A46, 'Base Lojas'!G:G, ">500000")/D46) -> 0.66666667 | K46: 483004.92 | L46: 0.095407422 | M46: 15187652 | N46: 96666 | O46: =_xlfn.XLOOKUP(A46,Cidades!A:A,Cidades!D:D) -> Entre 50k e 100k | P46: =_xlfn.XLOOKUP(A46,'[1]1° RAIZ'!$A:$A,'[1]1° RAIZ'!$AH:$AH) -> Francisco Beltrão | Q46: =_xlfn.XLOOKUP(A46,'[1]1° RAIZ'!$A:$A,'[1]1° RAIZ'!$AE:$AE) -> Cascavel | R46: 0.00015687808 | S46: 0.0198041 | T46: 47 | U46: 3 | V46: 40502.685 | W46: 4.2400865 | X46: 0.94539025 | Y46: 0.35016857 | Z46: -0.52026833 | AA46: 0.39362993 | AB46: =IF(B46="Capão do Leão","Erro IBGE", IF(AND(U46<=0,M46<=2000000),"Mercado insuficiente", IF(U46<=0,"Limite de expansão", IF(K46<500000,"Performance", IF(M46<=2000000,"Mercado insuficiente","Expansão") ) ) ) ) -> Performance | AC46: =IF(P46=B46,"Oportunidade","Validar") -> Oportunidade
A47: 411840 | B47: Paranavaí | C47: PR | D47: 3 | E47: =COUNTIFS('Contratos assinados '!F:F,'Direcional Expansão'!B47,'Contratos assinados '!J:J, "Assinado por ambos") -> 0 | F47: =COUNTIFS('Contratos assinados '!F:F,'Direcional Expansão'!B47,'Contratos assinados '!J:J,"Aquisição") -> 0 | G47: =COUNTIFS('Contratos assinados '!F:F,'Direcional Expansão'!B47,'Contratos assinados '!J:J,"Ampliação") -> 0 | H47: =COUNTIFS('Contratos assinados '!F:F,'Direcional Expansão'!B47,'Contratos assinados '!J:J,"Assinado por proprietário") -> 0 | I47: =SUM(E47:H47) -> 0 | J47: =IF(D47=0, "-", COUNTIFS('Base Lojas'!B:B, A47, 'Base Lojas'!I:I, ">500000")/D47) -> 1 | K47: 685217.31 | L47: 0.14639266 | M47: 14042042 | N47: 91950 | O47: =_xlfn.XLOOKUP(A47,Cidades!A:A,Cidades!D:D) -> Entre 50k e 100k | P47: =_xlfn.XLOOKUP(A47,'[1]1° RAIZ'!$A:$A,'[1]1° RAIZ'!$AH:$AH) -> Paranavaí | Q47: =_xlfn.XLOOKUP(A47,'[1]1° RAIZ'!$A:$A,'[1]1° RAIZ'!$AE:$AE) -> Maringá | R47: 9.2328985e-05 | S47: 0.0133358 | T47: 43 | U47: 3 | V47: 37129.157 | W47: 4.1212858 | X47: 0.86423315 | Y47: 0.18602875 | Z47: -0.25328488 | AA47: 0.36592037 | AB47: =IF(B47="Capão do Leão","Erro IBGE", IF(AND(U47<=0,M47<=2000000),"Mercado insuficiente", IF(U47<=0,"Limite de expansão", IF(K47<500000,"Performance", IF(M47<=2000000,"Mercado insuficiente","Expansão") ) ) ) ) -> Expansão | AC47: =IF(P47=B47,"Oportunidade","Validar") -> Oportunidade
A48: 410370 | B48: Cambé | C48: PR | D48: 4 | E48: =COUNTIFS('Contratos assinados '!F:F,'Direcional Expansão'!B48,'Contratos assinados '!J:J, "Assinado por ambos") -> 0 | F48: =COUNTIFS('Contratos assinados '!F:F,'Direcional Expansão'!B48,'Contratos assinados '!J:J,"Aquisição") -> 0 | G48: =COUNTIFS('Contratos assinados '!F:F,'Direcional Expansão'!B48,'Contratos assinados '!J:J,"Ampliação") -> 0 | H48: =COUNTIFS('Contratos assinados '!F:F,'Direcional Expansão'!B48,'Contratos assinados '!J:J,"Assinado por proprietário") -> 0 | I48: =SUM(E48:H48) -> 0 | J48: =IF(D48=0, "-", COUNTIFS('Base Lojas'!B:B, A48, 'Base Lojas'!I:I, ">500000")/D48) -> 0.5 | K48: 550069.37 | L48: 0.14686239 | M48: 14981899 | N48: 107208 | O48: =_xlfn.XLOOKUP(A48,Cidades!A:A,Cidades!D:D) -> Entre 100k e 150k | P48: =_xlfn.XLOOKUP(A48,'[1]1° RAIZ'!$A:$A,'[1]1° RAIZ'!$AH:$AH) -> Londrina | Q48: =_xlfn.XLOOKUP(A48,'[1]1° RAIZ'!$A:$A,'[1]1° RAIZ'!$AE:$AE) -> Londrina | R48: 7.9386989e-05 | S48: 0.012573596 | T48: 36 | U48: 3 | V48: 50622.432 | W48: 3.580381 | X48: 0.80368738 | Y48: 0.021607386 | Z48: -0.0072267783 | AA48: 0.34455932 | AB48: =IF(B48="Capão do Leão","Erro IBGE", IF(AND(U48<=0,M48<=2000000),"Mercado insuficiente", IF(U48<=0,"Limite de expansão", IF(K48<500000,"Performance", IF(M48<=2000000,"Mercado insuficiente","Expansão") ) ) ) ) -> Expansão | AC48: =IF(P48=B48,"Oportunidade","Validar") -> Validar
A49: 420140 | B49: Araranguá | C49: SC | D49: 1 | E49: =COUNTIFS('Contratos assinados '!F:F,'Direcional Expansão'!B49,'Contratos assinados '!J:J, "Assinado por ambos") -> 0 | F49: =COUNTIFS('Contratos assinados '!F:F,'Direcional Expansão'!B49,'Contratos assinados '!J:J,"Aquisição") -> 0 | G49: =COUNTIFS('Contratos assinados '!F:F,'Direcional Expansão'!B49,'Contratos assinados '!J:J,"Ampliação") -> 0 | H49: =COUNTIFS('Contratos assinados '!F:F,'Direcional Expansão'!B49,'Contratos assinados '!J:J,"Assinado por proprietário") -> 0 | I49: =SUM(E49:H49) -> 0 | J49: =IF(D49=0, "-", COUNTIFS('Base Lojas'!B:B, A49, 'Base Lojas'!G:G, ">500000")/D49) -> 0 | K49: 415005.2 | L49: 0.037481874 | M49: 11072157 | N49: 71922 | O49: =_xlfn.XLOOKUP(A49,Cidades!A:A,Cidades!D:D) -> Entre 50k e 100k | P49: =_xlfn.XLOOKUP(A49,'[1]1° RAIZ'!$A:$A,'[1]1° RAIZ'!$AH:$AH) -> Araranguá | Q49: =_xlfn.XLOOKUP(A49,'[1]1° RAIZ'!$A:$A,'[1]1° RAIZ'!$AE:$AE) -> Criciúma | R49: 0.00012318824 | S49: 0.015219881 | T49: 57 | U49: 3 | V49: 34980.437 | W49: 4.0137073 | X49: 0.84044617 | Y49: 0.035287677 | Z49: -0.73044824 | AA49: 0.27961779 | AB49: =IF(B49="Capão do Leão","Erro IBGE", IF(AND(U49<=0,M49<=2000000),"Mercado insuficiente", IF(U49<=0,"Limite de expansão", IF(K49<500000,"Performance", IF(M49<=2000000,"Mercado insuficiente","Expansão") ) ) ) ) -> Performance | AC49: =IF(P49=B49,"Oportunidade","Validar") -> Oportunidade
A50: 421950 | B50: Xanxerê | C50: SC | D50: 0 | E50: =COUNTIFS('Contratos assinados '!F:F,'Direcional Expansão'!B50,'Contratos assinados '!J:J, "Assinado por ambos") -> 0 | F50: =COUNTIFS('Contratos assinados '!F:F,'Direcional Expansão'!B50,'Contratos assinados '!J:J,"Aquisição") -> 0 | G50: =COUNTIFS('Contratos assinados '!F:F,'Direcional Expansão'!B50,'Contratos assinados '!J:J,"Ampliação") -> 0 | H50: =COUNTIFS('Contratos assinados '!F:F,'Direcional Expansão'!B50,'Contratos assinados '!J:J,"Assinado por proprietário") -> 0 | I50: =SUM(E50:H50) -> 0 | J50: =IF(D50=0, "-", COUNTIFS('Base Lojas'!B:B, A50, 'Base Lojas'!I:I, ">500000")/D50) -> - | K50: - | L50: 0 | M50: 8584204.1 | N50: 51607 | O50: =_xlfn.XLOOKUP(A50,Cidades!A:A,Cidades!D:D) -> Entre 50k e 100k | P50: =_xlfn.XLOOKUP(A50,'[1]1° RAIZ'!$A:$A,'[1]1° RAIZ'!$AH:$AH) -> Xanxerê | Q50: =_xlfn.XLOOKUP(A50,'[1]1° RAIZ'!$A:$A,'[1]1° RAIZ'!$AE:$AE) -> Chapecó | R50: 0.00012161993 | S50: 0.017376071 | T50: 31 | U50: 3 | V50: 54797.374 | W50: 4.5281045 | X50: 0.59798918 | Y50: 0.55006792 | Z50: -0.55880519 | AA50: 0.27005269 | AB50: =IF(B50="Capão do Leão","Erro IBGE", IF(AND(U50<=0,M50<=2000000),"Mercado insuficiente", IF(U50<=0,"Limite de expansão", IF(K50<500000,"Performance", IF(M50<=2000000,"Mercado insuficiente","Expansão") ) ) ) ) -> Expansão | AC50: =IF(P50=B50,"Oportunidade","Validar") -> Oportunidade
A51: 411580 | B51: Medianeira | C51: PR | D51: 0 | E51: =COUNTIFS('Contratos assinados '!F:F,'Direcional Expansão'!B51,'Contratos assinados '!J:J, "Assinado por ambos") -> 0 | F51: =COUNTIFS('Contratos assinados '!F:F,'Direcional Expansão'!B51,'Contratos assinados '!J:J,"Aquisição") -> 0 | G51: =COUNTIFS('Contratos assinados '!F:F,'Direcional Expansão'!B51,'Contratos assinados '!J:J,"Ampliação") -> 0 | H51: =COUNTIFS('Contratos assinados '!F:F,'Direcional Expansão'!B51,'Contratos assinados '!J:J,"Assinado por proprietário") -> 0 | I51: =SUM(E51:H51) -> 0 | J51: =IF(D51=0, "-", COUNTIFS('Base Lojas'!B:B, A51, 'Base Lojas'!I:I, ">500000")/D51) -> - | K51: - | L51: 0 | M51: 7903499.5 | N51: 54369 | O51: =_xlfn.XLOOKUP(A51,Cidades!A:A,Cidades!D:D) -> Entre 50k e 100k | P51: =_xlfn.XLOOKUP(A51,'[1]1° RAIZ'!$A:$A,'[1]1° RAIZ'!$AH:$AH) -> Foz do Iguaçu | Q51: =_xlfn.XLOOKUP(A51,'[1]1° RAIZ'!$A:$A,'[1]1° RAIZ'!$AE:$AE) -> Cascavel | R51: 0.00020372462 | S51: 0.022384281 | T51: 23 | U51: 3 | V51: 47419.246 | W51: 4.4203696 | X51: 0.52839845 | Y51: 0.60964563 | Z51: -0.85100734 | AA51: 0.21563216 | AB51: =IF(B51="Capão do Leão","Erro IBGE", IF(AND(U51<=0,M51<=2000000),"Mercado insuficiente", IF(U51<=0,"Limite de expansão", IF(K51<500000,"Performance", IF(M51<=2000000,"Mercado insuficiente","Expansão") ) ) ) ) -> Expansão | AC51: =IF(P51=B51,"Oportunidade","Validar") -> Validar
A52: 420730 | B52: Imbituba | C52: SC | D52: 0 | E52: =COUNTIFS('Contratos assinados '!F:F,'Direcional Expansão'!B52,'Contratos assinados '!J:J, "Assinado por ambos") -> 0 | F52: =COUNTIFS('Contratos assinados '!F:F,'Direcional Expansão'!B52,'Contratos assinados '!J:J,"Aquisição") -> 0 | G52: =COUNTIFS('Contratos assinados '!F:F,'Direcional Expansão'!B52,'Contratos assinados '!J:J,"Ampliação") -> 0 | H52: =COUNTIFS('Contratos assinados '!F:F,'Direcional Expansão'!B52,'Contratos assinados '!J:J,"Assinado por proprietário") -> 0 | I52: =SUM(E52:H52) -> 0 | J52: =IF(D52=0, "-", COUNTIFS('Base Lojas'!B:B, A52, 'Base Lojas'!I:I, ">500000")/D52) -> - | K52: - | L52: 0 | M52: 9162175.9 | N52: 52581 | O52: =_xlfn.XLOOKUP(A52,Cidades!A:A,Cidades!D:D) -> Entre 50k e 100k | P52: =_xlfn.XLOOKUP(A52,'[1]1° RAIZ'!$A:$A,'[1]1° RAIZ'!$AH:$AH) -> Florianópolis | Q52: =_xlfn.XLOOKUP(A52,'[1]1° RAIZ'!$A:$A,'[1]1° RAIZ'!$AE:$AE) -> Florianópolis | R52: 0.00020867658 | S52: 0.022939543 | T52: 42 | U52: 3 | V52: 49084.376 | W52: 3.6417083 | X52: 0.59586522 | Y52: 0.20019151 | Z52: -0.84121987 | AA52: 0.18654576 | AB52: =IF(B52="Capão do Leão","Erro IBGE", IF(AND(U52<=0,M52<=2000000),"Mercado insuficiente", IF(U52<=0,"Limite de expansão", IF(K52<500000,"Performance", IF(M52<=2000000,"Mercado insuficiente","Expansão") ) ) ) ) -> Expansão | AC52: =IF(P52=B52,"Oportunidade","Validar") -> Validar
A53: 410980 | B53: Ibiporã | C53: PR | D53: 0 | E53: =COUNTIFS('Contratos assinados '!F:F,'Direcional Expansão'!B53,'Contratos assinados '!J:J, "Assinado por ambos") -> 0 | F53: =COUNTIFS('Contratos assinados '!F:F,'Direcional Expansão'!B53,'Contratos assinados '!J:J,"Aquisição") -> 0 | G53: =COUNTIFS('Contratos assinados '!F:F,'Direcional Expansão'!B53,'Contratos assinados '!J:J,"Ampliação") -> 0 | H53: =COUNTIFS('Contratos assinados '!F:F,'Direcional Expansão'!B53,'Contratos assinados '!J:J,"Assinado por proprietário") -> 0 | I53: =SUM(E53:H53) -> 0 | J53: =IF(D53=0, "-", COUNTIFS('Base Lojas'!B:B, A53, 'Base Lojas'!I:I, ">500000")/D53) -> - | K53: - | L53: 0 | M53: 7174676.5 | N53: 51603 | O53: =_xlfn.XLOOKUP(A53,Cidades!A:A,Cidades!D:D) -> Entre 50k e 100k | P53: =_xlfn.XLOOKUP(A53,'[1]1° RAIZ'!$A:$A,'[1]1° RAIZ'!$AH:$AH) -> Londrina | Q53: =_xlfn.XLOOKUP(A53,'[1]1° RAIZ'!$A:$A,'[1]1° RAIZ'!$AE:$AE) -> Londrina | R53: 5.2615466e-05 | S53: 0.010091364 | T53: 18 | U53: 3 | V53: 70023.365 | W53: 3.5442217 | X53: 0.34211796 | Y53: 0.077063375 | Z53: -0.15836188 | AA53: 0.13871442 | AB53: =IF(B53="Capão do Leão","Erro IBGE", IF(AND(U53<=0,M53<=2000000),"Mercado insuficiente", IF(U53<=0,"Limite de expansão", IF(K53<500000,"Performance", IF(M53<=2000000,"Mercado insuficiente","Expansão") ) ) ) ) -> Expansão | AC53: =IF(P53=B53,"Oportunidade","Validar") -> Validar
A54: 411070 | B54: Irati | C54: PR | D54: 0 | E54: =COUNTIFS('Contratos assinados '!F:F,'Direcional Expansão'!B54,'Contratos assinados '!J:J, "Assinado por ambos") -> 0 | F54: =COUNTIFS('Contratos assinados '!F:F,'Direcional Expansão'!B54,'Contratos assinados '!J:J,"Aquisição") -> 0 | G54: =COUNTIFS('Contratos assinados '!F:F,'Direcional Expansão'!B54,'Contratos assinados '!J:J,"Ampliação") -> 0 | H54: =COUNTIFS('Contratos assinados '!F:F,'Direcional Expansão'!B54,'Contratos assinados '!J:J,"Assinado por proprietário") -> 0 | I54: =SUM(E54:H54) -> 0 | J54: =IF(D54=0, "-", COUNTIFS('Base Lojas'!B:B, A54, 'Base Lojas'!I:I, ">500000")/D54) -> - | K54: - | L54: 0 | M54: 7795549 | N54: 59250 | O54: =_xlfn.XLOOKUP(A54,Cidades!A:A,Cidades!D:D) -> Entre 50k e 100k | P54: =_xlfn.XLOOKUP(A54,'[1]1° RAIZ'!$A:$A,'[1]1° RAIZ'!$AH:$AH) -> Irati | Q54: =_xlfn.XLOOKUP(A54,'[1]1° RAIZ'!$A:$A,'[1]1° RAIZ'!$AE:$AE) -> Ponta Grossa | R54: 3.9527463e-05 | S54: 0.0097215773 | T54: 30 | U54: 3 | V54: 42204.33 | W54: 3.4410279 | X54: 0.44797439 | Y54: -0.30931056 | Z54: -0.57786446 | AA54: 0.080290299 | AB54: =IF(B54="Capão do Leão","Erro IBGE", IF(AND(U54<=0,M54<=2000000),"Mercado insuficiente", IF(U54<=0,"Limite de expansão", IF(K54<500000,"Performance", IF(M54<=2000000,"Mercado insuficiente","Expansão") ) ) ) ) -> Expansão | AC54: =IF(P54=B54,"Oportunidade","Validar") -> Oportunidade
A55: 410400 | B55: Campina Grande do Sul | C55: PR | D55: 0 | E55: =COUNTIFS('Contratos assinados '!F:F,'Direcional Expansão'!B55,'Contratos assinados '!J:J, "Assinado por ambos") -> 0 | F55: =COUNTIFS('Contratos assinados '!F:F,'Direcional Expansão'!B55,'Contratos assinados '!J:J,"Aquisição") -> 0 | G55: =COUNTIFS('Contratos assinados '!F:F,'Direcional Expansão'!B55,'Contratos assinados '!J:J,"Ampliação") -> 0 | H55: =COUNTIFS('Contratos assinados '!F:F,'Direcional Expansão'!B55,'Contratos assinados '!J:J,"Assinado por proprietário") -> 0 | I55: =SUM(E55:H55) -> 0 | J55: =IF(D55=0, "-", COUNTIFS('Base Lojas'!B:B, A55, 'Base Lojas'!I:I, ">500000")/D55) -> - | K55: - | L55: 0 | M55: 6307111.1 | N55: 47799 | O55: =_xlfn.XLOOKUP(A55,Cidades!A:A,Cidades!D:D) -> Entre 30k e 50k | P55: =_xlfn.XLOOKUP(A55,'[1]1° RAIZ'!$A:$A,'[1]1° RAIZ'!$AH:$AH) -> Curitiba | Q55: =_xlfn.XLOOKUP(A55,'[1]1° RAIZ'!$A:$A,'[1]1° RAIZ'!$AE:$AE) -> Curitiba | R55: 0.00016263068 | S55: 0.021511709 | T55: 15 | U55: 3 | V55: 48418.029 | W55: 3.4900718 | X55: 0.29768949 | Y55: 0.11886459 | Z55: -0.77494668 | AA55: 0.055418592 | AB55: =IF(B55="Capão do Leão","Erro IBGE", IF(AND(U55<=0,M55<=2000000),"Mercado insuficiente", IF(U55<=0,"Limite de expansão", IF(K55<500000,"Performance", IF(M55<=2000000,"Mercado insuficiente","Expansão") ) ) ) ) -> Expansão | AC55: =IF(P55=B55,"Oportunidade","Validar") -> Validar
A56: 411320 | B56: Lapa | C56: PR | D56: 0 | E56: =COUNTIFS('Contratos assinados '!F:F,'Direcional Expansão'!B56,'Contratos assinados '!J:J, "Assinado por ambos") -> 0 | F56: =COUNTIFS('Contratos assinados '!F:F,'Direcional Expansão'!B56,'Contratos assinados '!J:J,"Aquisição") -> 0 | G56: =COUNTIFS('Contratos assinados '!F:F,'Direcional Expansão'!B56,'Contratos assinados '!J:J,"Ampliação") -> 0 | H56: =COUNTIFS('Contratos assinados '!F:F,'Direcional Expansão'!B56,'Contratos assinados '!J:J,"Assinado por proprietário") -> 0 | I56: =SUM(E56:H56) -> 0 | J56: =IF(D56=0, "-", COUNTIFS('Base Lojas'!B:B, A56, 'Base Lojas'!I:I, ">500000")/D56) -> - | K56: - | L56: 0 | M56: 5883642.2 | N56: 45003 | O56: =_xlfn.XLOOKUP(A56,Cidades!A:A,Cidades!D:D) -> Entre 30k e 50k | P56: =_xlfn.XLOOKUP(A56,'[1]1° RAIZ'!$A:$A,'[1]1° RAIZ'!$AH:$AH) -> Curitiba | Q56: =_xlfn.XLOOKUP(A56,'[1]1° RAIZ'!$A:$A,'[1]1° RAIZ'!$AE:$AE) -> Curitiba | R56: 1.1461418e-06 | S56: 0.006606792 | T56: 11 | U56: 3 | V56: 69777.87 | W56: 3.0365865 | X56: 0.17472482 | Y56: -0.25798118 | Z56: -0.060931904 | AA56: 0.030321967 | AB56: =IF(B56="Capão do Leão","Erro IBGE", IF(AND(U56<=0,M56<=2000000),"Mercado insuficiente", IF(U56<=0,"Limite de expansão", IF(K56<500000,"Performance", IF(M56<=2000000,"Mercado insuficiente","Expansão") ) ) ) ) -> Expansão | AC56: =IF(P56=B56,"Oportunidade","Validar") -> Validar
A57: 412625 | B57: Sarandi - PR | C57: PR | D57: 3 | E57: =COUNTIFS('Contratos assinados '!F:F,'Direcional Expansão'!B57,'Contratos assinados '!J:J, "Assinado por ambos") -> 0 | F57: =COUNTIFS('Contratos assinados '!F:F,'Direcional Expansão'!B57,'Contratos assinados '!J:J,"Aquisição") -> 0 | G57: =COUNTIFS('Contratos assinados '!F:F,'Direcional Expansão'!B57,'Contratos assinados '!J:J,"Ampliação") -> 0 | H57: =COUNTIFS('Contratos assinados '!F:F,'Direcional Expansão'!B57,'Contratos assinados '!J:J,"Assinado por proprietário") -> 0 | I57: =SUM(E57:H57) -> 0 | J57: =IF(D57=0, "-", COUNTIFS('Base Lojas'!B:B, A57, 'Base Lojas'!G:G, ">500000")/D57) -> 0.33333333 | K57: 428223.24 | L57: 0.078179303 | M57: 16432351 | N57: 118455 | O57: =_xlfn.XLOOKUP(A57,Cidades!A:A,Cidades!D:D) -> Entre 100k e 150k | P57: =_xlfn.XLOOKUP(A57,'[1]1° RAIZ'!$A:$A,'[1]1° RAIZ'!$AH:$AH) -> Maringá | Q57: =_xlfn.XLOOKUP(A57,'[1]1° RAIZ'!$A:$A,'[1]1° RAIZ'!$AE:$AE) -> Maringá | R57: 0.00027889361 | S57: 0.030811154 | T57: 0 | U57: 3 | V57: 18180.401 | W57: 2.7754022 | X57: 0.48106691 | Y57: -0.25532642 | Z57: -1.2248362 | AA57: 0.028293618 | AB57: =IF(B57="Capão do Leão","Erro IBGE", IF(AND(U57<=0,M57<=2000000),"Mercado insuficiente", IF(U57<=0,"Limite de expansão", IF(K57<500000,"Performance", IF(M57<=2000000,"Mercado insuficiente","Expansão") ) ) ) ) -> Performance | AC57: =IF(P57=B57,"Oportunidade","Validar") -> Validar
A58: 430700 | B58: Erechim | C58: RS | D58: 5 | E58: =COUNTIFS('Contratos assinados '!F:F,'Direcional Expansão'!B58,'Contratos assinados '!J:J, "Assinado por ambos") -> 0 | F58: =COUNTIFS('Contratos assinados '!F:F,'Direcional Expansão'!B58,'Contratos assinados '!J:J,"Aquisição") -> 0 | G58: =COUNTIFS('Contratos assinados '!F:F,'Direcional Expansão'!B58,'Contratos assinados '!J:J,"Ampliação") -> 0 | H58: =COUNTIFS('Contratos assinados '!F:F,'Direcional Expansão'!B58,'Contratos assinados '!J:J,"Assinado por proprietário") -> 0 | I58: =SUM(E58:H58) -> 0 | J58: =IF(D58=0, "-", COUNTIFS('Base Lojas'!B:B, A58, 'Base Lojas'!G:G, ">500000")/D58) -> 0 | K58: 232853.06 | L58: 0.054167298 | M58: 21493878 | N58: 105705 | O58: =_xlfn.XLOOKUP(A58,Cidades!A:A,Cidades!D:D) -> Entre 100k e 150k | P58: =_xlfn.XLOOKUP(A58,'[1]1° RAIZ'!$A:$A,'[1]1° RAIZ'!$AH:$AH) -> Erechim | Q58: =_xlfn.XLOOKUP(A58,'[1]1° RAIZ'!$A:$A,'[1]1° RAIZ'!$AE:$AE) -> Passo Fundo | R58: 7.3507971e-05 | S58: 0.011613992 | T58: 53 | U58: 2 | V58: 70208.545 | W58: 4.7006399 | X58: 1.1055447 | Y58: 0.60551841 | Z58: 0.058221054 | AA58: 0.5646337 | AB58: =IF(B58="Capão do Leão","Erro IBGE", IF(AND(U58<=0,M58<=2000000),"Mercado insuficiente", IF(U58<=0,"Limite de expansão", IF(K58<500000,"Performance", IF(M58<=2000000,"Mercado insuficiente","Expansão") ) ) ) ) -> Performance | AC58: =IF(P58=B58,"Oportunidade","Validar") -> Oportunidade
A59: 421820 | B59: Timbó | C59: SC | D59: 1 | E59: =COUNTIFS('Contratos assinados '!F:F,'Direcional Expansão'!B59,'Contratos assinados '!J:J, "Assinado por ambos") -> 0 | F59: =COUNTIFS('Contratos assinados '!F:F,'Direcional Expansão'!B59,'Contratos assinados '!J:J,"Aquisição") -> 0 | G59: =COUNTIFS('Contratos assinados '!F:F,'Direcional Expansão'!B59,'Contratos assinados '!J:J,"Ampliação") -> 0 | H59: =COUNTIFS('Contratos assinados '!F:F,'Direcional Expansão'!B59,'Contratos assinados '!J:J,"Assinado por proprietário") -> 0 | I59: =SUM(E59:H59) -> 0 | J59: =IF(D59=0, "-", COUNTIFS('Base Lojas'!B:B, A59, 'Base Lojas'!G:G, ">500000")/D59) -> 0 | K59: 401203.86 | L59: 0.044388865 | M59: 9038389.7 | N59: 46099 | O59: =_xlfn.XLOOKUP(A59,Cidades!A:A,Cidades!D:D) -> Entre 30k e 50k | P59: =_xlfn.XLOOKUP(A59,'[1]1° RAIZ'!$A:$A,'[1]1° RAIZ'!$AH:$AH) -> Blumenau | Q59: =_xlfn.XLOOKUP(A59,'[1]1° RAIZ'!$A:$A,'[1]1° RAIZ'!$AE:$AE) -> Blumenau | R59: 0.00017445155 | S59: 0.019101947 | T59: 30 | U59: 2 | V59: 57201.543 | W59: 5.9889812 | X59: 0.72254836 | Y59: 1.4906161 | Z59: -0.43551113 | AA59: 0.47255735 | AB59: =IF(B59="Capão do Leão","Erro IBGE", IF(AND(U59<=0,M59<=2000000),"Mercado insuficiente", IF(U59<=0,"Limite de expansão", IF(K59<500000,"Performance", IF(M59<=2000000,"Mercado insuficiente","Expansão") ) ) ) ) -> Performance | AC59: =IF(P59=B59,"Oportunidade","Validar") -> Validar
A60: 420430 | B60: Concórdia | C60: SC | D60: 3 | E60: =COUNTIFS('Contratos assinados '!F:F,'Direcional Expansão'!B60,'Contratos assinados '!J:J, "Assinado por ambos") -> 0 | F60: =COUNTIFS('Contratos assinados '!F:F,'Direcional Expansão'!B60,'Contratos assinados '!J:J,"Aquisição") -> 0 | G60: =COUNTIFS('Contratos assinados '!F:F,'Direcional Expansão'!B60,'Contratos assinados '!J:J,"Ampliação") -> 0 | H60: =COUNTIFS('Contratos assinados '!F:F,'Direcional Expansão'!B60,'Contratos assinados '!J:J,"Assinado por proprietário") -> 0 | I60: =SUM(E60:H60) -> 0 | J60: =IF(D60=0, "-", COUNTIFS('Base Lojas'!B:B, A60, 'Base Lojas'!I:I, ">500000")/D60) -> 1 | K60: 804404.14 | L60: 0.16205937 | M60: 14890916 | N60: 81646 | O60: =_xlfn.XLOOKUP(A60,Cidades!A:A,Cidades!D:D) -> Entre 50k e 100k | P60: =_xlfn.XLOOKUP(A60,'[1]1° RAIZ'!$A:$A,'[1]1° RAIZ'!$AH:$AH) -> Concórdia | Q60: =_xlfn.XLOOKUP(A60,'[1]1° RAIZ'!$A:$A,'[1]1° RAIZ'!$AE:$AE) -> Chapecó | R60: 0.00013451732 | S60: 0.013985945 | T60: 31 | U60: 2 | V60: 58741.407 | W60: 4.7257446 | X60: 0.78275861 | Y60: 0.85532761 | Z60: 0.09883149 | AA60: 0.46775918 | AB60: =IF(B60="Capão do Leão","Erro IBGE", IF(AND(U60<=0,M60<=2000000),"Mercado insuficiente", IF(U60<=0,"Limite de expansão", IF(K60<500000,"Performance", IF(M60<=2000000,"Mercado insuficiente","Expansão") ) ) ) ) -> Expansão | AC60: =IF(P60=B60,"Oportunidade","Validar") -> Oportunidade
A61: 420130 | B61: Araquari | C61: SC | D61: 1 | E61: =COUNTIFS('Contratos assinados '!F:F,'Direcional Expansão'!B61,'Contratos assinados '!J:J, "Assinado por ambos") -> 0 | F61: =COUNTIFS('Contratos assinados '!F:F,'Direcional Expansão'!B61,'Contratos assinados '!J:J,"Aquisição") -> 0 | G61: =COUNTIFS('Contratos assinados '!F:F,'Direcional Expansão'!B61,'Contratos assinados '!J:J,"Ampliação") -> 0 | H61: =COUNTIFS('Contratos assinados '!F:F,'Direcional Expansão'!B61,'Contratos assinados '!J:J,"Assinado por proprietário") -> 0 | I61: =SUM(E61:H61) -> 0 | J61: =IF(D61=0, "-", COUNTIFS('Base Lojas'!B:B, A61, 'Base Lojas'!G:G, ">500000")/D61) -> 0 | K61: 470644.13 | L61: 0.081572118 | M61: 5769669.1 | N61: 45180 | O61: =_xlfn.XLOOKUP(A61,Cidades!A:A,Cidades!D:D) -> Entre 30k e 50k | P61: =_xlfn.XLOOKUP(A61,'[1]1° RAIZ'!$A:$A,'[1]1° RAIZ'!$AH:$AH) -> Joinville | Q61: =_xlfn.XLOOKUP(A61,'[1]1° RAIZ'!$A:$A,'[1]1° RAIZ'!$AE:$AE) -> Joinville | R61: 0.00047174814 | S61: 0.046055829 | T61: 1 | U61: 2 | V61: 160968.22 | W61: 3.2678416 | X61: 0.17729479 | Y61: 1.9681946 | Z61: 0.63154277 | AA61: 0.43090575 | AB61: =IF(B61="Capão do Leão","Erro IBGE", IF(AND(U61<=0,M61<=2000000),"Mercado insuficiente", IF(U61<=0,"Limite de expansão", IF(K61<500000,"Performance", IF(M61<=2000000,"Mercado insuficiente","Expansão") ) ) ) ) -> Performance | AC61: =IF(P61=B61,"Oportunidade","Validar") -> Validar
A62: 420750 | B62: Indaial | C62: SC | D62: 2 | E62: =COUNTIFS('Contratos assinados '!F:F,'Direcional Expansão'!B62,'Contratos assinados '!J:J, "Assinado por ambos") -> 0 | F62: =COUNTIFS('Contratos assinados '!F:F,'Direcional Expansão'!B62,'Contratos assinados '!J:J,"Aquisição") -> 0 | G62: =COUNTIFS('Contratos assinados '!F:F,'Direcional Expansão'!B62,'Contratos assinados '!J:J,"Ampliação") -> 0 | H62: =COUNTIFS('Contratos assinados '!F:F,'Direcional Expansão'!B62,'Contratos assinados '!J:J,"Assinado por proprietário") -> 0 | I62: =SUM(E62:H62) -> 0 | J62: =IF(D62=0, "-", COUNTIFS('Base Lojas'!B:B, A62, 'Base Lojas'!G:G, ">500000")/D62) -> 0 | K62: 345054.05 | L62: 0.05454034 | M62: 12653168 | N62: 71549 | O62: =_xlfn.XLOOKUP(A62,Cidades!A:A,Cidades!D:D) -> Entre 50k e 100k | P62: =_xlfn.XLOOKUP(A62,'[1]1° RAIZ'!$A:$A,'[1]1° RAIZ'!$AH:$AH) -> Blumenau | Q62: =_xlfn.XLOOKUP(A62,'[1]1° RAIZ'!$A:$A,'[1]1° RAIZ'!$AE:$AE) -> Blumenau | R62: 0.00020735267 | S62: 0.021334745 | T62: 27 | U62: 2 | V62: 52995.51 | W62: 4.6404277 | X62: 0.66650768 | Y62: 0.8248661 | Z62: -0.53748321 | AA62: 0.34122175 | AB62: =IF(B62="Capão do Leão","Erro IBGE", IF(AND(U62<=0,M62<=2000000),"Mercado insuficiente", IF(U62<=0,"Limite de expansão", IF(K62<500000,"Performance", IF(M62<=2000000,"Mercado insuficiente","Expansão") ) ) ) ) -> Performance | AC62: =IF(P62=B62,"Oportunidade","Validar") -> Validar
A63: 411460 | B63: Marechal Cândido Rondon | C63: PR | D63: 1 | E63: =COUNTIFS('Contratos assinados '!F:F,'Direcional Expansão'!B63,'Contratos assinados '!J:J, "Assinado por ambos") -> 0 | F63: =COUNTIFS('Contratos assinados '!F:F,'Direcional Expansão'!B63,'Contratos assinados '!J:J,"Aquisição") -> 0 | G63: =COUNTIFS('Contratos assinados '!F:F,'Direcional Expansão'!B63,'Contratos assinados '!J:J,"Ampliação") -> 0 | H63: =COUNTIFS('Contratos assinados '!F:F,'Direcional Expansão'!B63,'Contratos assinados '!J:J,"Assinado por proprietário") -> 0 | I63: =SUM(E63:H63) -> 0 | J63: =IF(D63=0, "-", COUNTIFS('Base Lojas'!B:B, A63, 'Base Lojas'!G:G, ">500000")/D63) -> 0 | K63: 490362.82 | L63: 0.054916864 | M63: 8929184.6 | N63: 55836 | O63: =_xlfn.XLOOKUP(A63,Cidades!A:A,Cidades!D:D) -> Entre 50k e 100k | P63: =_xlfn.XLOOKUP(A63,'[1]1° RAIZ'!$A:$A,'[1]1° RAIZ'!$AH:$AH) -> Marechal Cândido Rondon | Q63: =_xlfn.XLOOKUP(A63,'[1]1° RAIZ'!$A:$A,'[1]1° RAIZ'!$AE:$AE) -> Cascavel | R63: 0.00013673952 | S63: 0.015873421 | T63: 25 | U63: 2 | V63: 56027.286 | W63: 4.8272335 | X63: 0.560015 | Y63: 0.83015182 | Z63: -0.34097989 | AA63: 0.319063 | AB63: =IF(B63="Capão do Leão","Erro IBGE", IF(AND(U63<=0,M63<=2000000),"Mercado insuficiente", IF(U63<=0,"Limite de expansão", IF(K63<500000,"Performance", IF(M63<=2000000,"Mercado insuficiente","Expansão") ) ) ) ) -> Performance | AC63: =IF(P63=B63,"Oportunidade","Validar") -> Oportunidade
A64: 412240 | B64: Rolândia | C64: PR | D64: 2 | E64: =COUNTIFS('Contratos assinados '!F:F,'Direcional Expansão'!B64,'Contratos assinados '!J:J, "Assinado por ambos") -> 0 | F64: =COUNTIFS('Contratos assinados '!F:F,'Direcional Expansão'!B64,'Contratos assinados '!J:J,"Aquisição") -> 0 | G64: =COUNTIFS('Contratos assinados '!F:F,'Direcional Expansão'!B64,'Contratos assinados '!J:J,"Ampliação") -> 0 | H64: =COUNTIFS('Contratos assinados '!F:F,'Direcional Expansão'!B64,'Contratos assinados '!J:J,"Assinado por proprietário") -> 0 | I64: =SUM(E64:H64) -> 0 | J64: =IF(D64=0, "-", COUNTIFS('Base Lojas'!B:B, A64, 'Base Lojas'!G:G, ">500000")/D64) -> 0.5 | K64: 481579.41 | L64: 0.090592064 | M64: 10631823 | N64: 71670 | O64: =_xlfn.XLOOKUP(A64,Cidades!A:A,Cidades!D:D) -> Entre 50k e 100k | P64: =_xlfn.XLOOKUP(A64,'[1]1° RAIZ'!$A:$A,'[1]1° RAIZ'!$AH:$AH) -> Londrina | Q64: =_xlfn.XLOOKUP(A64,'[1]1° RAIZ'!$A:$A,'[1]1° RAIZ'!$AE:$AE) -> Londrina | R64: 0.00016587855 | S64: 0.019124574 | T64: 31 | U64: 2 | V64: 53042.127 | W64: 3.9995647 | X64: 0.58776532 | Y64: 0.46830409 | Z64: -0.3409642 | AA64: 0.27879902 | AB64: =IF(B64="Capão do Leão","Erro IBGE", IF(AND(U64<=0,M64<=2000000),"Mercado insuficiente", IF(U64<=0,"Limite de expansão", IF(K64<500000,"Performance", IF(M64<=2000000,"Mercado insuficiente","Expansão") ) ) ) ) -> Performance | AC64: =IF(P64=B64,"Oportunidade","Validar") -> Validar
A65: 420210 | B65: Barra Velha | C65: SC | D65: 1 | E65: =COUNTIFS('Contratos assinados '!F:F,'Direcional Expansão'!B65,'Contratos assinados '!J:J, "Assinado por ambos") -> 0 | F65: =COUNTIFS('Contratos assinados '!F:F,'Direcional Expansão'!B65,'Contratos assinados '!J:J,"Aquisição") -> 0 | G65: =COUNTIFS('Contratos assinados '!F:F,'Direcional Expansão'!B65,'Contratos assinados '!J:J,"Ampliação") -> 0 | H65: =COUNTIFS('Contratos assinados '!F:F,'Direcional Expansão'!B65,'Contratos assinados '!J:J,"Assinado por proprietário") -> 0 | I65: =SUM(E65:H65) -> 0 | J65: =IF(D65=0, "-", COUNTIFS('Base Lojas'!B:B, A65, 'Base Lojas'!G:G, ">500000")/D65) -> 0 | K65: 309817.26 | L65: 0.045271825 | M65: 6843489.5 | N65: 45371 | O65: =_xlfn.XLOOKUP(A65,Cidades!A:A,Cidades!D:D) -> Entre 30k e 50k | P65: =_xlfn.XLOOKUP(A65,'[1]1° RAIZ'!$A:$A,'[1]1° RAIZ'!$AH:$AH) -> Itajaí | Q65: =_xlfn.XLOOKUP(A65,'[1]1° RAIZ'!$A:$A,'[1]1° RAIZ'!$AE:$AE) -> Blumenau | R65: 0.00055783286 | S65: 0.05300517 | T65: 21 | U65: 2 | V65: 50271.11 | W65: 3.8031287 | X65: 0.39550082 | Y65: 1.2386282 | Z65: -1.452294 | AA65: 0.180924 | AB65: =IF(B65="Capão do Leão","Erro IBGE", IF(AND(U65<=0,M65<=2000000),"Mercado insuficiente", IF(U65<=0,"Limite de expansão", IF(K65<500000,"Performance", IF(M65<=2000000,"Mercado insuficiente","Expansão") ) ) ) ) -> Performance | AC65: =IF(P65=B65,"Oportunidade","Validar") -> Validar
A66: 421010 | B66: Mafra | C66: SC | D66: 1 | E66: =COUNTIFS('Contratos assinados '!F:F,'Direcional Expansão'!B66,'Contratos assinados '!J:J, "Assinado por ambos") -> 0 | F66: =COUNTIFS('Contratos assinados '!F:F,'Direcional Expansão'!B66,'Contratos assinados '!J:J,"Aquisição") -> 0 | G66: =COUNTIFS('Contratos assinados '!F:F,'Direcional Expansão'!B66,'Contratos assinados '!J:J,"Ampliação") -> 0 | H66: =COUNTIFS('Contratos assinados '!F:F,'Direcional Expansão'!B66,'Contratos assinados '!J:J,"Assinado por proprietário") -> 0 | I66: =SUM(E66:H66) -> 0 | J66: =IF(D66=0, "-", COUNTIFS('Base Lojas'!B:B, A66, 'Base Lojas'!G:G, ">500000")/D66) -> 0 | K66: 402630.68 | L66: 0.045623811 | M66: 8825012 | N66: 55286 | O66: =_xlfn.XLOOKUP(A66,Cidades!A:A,Cidades!D:D) -> Entre 50k e 100k | P66: =_xlfn.XLOOKUP(A66,'[1]1° RAIZ'!$A:$A,'[1]1° RAIZ'!$AH:$AH) -> Mafra | Q66: =_xlfn.XLOOKUP(A66,'[1]1° RAIZ'!$A:$A,'[1]1° RAIZ'!$AE:$AE) -> Joinville | R66: 3.3701565e-05 | S66: 0.0080251475 | T66: 23 | U66: 2 | V66: 48878.245 | W66: 3.9699661 | X66: 0.41343384 | Y66: 0.10221821 | Z66: -0.26710226 | AA66: 0.16029299 | AB66: =IF(B66="Capão do Leão","Erro IBGE", IF(AND(U66<=0,M66<=2000000),"Mercado insuficiente", IF(U66<=0,"Limite de expansão", IF(K66<500000,"Performance", IF(M66<=2000000,"Mercado insuficiente","Expansão") ) ) ) ) -> Performance | AC66: =IF(P66=B66,"Oportunidade","Validar") -> Oportunidade
A67: 420545 | B67: Forquilhinha | C67: SC | D67: 0 | E67: =COUNTIFS('Contratos assinados '!F:F,'Direcional Expansão'!B67,'Contratos assinados '!J:J, "Assinado por ambos") -> 1 | F67: =COUNTIFS('Contratos assinados '!F:F,'Direcional Expansão'!B67,'Contratos assinados '!J:J,"Aquisição") -> 0 | G67: =COUNTIFS('Contratos assinados '!F:F,'Direcional Expansão'!B67,'Contratos assinados '!J:J,"Ampliação") -> 0 | H67: =COUNTIFS('Contratos assinados '!F:F,'Direcional Expansão'!B67,'Contratos assinados '!J:J,"Assinado por proprietário") -> 0 | I67: =SUM(E67:H67) -> 1 | J67: =IF(D67=0, "-", COUNTIFS('Base Lojas'!B:B, A67, 'Base Lojas'!I:I, ">500000")/D67) -> - | K67: - | L67: 0 | M67: 4481119.2 | N67: 31431 | O67: =_xlfn.XLOOKUP(A67,Cidades!A:A,Cidades!D:D) -> Entre 30k e 50k | P67: =_xlfn.XLOOKUP(A67,'[1]1° RAIZ'!$A:$A,'[1]1° RAIZ'!$AH:$AH) -> Criciúma | Q67: =_xlfn.XLOOKUP(A67,'[1]1° RAIZ'!$A:$A,'[1]1° RAIZ'!$AE:$AE) -> Criciúma | R67: 0.00025879065 | S67: 0.025001436 | T67: 17 | U67: 2 | V67: 39484.32 | W67: 4.3136641 | X67: 0.29236277 | Y67: 0.66638264 | Z67: -1.0800215 | AA67: 0.097130954 | AB67: =IF(B67="Capão do Leão","Erro IBGE", IF(AND(U67<=0,M67<=2000000),"Mercado insuficiente", IF(U67<=0,"Limite de expansão", IF(K67<500000,"Performance", IF(M67<=2000000,"Mercado insuficiente","Expansão") ) ) ) ) -> Expansão | AC67: =IF(P67=B67,"Oportunidade","Validar") -> Validar
A68: 412820 | B68: União da Vitória | C68: PR | D68: 1 | E68: =COUNTIFS('Contratos assinados '!F:F,'Direcional Expansão'!B68,'Contratos assinados '!J:J, "Assinado por ambos") -> 0 | F68: =COUNTIFS('Contratos assinados '!F:F,'Direcional Expansão'!B68,'Contratos assinados '!J:J,"Aquisição") -> 0 | G68: =COUNTIFS('Contratos assinados '!F:F,'Direcional Expansão'!B68,'Contratos assinados '!J:J,"Ampliação") -> 0 | H68: =COUNTIFS('Contratos assinados '!F:F,'Direcional Expansão'!B68,'Contratos assinados '!J:J,"Assinado por proprietário") -> 0 | I68: =SUM(E68:H68) -> 0 | J68: =IF(D68=0, "-", COUNTIFS('Base Lojas'!B:B, A68, 'Base Lojas'!G:G, ">500000")/D68) -> 0 | K68: 441391.84 | L68: 0.05742997 | M68: 7685740.4 | N68: 55033 | O68: =_xlfn.XLOOKUP(A68,Cidades!A:A,Cidades!D:D) -> Entre 50k e 100k | P68: =_xlfn.XLOOKUP(A68,'[1]1° RAIZ'!$A:$A,'[1]1° RAIZ'!$AH:$AH) -> União da Vitória | Q68: =_xlfn.XLOOKUP(A68,'[1]1° RAIZ'!$A:$A,'[1]1° RAIZ'!$AE:$AE) -> Curitiba | R68: 3.2600997e-05 | S68: 0.0089537563 | T68: 28 | U68: 2 | V68: 39013.276 | W68: 3.3861812 | X68: 0.36089664 | Y68: -0.27143512 | Z68: -0.39859126 | AA68: 0.06912386 | AB68: =IF(B68="Capão do Leão","Erro IBGE", IF(AND(U68<=0,M68<=2000000),"Mercado insuficiente", IF(U68<=0,"Limite de expansão", IF(K68<500000,"Performance", IF(M68<=2000000,"Mercado insuficiente","Expansão") ) ) ) ) -> Performance | AC68: =IF(P68=B68,"Oportunidade","Validar") -> Oportunidade
A69: 421970 | B69: Xaxim | C69: SC | D69: 0 | E69: =COUNTIFS('Contratos assinados '!F:F,'Direcional Expansão'!B69,'Contratos assinados '!J:J, "Assinado por ambos") -> 0 | F69: =COUNTIFS('Contratos assinados '!F:F,'Direcional Expansão'!B69,'Contratos assinados '!J:J,"Aquisição") -> 0 | G69: =COUNTIFS('Contratos assinados '!F:F,'Direcional Expansão'!B69,'Contratos assinados '!J:J,"Ampliação") -> 0 | H69: =COUNTIFS('Contratos assinados '!F:F,'Direcional Expansão'!B69,'Contratos assinados '!J:J,"Assinado por proprietário") -> 0 | I69: =SUM(E69:H69) -> 0 | J69: =IF(D69=0, "-", COUNTIFS('Base Lojas'!B:B, A69, 'Base Lojas'!I:I, ">500000")/D69) -> - | K69: - | L69: 0 | M69: 5245539.5 | N69: 31918 | O69: =_xlfn.XLOOKUP(A69,Cidades!A:A,Cidades!D:D) -> Entre 30k e 50k | P69: =_xlfn.XLOOKUP(A69,'[1]1° RAIZ'!$A:$A,'[1]1° RAIZ'!$AH:$AH) -> Chapecó | Q69: =_xlfn.XLOOKUP(A69,'[1]1° RAIZ'!$A:$A,'[1]1° RAIZ'!$AE:$AE) -> Chapecó | R69: 0.00016816435 | S69: 0.019200576 | T69: 14 | U69: 2 | V69: 48512.624 | W69: 3.9105678 | X69: 0.22015361 | Y69: 0.37098554 | Z69: -0.7451509 | AA69: 0.062089305 | AB69: =IF(B69="Capão do Leão","Erro IBGE", IF(AND(U69<=0,M69<=2000000),"Mercado insuficiente", IF(U69<=0,"Limite de expansão", IF(K69<500000,"Performance", IF(M69<=2000000,"Mercado insuficiente","Expansão") ) ) ) ) -> Expansão | AC69: =IF(P69=B69,"Oportunidade","Validar") -> Validar
A70: 412410 | B70: Santo Antônio da Platina | C70: PR | D70: 0 | E70: =COUNTIFS('Contratos assinados '!F:F,'Direcional Expansão'!B70,'Contratos assinados '!J:J, "Assinado por ambos") -> 0 | F70: =COUNTIFS('Contratos assinados '!F:F,'Direcional Expansão'!B70,'Contratos assinados '!J:J,"Aquisição") -> 0 | G70: =COUNTIFS('Contratos assinados '!F:F,'Direcional Expansão'!B70,'Contratos assinados '!J:J,"Ampliação") -> 0 | H70: =COUNTIFS('Contratos assinados '!F:F,'Direcional Expansão'!B70,'Contratos assinados '!J:J,"Assinado por proprietário") -> 0 | I70: =SUM(E70:H70) -> 0 | J70: =IF(D70=0, "-", COUNTIFS('Base Lojas'!B:B, A70, 'Base Lojas'!I:I, ">500000")/D70) -> - | K70: - | L70: 0 | M70: 5928799.9 | N70: 44369 | O70: =_xlfn.XLOOKUP(A70,Cidades!A:A,Cidades!D:D) -> Entre 30k e 50k | P70: =_xlfn.XLOOKUP(A70,'[1]1° RAIZ'!$A:$A,'[1]1° RAIZ'!$AH:$AH) -> Santo Antônio da Platina | Q70: =_xlfn.XLOOKUP(A70,'[1]1° RAIZ'!$A:$A,'[1]1° RAIZ'!$AE:$AE) -> Londrina | R70: 2.9754315e-05 | S70: 0.0079185813 | T70: 16 | U70: 2 | V70: 37107.228 | W70: 3.8145906 | X70: 0.24885006 | Y70: -0.11564311 | Z70: -0.61233358 | AA70: 0.019428494 | AB70: =IF(B70="Capão do Leão","Erro IBGE", IF(AND(U70<=0,M70<=2000000),"Mercado insuficiente", IF(U70<=0,"Limite de expansão", IF(K70<500000,"Performance", IF(M70<=2000000,"Mercado insuficiente","Expansão") ) ) ) ) -> Expansão | AC70: =IF(P70=B70,"Oportunidade","Validar") -> Oportunidade
A71: 420480 | B71: Curitibanos | C71: SC | D71: 0 | E71: =COUNTIFS('Contratos assinados '!F:F,'Direcional Expansão'!B71,'Contratos assinados '!J:J, "Assinado por ambos") -> 0 | F71: =COUNTIFS('Contratos assinados '!F:F,'Direcional Expansão'!B71,'Contratos assinados '!J:J,"Aquisição") -> 0 | G71: =COUNTIFS('Contratos assinados '!F:F,'Direcional Expansão'!B71,'Contratos assinados '!J:J,"Ampliação") -> 0 | H71: =COUNTIFS('Contratos assinados '!F:F,'Direcional Expansão'!B71,'Contratos assinados '!J:J,"Assinado por proprietário") -> 0 | I71: =SUM(E71:H71) -> 0 | J71: =IF(D71=0, "-", COUNTIFS('Base Lojas'!B:B, A71, 'Base Lojas'!I:I, ">500000")/D71) -> - | K71: - | L71: 0 | M71: 5670523.2 | N71: 40045 | O71: =_xlfn.XLOOKUP(A71,Cidades!A:A,Cidades!D:D) -> Entre 30k e 50k | P71: =_xlfn.XLOOKUP(A71,'[1]1° RAIZ'!$A:$A,'[1]1° RAIZ'!$AH:$AH) -> Curitibanos | Q71: =_xlfn.XLOOKUP(A71,'[1]1° RAIZ'!$A:$A,'[1]1° RAIZ'!$AE:$AE) -> Lages | R71: 4.5010832e-05 | S71: 0.0082179844 | T71: 15 | U71: 2 | V71: 50435.189 | W71: 3.4555052 | X71: 0.1838955 | Y71: -0.13127679 | Z71: -0.43063015 | AA71: 0.010259258 | AB71: =IF(B71="Capão do Leão","Erro IBGE", IF(AND(U71<=0,M71<=2000000),"Mercado insuficiente", IF(U71<=0,"Limite de expansão", IF(K71<500000,"Performance", IF(M71<=2000000,"Mercado insuficiente","Expansão") ) ) ) ) -> Expansão | AC71: =IF(P71=B71,"Oportunidade","Validar") -> Oportunidade
A72: 411570 | B72: Matinhos | C72: PR | D72: 0 | E72: =COUNTIFS('Contratos assinados '!F:F,'Direcional Expansão'!B72,'Contratos assinados '!J:J, "Assinado por ambos") -> 0 | F72: =COUNTIFS('Contratos assinados '!F:F,'Direcional Expansão'!B72,'Contratos assinados '!J:J,"Aquisição") -> 0 | G72: =COUNTIFS('Contratos assinados '!F:F,'Direcional Expansão'!B72,'Contratos assinados '!J:J,"Ampliação") -> 0 | H72: =COUNTIFS('Contratos assinados '!F:F,'Direcional Expansão'!B72,'Contratos assinados '!J:J,"Assinado por proprietário") -> 0 | I72: =SUM(E72:H72) -> 0 | J72: =IF(D72=0, "-", COUNTIFS('Base Lojas'!B:B, A72, 'Base Lojas'!I:I, ">500000")/D72) -> - | K72: - | L72: 0 | M72: 5503287 | N72: 39259 | O72: =_xlfn.XLOOKUP(A72,Cidades!A:A,Cidades!D:D) -> Entre 30k e 50k | P72: =_xlfn.XLOOKUP(A72,'[1]1° RAIZ'!$A:$A,'[1]1° RAIZ'!$AH:$AH) -> Paranaguá | Q72: =_xlfn.XLOOKUP(A72,'[1]1° RAIZ'!$A:$A,'[1]1° RAIZ'!$AE:$AE) -> Curitiba | R72: 0.00022424823 | S72: 0.025570105 | T72: 21 | U72: 2 | V72: 23847.507 | W72: 3.8406263 | X72: 0.29569448 | Y72: 0.20980075 | Z72: -1.2789256 | AA72: 0.010122242 | AB72: =IF(B72="Capão do Leão","Erro IBGE", IF(AND(U72<=0,M72<=2000000),"Mercado insuficiente", IF(U72<=0,"Limite de expansão", IF(K72<500000,"Performance", IF(M72<=2000000,"Mercado insuficiente","Expansão") ) ) ) ) -> Expansão | AC72: =IF(P72=B72,"Oportunidade","Validar") -> Validar
A73: 410960 | B73: Guaratuba | C73: PR | D73: 0 | E73: =COUNTIFS('Contratos assinados '!F:F,'Direcional Expansão'!B73,'Contratos assinados '!J:J, "Assinado por ambos") -> 0 | F73: =COUNTIFS('Contratos assinados '!F:F,'Direcional Expansão'!B73,'Contratos assinados '!J:J,"Aquisição") -> 0 | G73: =COUNTIFS('Contratos assinados '!F:F,'Direcional Expansão'!B73,'Contratos assinados '!J:J,"Ampliação") -> 0 | H73: =COUNTIFS('Contratos assinados '!F:F,'Direcional Expansão'!B73,'Contratos assinados '!J:J,"Assinado por proprietário") -> 0 | I73: =SUM(E73:H73) -> 0 | J73: =IF(D73=0, "-", COUNTIFS('Base Lojas'!B:B, A73, 'Base Lojas'!I:I, ">500000")/D73) -> - | K73: - | L73: 0 | M73: 5813744.3 | N73: 42062 | O73: =_xlfn.XLOOKUP(A73,Cidades!A:A,Cidades!D:D) -> Entre 30k e 50k | P73: =_xlfn.XLOOKUP(A73,'[1]1° RAIZ'!$A:$A,'[1]1° RAIZ'!$AH:$AH) -> Paranaguá | Q73: =_xlfn.XLOOKUP(A73,'[1]1° RAIZ'!$A:$A,'[1]1° RAIZ'!$AE:$AE) -> Curitiba | R73: 0.00021038452 | S73: 0.024788179 | T73: 18 | U73: 2 | V73: 24542.294 | W73: 3.6039368 | X73: 0.25346881 | Y73: 0.074106275 | Z73: -1.2400009 | AA73: -0.022948792 | AB73: =IF(B73="Capão do Leão","Erro IBGE", IF(AND(U73<=0,M73<=2000000),"Mercado insuficiente", IF(U73<=0,"Limite de expansão", IF(K73<500000,"Performance", IF(M73<=2000000,"Mercado insuficiente","Expansão") ) ) ) ) -> Expansão | AC73: =IF(P73=B73,"Oportunidade","Validar") -> Validar
A74: 420550 | B74: Fraiburgo | C74: SC | D74: 0 | E74: =COUNTIFS('Contratos assinados '!F:F,'Direcional Expansão'!B74,'Contratos assinados '!J:J, "Assinado por ambos") -> 0 | F74: =COUNTIFS('Contratos assinados '!F:F,'Direcional Expansão'!B74,'Contratos assinados '!J:J,"Aquisição") -> 0 | G74: =COUNTIFS('Contratos assinados '!F:F,'Direcional Expansão'!B74,'Contratos assinados '!J:J,"Ampliação") -> 0 | H74: =COUNTIFS('Contratos assinados '!F:F,'Direcional Expansão'!B74,'Contratos assinados '!J:J,"Assinado por proprietário") -> 0 | I74: =SUM(E74:H74) -> 0 | J74: =IF(D74=0, "-", COUNTIFS('Base Lojas'!B:B, A74, 'Base Lojas'!I:I, ">500000")/D74) -> - | K74: - | L74: 0 | M74: 4742723.6 | N74: 33481 | O74: =_xlfn.XLOOKUP(A74,Cidades!A:A,Cidades!D:D) -> Entre 30k e 50k | P74: =_xlfn.XLOOKUP(A74,'[1]1° RAIZ'!$A:$A,'[1]1° RAIZ'!$AH:$AH) -> Videira | Q74: =_xlfn.XLOOKUP(A74,'[1]1° RAIZ'!$A:$A,'[1]1° RAIZ'!$AE:$AE) -> Caçador | R74: -2.4258332e-05 | S74: 0.0035470059 | T74: 16 | U74: 2 | V74: 41978.496 | W74: 3.5341197 | X74: 0.15507688 | Y74: -0.31204688 | Z74: -0.42066845 | AA74: -0.026896649 | AB74: =IF(B74="Capão do Leão","Erro IBGE", IF(AND(U74<=0,M74<=2000000),"Mercado insuficiente", IF(U74<=0,"Limite de expansão", IF(K74<500000,"Performance", IF(M74<=2000000,"Mercado insuficiente","Expansão") ) ) ) ) -> Expansão | AC74: =IF(P74=B74,"Oportunidade","Validar") -> Validar
A75: 421500 | B75: Rio Negrinho | C75: SC | D75: 0 | E75: =COUNTIFS('Contratos assinados '!F:F,'Direcional Expansão'!B75,'Contratos assinados '!J:J, "Assinado por ambos") -> 0 | F75: =COUNTIFS('Contratos assinados '!F:F,'Direcional Expansão'!B75,'Contratos assinados '!J:J,"Aquisição") -> 0 | G75: =COUNTIFS('Contratos assinados '!F:F,'Direcional Expansão'!B75,'Contratos assinados '!J:J,"Ampliação") -> 0 | H75: =COUNTIFS('Contratos assinados '!F:F,'Direcional Expansão'!B75,'Contratos assinados '!J:J,"Assinado por proprietário") -> 0 | I75: =SUM(E75:H75) -> 0 | J75: =IF(D75=0, "-", COUNTIFS('Base Lojas'!B:B, A75, 'Base Lojas'!I:I, ">500000")/D75) -> - | K75: - | L75: 0 | M75: 5453667.9 | N75: 39258 | O75: =_xlfn.XLOOKUP(A75,Cidades!A:A,Cidades!D:D) -> Entre 30k e 50k | P75: =_xlfn.XLOOKUP(A75,'[1]1° RAIZ'!$A:$A,'[1]1° RAIZ'!$AH:$AH) -> São Bento do Sul - Rio Negrinho | Q75: =_xlfn.XLOOKUP(A75,'[1]1° RAIZ'!$A:$A,'[1]1° RAIZ'!$AE:$AE) -> Joinville | R75: -1.1487294e-05 | S75: 0.0043262666 | T75: 9 | U75: 2 | V75: 45170.711 | W75: 3.4653885 | X75: 0.12194665 | Y75: -0.28079237 | Z75: -0.39394411 | AA75: -0.033456448 | AB75: =IF(B75="Capão do Leão","Erro IBGE", IF(AND(U75<=0,M75<=2000000),"Mercado insuficiente", IF(U75<=0,"Limite de expansão", IF(K75<500000,"Performance", IF(M75<=2000000,"Mercado insuficiente","Expansão") ) ) ) ) -> Expansão | AC75: =IF(P75=B75,"Oportunidade","Validar") -> Validar
A76: 411200 | B76: Jaguariaíva | C76: PR | D76: 0 | E76: =COUNTIFS('Contratos assinados '!F:F,'Direcional Expansão'!B76,'Contratos assinados '!J:J, "Assinado por ambos") -> 0 | F76: =COUNTIFS('Contratos assinados '!F:F,'Direcional Expansão'!B76,'Contratos assinados '!J:J,"Aquisição") -> 0 | G76: =COUNTIFS('Contratos assinados '!F:F,'Direcional Expansão'!B76,'Contratos assinados '!J:J,"Ampliação") -> 0 | H76: =COUNTIFS('Contratos assinados '!F:F,'Direcional Expansão'!B76,'Contratos assinados '!J:J,"Assinado por proprietário") -> 0 | I76: =SUM(E76:H76) -> 0 | J76: =IF(D76=0, "-", COUNTIFS('Base Lojas'!B:B, A76, 'Base Lojas'!I:I, ">500000")/D76) -> - | K76: - | L76: 0 | M76: 4611509.2 | N76: 35141 | O76: =_xlfn.XLOOKUP(A76,Cidades!A:A,Cidades!D:D) -> Entre 30k e 50k | P76: =_xlfn.XLOOKUP(A76,'[1]1° RAIZ'!$A:$A,'[1]1° RAIZ'!$AH:$AH) -> Ponta Grossa | Q76: =_xlfn.XLOOKUP(A76,'[1]1° RAIZ'!$A:$A,'[1]1° RAIZ'!$AE:$AE) -> Ponta Grossa | R76: 5.7522947e-05 | S76: 0.0099171088 | T76: 15 | U76: 2 | V76: 55280.504 | W76: 3.0554063 | X76: 0.10568438 | Y76: -0.24021646 | Z76: -0.39338914 | AA76: -0.034478401 | AB76: =IF(B76="Capão do Leão","Erro IBGE", IF(AND(U76<=0,M76<=2000000),"Mercado insuficiente", IF(U76<=0,"Limite de expansão", IF(K76<500000,"Performance", IF(M76<=2000000,"Mercado insuficiente","Expansão") ) ) ) ) -> Expansão | AC76: =IF(P76=B76,"Oportunidade","Validar") -> Validar
A77: 411995 | B77: Pontal do Paraná | C77: PR | D77: 0 | E77: =COUNTIFS('Contratos assinados '!F:F,'Direcional Expansão'!B77,'Contratos assinados '!J:J, "Assinado por ambos") -> 0 | F77: =COUNTIFS('Contratos assinados '!F:F,'Direcional Expansão'!B77,'Contratos assinados '!J:J,"Aquisição") -> 0 | G77: =COUNTIFS('Contratos assinados '!F:F,'Direcional Expansão'!B77,'Contratos assinados '!J:J,"Ampliação") -> 0 | H77: =COUNTIFS('Contratos assinados '!F:F,'Direcional Expansão'!B77,'Contratos assinados '!J:J,"Assinado por proprietário") -> 0 | I77: =SUM(E77:H77) -> 0 | J77: =IF(D77=0, "-", COUNTIFS('Base Lojas'!B:B, A77, 'Base Lojas'!I:I, ">500000")/D77) -> - | K77: - | L77: 0 | M77: 4221992.7 | N77: 30425 | O77: =_xlfn.XLOOKUP(A77,Cidades!A:A,Cidades!D:D) -> Entre 30k e 50k | P77: =_xlfn.XLOOKUP(A77,'[1]1° RAIZ'!$A:$A,'[1]1° RAIZ'!$AH:$AH) -> Paranaguá | Q77: =_xlfn.XLOOKUP(A77,'[1]1° RAIZ'!$A:$A,'[1]1° RAIZ'!$AE:$AE) -> Curitiba | R77: 0.00029235103 | S77: 0.030413966 | T77: 20 | U77: 2 | V77: 22189.695 | W77: 3.6237726 | X77: 0.22301181 | Y77: 0.24586956 | Z77: -1.4605437 | AA77: -0.03637427 | AB77: =IF(B77="Capão do Leão","Erro IBGE", IF(AND(U77<=0,M77<=2000000),"Mercado insuficiente", IF(U77<=0,"Limite de expansão", IF(K77<500000,"Performance", IF(M77<=2000000,"Mercado insuficiente","Expansão") ) ) ) ) -> Expansão | AC77: =IF(P77=B77,"Oportunidade","Validar") -> Validar
A78: 411750 | B78: Paiçandu | C78: PR | D78: 1 | E78: =COUNTIFS('Contratos assinados '!F:F,'Direcional Expansão'!B78,'Contratos assinados '!J:J, "Assinado por ambos") -> 0 | F78: =COUNTIFS('Contratos assinados '!F:F,'Direcional Expansão'!B78,'Contratos assinados '!J:J,"Aquisição") -> 0 | G78: =COUNTIFS('Contratos assinados '!F:F,'Direcional Expansão'!B78,'Contratos assinados '!J:J,"Ampliação") -> 0 | H78: =COUNTIFS('Contratos assinados '!F:F,'Direcional Expansão'!B78,'Contratos assinados '!J:J,"Assinado por proprietário") -> 0 | I78: =SUM(E78:H78) -> 0 | J78: =IF(D78=0, "-", COUNTIFS('Base Lojas'!B:B, A78, 'Base Lojas'!G:G, ">500000")/D78) -> 0 | K78: 482403.63 | L78: 0.078706892 | M78: 6129115.5 | N78: 45962 | O78: =_xlfn.XLOOKUP(A78,Cidades!A:A,Cidades!D:D) -> Entre 30k e 50k | P78: =_xlfn.XLOOKUP(A78,'[1]1° RAIZ'!$A:$A,'[1]1° RAIZ'!$AH:$AH) -> Maringá | Q78: =_xlfn.XLOOKUP(A78,'[1]1° RAIZ'!$A:$A,'[1]1° RAIZ'!$AE:$AE) -> Maringá | R78: 0.00019098257 | S78: 0.022638917 | T78: 9 | U78: 2 | V78: 24356.713 | W78: 3.0537933 | X78: 0.13925991 | Y78: -0.13568368 | Z78: -0.93402665 | AA78: -0.066853961 | AB78: =IF(B78="Capão do Leão","Erro IBGE", IF(AND(U78<=0,M78<=2000000),"Mercado insuficiente", IF(U78<=0,"Limite de expansão", IF(K78<500000,"Performance", IF(M78<=2000000,"Mercado insuficiente","Expansão") ) ) ) ) -> Performance | AC78: =IF(P78=B78,"Oportunidade","Validar") -> Validar
A79: 412060 | B79: Prudentópolis | C79: PR | D79: 1 | E79: =COUNTIFS('Contratos assinados '!F:F,'Direcional Expansão'!B79,'Contratos assinados '!J:J, "Assinado por ambos") -> 0 | F79: =COUNTIFS('Contratos assinados '!F:F,'Direcional Expansão'!B79,'Contratos assinados '!J:J,"Aquisição") -> 0 | G79: =COUNTIFS('Contratos assinados '!F:F,'Direcional Expansão'!B79,'Contratos assinados '!J:J,"Ampliação") -> 0 | H79: =COUNTIFS('Contratos assinados '!F:F,'Direcional Expansão'!B79,'Contratos assinados '!J:J,"Assinado por proprietário") -> 0 | I79: =SUM(E79:H79) -> 0 | J79: =IF(D79=0, "-", COUNTIFS('Base Lojas'!B:B, A79, 'Base Lojas'!I:I, ">500000")/D79) -> 1 | K79: 619280.67 | L79: 0.11168466 | M79: 5544903.7 | N79: 49393 | O79: =_xlfn.XLOOKUP(A79,Cidades!A:A,Cidades!D:D) -> Entre 30k e 50k | P79: =_xlfn.XLOOKUP(A79,'[1]1° RAIZ'!$A:$A,'[1]1° RAIZ'!$AH:$AH) -> Guarapuava | Q79: =_xlfn.XLOOKUP(A79,'[1]1° RAIZ'!$A:$A,'[1]1° RAIZ'!$AE:$AE) -> Guarapuava | R79: 9.4058467e-06 | S79: 0.0079397131 | T79: 16 | U79: 2 | V79: 35068.432 | W79: 2.5992082 | X79: 0.12104346 | Y79: -0.63539622 | Z79: -0.24735182 | AA79: -0.068147005 | AB79: =IF(B79="Capão do Leão","Erro IBGE", IF(AND(U79<=0,M79<=2000000),"Mercado insuficiente", IF(U79<=0,"Limite de expansão", IF(K79<500000,"Performance", IF(M79<=2000000,"Mercado insuficiente","Expansão") ) ) ) ) -> Expansão | AC79: =IF(P79=B79,"Oportunidade","Validar") -> Validar
A80: 410240 | B80: Bandeirantes | C80: PR | D80: 0 | E80: =COUNTIFS('Contratos assinados '!F:F,'Direcional Expansão'!B80,'Contratos assinados '!J:J, "Assinado por ambos") -> 0 | F80: =COUNTIFS('Contratos assinados '!F:F,'Direcional Expansão'!B80,'Contratos assinados '!J:J,"Aquisição") -> 0 | G80: =COUNTIFS('Contratos assinados '!F:F,'Direcional Expansão'!B80,'Contratos assinados '!J:J,"Ampliação") -> 0 | H80: =COUNTIFS('Contratos assinados '!F:F,'Direcional Expansão'!B80,'Contratos assinados '!J:J,"Assinado por proprietário") -> 0 | I80: =SUM(E80:H80) -> 0 | J80: =IF(D80=0, "-", COUNTIFS('Base Lojas'!B:B, A80, 'Base Lojas'!I:I, ">500000")/D80) -> - | K80: - | L80: 0 | M80: 3886845.1 | N80: 31273 | O80: =_xlfn.XLOOKUP(A80,Cidades!A:A,Cidades!D:D) -> Entre 30k e 50k | P80: =_xlfn.XLOOKUP(A80,'[1]1° RAIZ'!$A:$A,'[1]1° RAIZ'!$AH:$AH) -> Cornélio Procópio – Bandeirantes | Q80: =_xlfn.XLOOKUP(A80,'[1]1° RAIZ'!$A:$A,'[1]1° RAIZ'!$AE:$AE) -> Londrina | R80: -2.2015871e-05 | S80: 0.003552074 | T80: 9 | U80: 2 | V80: 36628.103 | W80: 3.3964077 | X80: 0.060861973 | Y80: -0.40762969 | Z80: -0.51391721 | AA80: -0.091424589 | AB80: =IF(B80="Capão do Leão","Erro IBGE", IF(AND(U80<=0,M80<=2000000),"Mercado insuficiente", IF(U80<=0,"Limite de expansão", IF(K80<500000,"Performance", IF(M80<=2000000,"Mercado insuficiente","Expansão") ) ) ) ) -> Expansão | AC80: =IF(P80=B80,"Oportunidade","Validar") -> Validar
A81: 411960 | B81: Pitanga | C81: PR | D81: 0 | E81: =COUNTIFS('Contratos assinados '!F:F,'Direcional Expansão'!B81,'Contratos assinados '!J:J, "Assinado por ambos") -> 0 | F81: =COUNTIFS('Contratos assinados '!F:F,'Direcional Expansão'!B81,'Contratos assinados '!J:J,"Aquisição") -> 0 | G81: =COUNTIFS('Contratos assinados '!F:F,'Direcional Expansão'!B81,'Contratos assinados '!J:J,"Ampliação") -> 0 | H81: =COUNTIFS('Contratos assinados '!F:F,'Direcional Expansão'!B81,'Contratos assinados '!J:J,"Assinado por proprietário") -> 0 | I81: =SUM(E81:H81) -> 0 | J81: =IF(D81=0, "-", COUNTIFS('Base Lojas'!B:B, A81, 'Base Lojas'!I:I, ">500000")/D81) -> - | K81: - | L81: 0 | M81: 4062805.8 | N81: 33567 | O81: =_xlfn.XLOOKUP(A81,Cidades!A:A,Cidades!D:D) -> Entre 30k e 50k | P81: =_xlfn.XLOOKUP(A81,'[1]1° RAIZ'!$A:$A,'[1]1° RAIZ'!$AH:$AH) -> Pitanga | Q81: =_xlfn.XLOOKUP(A81,'[1]1° RAIZ'!$A:$A,'[1]1° RAIZ'!$AE:$AE) -> Guarapuava | R81: 2.144738e-05 | S81: 0.0087584235 | T81: 13 | U81: 2 | V81: 37059.734 | W81: 3.1276303 | X81: 0.075794473 | Y81: -0.43821235 | Z81: -0.61899937 | AA81: -0.10146373 | AB81: =IF(B81="Capão do Leão","Erro IBGE", IF(AND(U81<=0,M81<=2000000),"Mercado insuficiente", IF(U81<=0,"Limite de expansão", IF(K81<500000,"Performance", IF(M81<=2000000,"Mercado insuficiente","Expansão") ) ) ) ) -> Expansão | AC81: =IF(P81=B81,"Oportunidade","Validar") -> Oportunidade
A82: 412220 | B82: Rio Branco do Sul | C82: PR | D82: 0 | E82: =COUNTIFS('Contratos assinados '!F:F,'Direcional Expansão'!B82,'Contratos assinados '!J:J, "Assinado por ambos") -> 0 | F82: =COUNTIFS('Contratos assinados '!F:F,'Direcional Expansão'!B82,'Contratos assinados '!J:J,"Aquisição") -> 0 | G82: =COUNTIFS('Contratos assinados '!F:F,'Direcional Expansão'!B82,'Contratos assinados '!J:J,"Ampliação") -> 0 | H82: =COUNTIFS('Contratos assinados '!F:F,'Direcional Expansão'!B82,'Contratos assinados '!J:J,"Assinado por proprietário") -> 0 | I82: =SUM(E82:H82) -> 0 | J82: =IF(D82=0, "-", COUNTIFS('Base Lojas'!B:B, A82, 'Base Lojas'!I:I, ">500000")/D82) -> - | K82: - | L82: 0 | M82: 4617064.7 | N82: 37558 | O82: =_xlfn.XLOOKUP(A82,Cidades!A:A,Cidades!D:D) -> Entre 30k e 50k | P82: =_xlfn.XLOOKUP(A82,'[1]1° RAIZ'!$A:$A,'[1]1° RAIZ'!$AH:$AH) -> Curitiba | Q82: =_xlfn.XLOOKUP(A82,'[1]1° RAIZ'!$A:$A,'[1]1° RAIZ'!$AE:$AE) -> Curitiba | R82: 0.00015727183 | S82: 0.021404108 | T82: 8 | U82: 2 | V82: 38891.713 | W82: 2.9279791 | X82: 0.052895368 | Y82: -0.19807445 | Z82: -0.90731954 | AA82: -0.10956637 | AB82: =IF(B82="Capão do Leão","Erro IBGE", IF(AND(U82<=0,M82<=2000000),"Mercado insuficiente", IF(U82<=0,"Limite de expansão", IF(K82<500000,"Performance", IF(M82<=2000000,"Mercado insuficiente","Expansão") ) ) ) ) -> Expansão | AC82: =IF(P82=B82,"Oportunidade","Validar") -> Validar
A83: 411150 | B83: Ivaiporã | C83: PR | D83: 0 | E83: =COUNTIFS('Contratos assinados '!F:F,'Direcional Expansão'!B83,'Contratos assinados '!J:J, "Assinado por ambos") -> 0 | F83: =COUNTIFS('Contratos assinados '!F:F,'Direcional Expansão'!B83,'Contratos assinados '!J:J,"Aquisição") -> 0 | G83: =COUNTIFS('Contratos assinados '!F:F,'Direcional Expansão'!B83,'Contratos assinados '!J:J,"Ampliação") -> 0 | H83: =COUNTIFS('Contratos assinados '!F:F,'Direcional Expansão'!B83,'Contratos assinados '!J:J,"Assinado por proprietário") -> 0 | I83: =SUM(E83:H83) -> 0 | J83: =IF(D83=0, "-", COUNTIFS('Base Lojas'!B:B, A83, 'Base Lojas'!I:I, ">500000")/D83) -> - | K83: - | L83: 0 | M83: 5085950.4 | N83: 32720 | O83: =_xlfn.XLOOKUP(A83,Cidades!A:A,Cidades!D:D) -> Entre 30k e 50k | P83: =_xlfn.XLOOKUP(A83,'[1]1° RAIZ'!$A:$A,'[1]1° RAIZ'!$AH:$AH) -> Ivaiporã | Q83: =_xlfn.XLOOKUP(A83,'[1]1° RAIZ'!$A:$A,'[1]1° RAIZ'!$AE:$AE) -> Londrina | R83: 2.1671861e-05 | S83: 0.0068679234 | T83: 11 | U83: 2 | V83: 31748.302 | W83: 3.078098 | X83: 0.064012535 | Y83: -0.53133035 | Z83: -0.68875576 | AA83: -0.12784838 | AB83: =IF(B83="Capão do Leão","Erro IBGE", IF(AND(U83<=0,M83<=2000000),"Mercado insuficiente", IF(U83<=0,"Limite de expansão", IF(K83<500000,"Performance", IF(M83<=2000000,"Mercado insuficiente","Expansão") ) ) ) ) -> Expansão | AC83: =IF(P83=B83,"Oportunidade","Validar") -> Oportunidade
A84: 411125 | B84: Itaperuçu | C84: PR | D84: 0 | E84: =COUNTIFS('Contratos assinados '!F:F,'Direcional Expansão'!B84,'Contratos assinados '!J:J, "Assinado por ambos") -> 0 | F84: =COUNTIFS('Contratos assinados '!F:F,'Direcional Expansão'!B84,'Contratos assinados '!J:J,"Aquisição") -> 0 | G84: =COUNTIFS('Contratos assinados '!F:F,'Direcional Expansão'!B84,'Contratos assinados '!J:J,"Ampliação") -> 0 | H84: =COUNTIFS('Contratos assinados '!F:F,'Direcional Expansão'!B84,'Contratos assinados '!J:J,"Assinado por proprietário") -> 0 | I84: =SUM(E84:H84) -> 0 | J84: =IF(D84=0, "-", COUNTIFS('Base Lojas'!B:B, A84, 'Base Lojas'!I:I, ">500000")/D84) -> - | K84: - | L84: 0 | M84: 3716137.4 | N84: 31217 | O84: =_xlfn.XLOOKUP(A84,Cidades!A:A,Cidades!D:D) -> Entre 30k e 50k | P84: =_xlfn.XLOOKUP(A84,'[1]1° RAIZ'!$A:$A,'[1]1° RAIZ'!$AH:$AH) -> Curitiba | Q84: =_xlfn.XLOOKUP(A84,'[1]1° RAIZ'!$A:$A,'[1]1° RAIZ'!$AE:$AE) -> Curitiba | R84: 0.00020760736 | S84: 0.024760696 | T84: 9 | U84: 2 | V84: 21112.528 | W84: 2.5430769 | X84: -0.019039875 | Y84: -0.453112 | Z84: -1.3072743 | AA84: -0.22257227 | AB84: =IF(B84="Capão do Leão","Erro IBGE", IF(AND(U84<=0,M84<=2000000),"Mercado insuficiente", IF(U84<=0,"Limite de expansão", IF(K84<500000,"Performance", IF(M84<=2000000,"Mercado insuficiente","Expansão") ) ) ) ) -> Expansão | AC84: =IF(P84=B84,"Oportunidade","Validar") -> Validar
A85: 420830 | B85: Itapema | C85: SC | D85: 4 | E85: =COUNTIFS('Contratos assinados '!F:F,'Direcional Expansão'!B85,'Contratos assinados '!J:J, "Assinado por ambos") -> 1 | F85: =COUNTIFS('Contratos assinados '!F:F,'Direcional Expansão'!B85,'Contratos assinados '!J:J,"Aquisição") -> 0 | G85: =COUNTIFS('Contratos assinados '!F:F,'Direcional Expansão'!B85,'Contratos assinados '!J:J,"Ampliação") -> 0 | H85: =COUNTIFS('Contratos assinados '!F:F,'Direcional Expansão'!B85,'Contratos assinados '!J:J,"Assinado por proprietário") -> 0 | I85: =SUM(E85:H85) -> 1 | J85: =IF(D85=0, "-", COUNTIFS('Base Lojas'!B:B, A85, 'Base Lojas'!I:I, ">500000")/D85) -> 1 | K85: 850572.62 | L85: 0.24011116 | M85: 14169648 | N85: 75940 | O85: =_xlfn.XLOOKUP(A85,Cidades!A:A,Cidades!D:D) -> Entre 50k e 100k | P85: =_xlfn.XLOOKUP(A85,'[1]1° RAIZ'!$A:$A,'[1]1° RAIZ'!$AH:$AH) -> Itajaí | Q85: =_xlfn.XLOOKUP(A85,'[1]1° RAIZ'!$A:$A,'[1]1° RAIZ'!$AE:$AE) -> Blumenau | R85: 0.00039638828 | S85: 0.035867065 | T85: 59 | U85: 1 | V85: 37621.135 | W85: 5.1762288 | X85: 1.023711 | Y85: 1.5304998 | Z85: -0.54803252 | AA85: 0.59371142 | AB85: =IF(B85="Capão do Leão","Erro IBGE", IF(AND(U85<=0,M85<=2000000),"Mercado insuficiente", IF(U85<=0,"Limite de expansão", IF(K85<500000,"Performance", IF(M85<=2000000,"Mercado insuficiente","Expansão") ) ) ) ) -> Expansão | AC85: =IF(P85=B85,"Oportunidade","Validar") -> Validar
A86: 410140 | B86: Apucarana | C86: PR | D86: 7 | E86: =COUNTIFS('Contratos assinados '!F:F,'Direcional Expansão'!B86,'Contratos assinados '!J:J, "Assinado por ambos") -> 1 | F86: =COUNTIFS('Contratos assinados '!F:F,'Direcional Expansão'!B86,'Contratos assinados '!J:J,"Aquisição") -> 0 | G86: =COUNTIFS('Contratos assinados '!F:F,'Direcional Expansão'!B86,'Contratos assinados '!J:J,"Ampliação") -> 0 | H86: =COUNTIFS('Contratos assinados '!F:F,'Direcional Expansão'!B86,'Contratos assinados '!J:J,"Assinado por proprietário") -> 0 | I86: =SUM(E86:H86) -> 1 | J86: =IF(D86=0, "-", COUNTIFS('Base Lojas'!B:B, A86, 'Base Lojas'!I:I, ">500000")/D86) -> 0.57142857 | K86: 561401.73 | L86: 0.2170567 | M86: 18105003 | N86: 130134 | O86: =_xlfn.XLOOKUP(A86,Cidades!A:A,Cidades!D:D) -> Entre 100k e 150k | P86: =_xlfn.XLOOKUP(A86,'[1]1° RAIZ'!$A:$A,'[1]1° RAIZ'!$AH:$AH) -> Apucarana | Q86: =_xlfn.XLOOKUP(A86,'[1]1° RAIZ'!$A:$A,'[1]1° RAIZ'!$AE:$AE) -> Londrina | R86: 5.6879059e-05 | S86: 0.010374094 | T86: 56 | U86: 1 | V86: 32280.437 | W86: 3.9614292 | X86: 1.0180681 | Y86: 0.048762033 | Z86: 0.048903091 | AA86: 0.44617634 | AB86: =IF(B86="Capão do Leão","Erro IBGE", IF(AND(U86<=0,M86<=2000000),"Mercado insuficiente", IF(U86<=0,"Limite de expansão", IF(K86<500000,"Performance", IF(M86<=2000000,"Mercado insuficiente","Expansão") ) ) ) ) -> Expansão | AC86: =IF(P86=B86,"Oportunidade","Validar") -> Oportunidade
A87: 421130 | B87: Navegantes | C87: SC | D87: 4 | E87: =COUNTIFS('Contratos assinados '!F:F,'Direcional Expansão'!B87,'Contratos assinados '!J:J, "Assinado por ambos") -> 0 | F87: =COUNTIFS('Contratos assinados '!F:F,'Direcional Expansão'!B87,'Contratos assinados '!J:J,"Aquisição") -> 0 | G87: =COUNTIFS('Contratos assinados '!F:F,'Direcional Expansão'!B87,'Contratos assinados '!J:J,"Ampliação") -> 0 | H87: =COUNTIFS('Contratos assinados '!F:F,'Direcional Expansão'!B87,'Contratos assinados '!J:J,"Assinado por proprietário") -> 0 | I87: =SUM(E87:H87) -> 0 | J87: =IF(D87=0, "-", COUNTIFS('Base Lojas'!B:B, A87, 'Base Lojas'!I:I, ">500000")/D87) -> 0.75 | K87: 674059.51 | L87: 0.20080494 | M87: 13427150 | N87: 86401 | O87: =_xlfn.XLOOKUP(A87,Cidades!A:A,Cidades!D:D) -> Entre 50k e 100k | P87: =_xlfn.XLOOKUP(A87,'[1]1° RAIZ'!$A:$A,'[1]1° RAIZ'!$AH:$AH) -> Itajaí | Q87: =_xlfn.XLOOKUP(A87,'[1]1° RAIZ'!$A:$A,'[1]1° RAIZ'!$AE:$AE) -> Blumenau | R87: 0.00027676249 | S87: 0.025397423 | T87: 39 | U87: 1 | V87: 71653.108 | W87: 3.8406251 | X87: 0.70162249 | Y87: 0.91810705 | Z87: 0.12988571 | AA87: 0.44578663 | AB87: =IF(B87="Capão do Leão","Erro IBGE", IF(AND(U87<=0,M87<=2000000),"Mercado insuficiente", IF(U87<=0,"Limite de expansão", IF(K87<500000,"Performance", IF(M87<=2000000,"Mercado insuficiente","Expansão") ) ) ) ) -> Expansão | AC87: =IF(P87=B87,"Oportunidade","Validar") -> Validar
A88: 432000 | B88: Sapucaia do Sul | C88: RS | D88: 7 | E88: =COUNTIFS('Contratos assinados '!F:F,'Direcional Expansão'!B88,'Contratos assinados '!J:J, "Assinado por ambos") -> 0 | F88: =COUNTIFS('Contratos assinados '!F:F,'Direcional Expansão'!B88,'Contratos assinados '!J:J,"Aquisição") -> 0 | G88: =COUNTIFS('Contratos assinados '!F:F,'Direcional Expansão'!B88,'Contratos assinados '!J:J,"Ampliação") -> 0 | H88: =COUNTIFS('Contratos assinados '!F:F,'Direcional Expansão'!B88,'Contratos assinados '!J:J,"Assinado por proprietário") -> 0 | I88: =SUM(E88:H88) -> 0 | J88: =IF(D88=0, "-", COUNTIFS('Base Lojas'!B:B, A88, 'Base Lojas'!I:I, ">500000")/D88) -> 1 | K88: 771905.31 | L88: 0.23082685 | M88: 23408616 | N88: 132107 | O88: =_xlfn.XLOOKUP(A88,Cidades!A:A,Cidades!D:D) -> Entre 100k e 150k | P88: =_xlfn.XLOOKUP(A88,'[1]1° RAIZ'!$A:$A,'[1]1° RAIZ'!$AH:$AH) -> Porto Alegre | Q88: =_xlfn.XLOOKUP(A88,'[1]1° RAIZ'!$A:$A,'[1]1° RAIZ'!$AE:$AE) -> Porto Alegre | R88: 6.5455908e-06 | S88: 0.0050511214 | T88: 43 | U88: 1 | V88: 34429.027 | W88: 3.5297813 | X88: 0.940537 | Y88: -0.24512631 | Z88: 0.25952177 | AA88: 0.39490032 | AB88: =IF(B88="Capão do Leão","Erro IBGE", IF(AND(U88<=0,M88<=2000000),"Mercado insuficiente", IF(U88<=0,"Limite de expansão", IF(K88<500000,"Performance", IF(M88<=2000000,"Mercado insuficiente","Expansão") ) ) ) ) -> Expansão | AC88: =IF(P88=B88,"Oportunidade","Validar") -> Validar
A89: 430160 | B89: Bagé | C89: RS | D89: 6 | E89: =COUNTIFS('Contratos assinados '!F:F,'Direcional Expansão'!B89,'Contratos assinados '!J:J, "Assinado por ambos") -> 0 | F89: =COUNTIFS('Contratos assinados '!F:F,'Direcional Expansão'!B89,'Contratos assinados '!J:J,"Aquisição") -> 1 | G89: =COUNTIFS('Contratos assinados '!F:F,'Direcional Expansão'!B89,'Contratos assinados '!J:J,"Ampliação") -> 0 | H89: =COUNTIFS('Contratos assinados '!F:F,'Direcional Expansão'!B89,'Contratos assinados '!J:J,"Assinado por proprietário") -> 0 | I89: =SUM(E89:H89) -> 1 | J89: =IF(D89=0, "-", COUNTIFS('Base Lojas'!B:B, A89, 'Base Lojas'!I:I, ">500000")/D89) -> 0.66666667 | K89: 557344.61 | L89: 0.16766897 | M89: 19944464 | N89: 117938 | O89: =_xlfn.XLOOKUP(A89,Cidades!A:A,Cidades!D:D) -> Entre 100k e 150k | P89: =_xlfn.XLOOKUP(A89,'[1]1° RAIZ'!$A:$A,'[1]1° RAIZ'!$AH:$AH) -> Bagé | Q89: =_xlfn.XLOOKUP(A89,'[1]1° RAIZ'!$A:$A,'[1]1° RAIZ'!$AE:$AE) -> Pelotas | R89: 7.513966e-06 | S89: 0.0053878028 | T89: 39 | U89: 1 | V89: 34384.333 | W89: 3.7904658 | X89: 0.83506229 | Y89: -0.15214108 | Z89: 0.033900149 | AA89: 0.33760724 | AB89: =IF(B89="Capão do Leão","Erro IBGE", IF(AND(U89<=0,M89<=2000000),"Mercado insuficiente", IF(U89<=0,"Limite de expansão", IF(K89<500000,"Performance", IF(M89<=2000000,"Mercado insuficiente","Expansão") ) ) ) ) -> Expansão | AC89: =IF(P89=B89,"Oportunidade","Validar") -> Oportunidade
A90: 421320 | B90: Pomerode | C90: SC | D90: 1 | E90: =COUNTIFS('Contratos assinados '!F:F,'Direcional Expansão'!B90,'Contratos assinados '!J:J, "Assinado por ambos") -> 0 | F90: =COUNTIFS('Contratos assinados '!F:F,'Direcional Expansão'!B90,'Contratos assinados '!J:J,"Aquisição") -> 0 | G90: =COUNTIFS('Contratos assinados '!F:F,'Direcional Expansão'!B90,'Contratos assinados '!J:J,"Ampliação") -> 0 | H90: =COUNTIFS('Contratos assinados '!F:F,'Direcional Expansão'!B90,'Contratos assinados '!J:J,"Assinado por proprietário") -> 0 | I90: =SUM(E90:H90) -> 0 | J90: =IF(D90=0, "-", COUNTIFS('Base Lojas'!B:B, A90, 'Base Lojas'!G:G, ">500000")/D90) -> 0 | K90: 153634.96 | L90: 0.023074747 | M90: 6658142.7 | N90: 34263 | O90: =_xlfn.XLOOKUP(A90,Cidades!A:A,Cidades!D:D) -> Entre 30k e 50k | P90: =_xlfn.XLOOKUP(A90,'[1]1° RAIZ'!$A:$A,'[1]1° RAIZ'!$AH:$AH) -> Blumenau | Q90: =_xlfn.XLOOKUP(A90,'[1]1° RAIZ'!$A:$A,'[1]1° RAIZ'!$AE:$AE) -> Blumenau | R90: 0.00016287975 | S90: 0.016870195 | T90: 10 | U90: 1 | V90: 85058.038 | W90: 5.0773643 | X90: 0.32024994 | Y90: 1.3469188 | Z90: -0.018584864 | AA90: 0.32814067 | AB90: =IF(B90="Capão do Leão","Erro IBGE", IF(AND(U90<=0,M90<=2000000),"Mercado insuficiente", IF(U90<=0,"Limite de expansão", IF(K90<500000,"Performance", IF(M90<=2000000,"Mercado insuficiente","Expansão") ) ) ) ) -> Performance | AC90: =IF(P90=B90,"Oportunidade","Validar") -> Validar
A91: 420320 | B91: Camboriú | C91: SC | D91: 5 | E91: =COUNTIFS('Contratos assinados '!F:F,'Direcional Expansão'!B91,'Contratos assinados '!J:J, "Assinado por ambos") -> 0 | F91: =COUNTIFS('Contratos assinados '!F:F,'Direcional Expansão'!B91,'Contratos assinados '!J:J,"Aquisição") -> 0 | G91: =COUNTIFS('Contratos assinados '!F:F,'Direcional Expansão'!B91,'Contratos assinados '!J:J,"Ampliação") -> 0 | H91: =COUNTIFS('Contratos assinados '!F:F,'Direcional Expansão'!B91,'Contratos assinados '!J:J,"Assinado por proprietário") -> 0 | I91: =SUM(E91:H91) -> 0 | J91: =IF(D91=0, "-", COUNTIFS('Base Lojas'!B:B, A91, 'Base Lojas'!I:I, ">500000")/D91) -> 0.4 | K91: 500794.68 | L91: 0.14536419 | M91: 17225517 | N91: 103074 | O91: =_xlfn.XLOOKUP(A91,Cidades!A:A,Cidades!D:D) -> Entre 100k e 150k | P91: =_xlfn.XLOOKUP(A91,'[1]1° RAIZ'!$A:$A,'[1]1° RAIZ'!$AH:$AH) -> Itajaí | Q91: =_xlfn.XLOOKUP(A91,'[1]1° RAIZ'!$A:$A,'[1]1° RAIZ'!$AE:$AE) -> Blumenau | R91: 0.00039503563 | S91: 0.040961699 | T91: 34 | U91: 1 | V91: 21393.636 | W91: 4.1526957 | X91: 0.80608102 | Y91: 0.80755519 | Z91: -1.1593755 | AA91: 0.3271741 | AB91: =IF(B91="Capão do Leão","Erro IBGE", IF(AND(U91<=0,M91<=2000000),"Mercado insuficiente", IF(U91<=0,"Limite de expansão", IF(K91<500000,"Performance", IF(M91<=2000000,"Mercado insuficiente","Expansão") ) ) ) ) -> Expansão | AC91: =IF(P91=B91,"Oportunidade","Validar") -> Validar
A92: 421720 | B92: São Miguel do Oeste | C92: SC | D92: 1 | E92: =COUNTIFS('Contratos assinados '!F:F,'Direcional Expansão'!B92,'Contratos assinados '!J:J, "Assinado por ambos") -> 0 | F92: =COUNTIFS('Contratos assinados '!F:F,'Direcional Expansão'!B92,'Contratos assinados '!J:J,"Aquisição") -> 0 | G92: =COUNTIFS('Contratos assinados '!F:F,'Direcional Expansão'!B92,'Contratos assinados '!J:J,"Ampliação") -> 0 | H92: =COUNTIFS('Contratos assinados '!F:F,'Direcional Expansão'!B92,'Contratos assinados '!J:J,"Assinado por proprietário") -> 0 | I92: =SUM(E92:H92) -> 0 | J92: =IF(D92=0, "-", COUNTIFS('Base Lojas'!B:B, A92, 'Base Lojas'!G:G, ">500000")/D92) -> 0 | K92: 353426.94 | L92: 0.042322403 | M92: 8350824.1 | N92: 44330 | O92: =_xlfn.XLOOKUP(A92,Cidades!A:A,Cidades!D:D) -> Entre 30k e 50k | P92: =_xlfn.XLOOKUP(A92,'[1]1° RAIZ'!$A:$A,'[1]1° RAIZ'!$AH:$AH) -> São Miguel do Oeste | Q92: =_xlfn.XLOOKUP(A92,'[1]1° RAIZ'!$A:$A,'[1]1° RAIZ'!$AE:$AE) -> Chapecó | R92: 0.00015502135 | S92: 0.017884749 | T92: 28 | U92: 1 | V92: 51122.527 | W92: 4.9537898 | X92: 0.49763769 | Y92: 0.91356877 | Z92: -0.48791767 | AA92: 0.2877298 | AB92: =IF(B92="Capão do Leão","Erro IBGE", IF(AND(U92<=0,M92<=2000000),"Mercado insuficiente", IF(U92<=0,"Limite de expansão", IF(K92<500000,"Performance", IF(M92<=2000000,"Mercado insuficiente","Expansão") ) ) ) ) -> Performance | AC92: =IF(P92=B92,"Oportunidade","Validar") -> Oportunidade
A93: 421800 | B93: Tijucas | C93: SC | D93: 2 | E93: =COUNTIFS('Contratos assinados '!F:F,'Direcional Expansão'!B93,'Contratos assinados '!J:J, "Assinado por ambos") -> 0 | F93: =COUNTIFS('Contratos assinados '!F:F,'Direcional Expansão'!B93,'Contratos assinados '!J:J,"Aquisição") -> 0 | G93: =COUNTIFS('Contratos assinados '!F:F,'Direcional Expansão'!B93,'Contratos assinados '!J:J,"Ampliação") -> 0 | H93: =COUNTIFS('Contratos assinados '!F:F,'Direcional Expansão'!B93,'Contratos assinados '!J:J,"Assinado por proprietário") -> 0 | I93: =SUM(E93:H93) -> 0 | J93: =IF(D93=0, "-", COUNTIFS('Base Lojas'!B:B, A93, 'Base Lojas'!I:I, ">500000")/D93) -> 0.5 | K93: 785628.57 | L93: 0.19791074 | M93: 7939221.1 | N93: 51592 | O93: =_xlfn.XLOOKUP(A93,Cidades!A:A,Cidades!D:D) -> Entre 50k e 100k | P93: =_xlfn.XLOOKUP(A93,'[1]1° RAIZ'!$A:$A,'[1]1° RAIZ'!$AH:$AH) -> Itajaí | Q93: =_xlfn.XLOOKUP(A93,'[1]1° RAIZ'!$A:$A,'[1]1° RAIZ'!$AE:$AE) -> Blumenau | R93: 0.0004003052 | S93: 0.037941828 | T93: 23 | U93: 1 | V93: 46655.891 | W93: 4.0829593 | X93: 0.42601329 | Y93: 1.1813445 | Z93: -0.5969407 | AA93: 0.2833234 | AB93: =IF(B93="Capão do Leão","Erro IBGE", IF(AND(U93<=0,M93<=2000000),"Mercado insuficiente", IF(U93<=0,"Limite de expansão", IF(K93<500000,"Performance", IF(M93<=2000000,"Mercado insuficiente","Expansão") ) ) ) ) -> Expansão | AC93: =IF(P93=B93,"Oportunidade","Validar") -> Validar
A94: 410550 | B94: Cianorte | C94: PR | D94: 4 | E94: =COUNTIFS('Contratos assinados '!F:F,'Direcional Expansão'!B94,'Contratos assinados '!J:J, "Assinado por ambos") -> 0 | F94: =COUNTIFS('Contratos assinados '!F:F,'Direcional Expansão'!B94,'Contratos assinados '!J:J,"Aquisição") -> 0 | G94: =COUNTIFS('Contratos assinados '!F:F,'Direcional Expansão'!B94,'Contratos assinados '!J:J,"Ampliação") -> 0 | H94: =COUNTIFS('Contratos assinados '!F:F,'Direcional Expansão'!B94,'Contratos assinados '!J:J,"Assinado por proprietário") -> 0 | I94: =SUM(E94:H94) -> 0 | J94: =IF(D94=0, "-", COUNTIFS('Base Lojas'!B:B, A94, 'Base Lojas'!G:G, ">500000")/D94) -> 0.25 | K94: 418211.38 | L94: 0.14597894 | M94: 11459499 | N94: 79527 | O94: =_xlfn.XLOOKUP(A94,Cidades!A:A,Cidades!D:D) -> Entre 50k e 100k | P94: =_xlfn.XLOOKUP(A94,'[1]1° RAIZ'!$A:$A,'[1]1° RAIZ'!$AH:$AH) -> Cianorte | Q94: =_xlfn.XLOOKUP(A94,'[1]1° RAIZ'!$A:$A,'[1]1° RAIZ'!$AE:$AE) -> Maringá | R94: 9.9060004e-05 | S94: 0.014056477 | T94: 35 | U94: 1 | V94: 41232.317 | W94: 4.0428886 | X94: 0.60092385 | Y94: 0.31068079 | Z94: -0.17012751 | AA94: 0.28121811 | AB94: =IF(B94="Capão do Leão","Erro IBGE", IF(AND(U94<=0,M94<=2000000),"Mercado insuficiente", IF(U94<=0,"Limite de expansão", IF(K94<500000,"Performance", IF(M94<=2000000,"Mercado insuficiente","Expansão") ) ) ) ) -> Performance | AC94: =IF(P94=B94,"Oportunidade","Validar") -> Oportunidade
A95: 420300 | B95: Caçador | C95: SC | D95: 3 | E95: =COUNTIFS('Contratos assinados '!F:F,'Direcional Expansão'!B95,'Contratos assinados '!J:J, "Assinado por ambos") -> 0 | F95: =COUNTIFS('Contratos assinados '!F:F,'Direcional Expansão'!B95,'Contratos assinados '!J:J,"Aquisição") -> 0 | G95: =COUNTIFS('Contratos assinados '!F:F,'Direcional Expansão'!B95,'Contratos assinados '!J:J,"Ampliação") -> 0 | H95: =COUNTIFS('Contratos assinados '!F:F,'Direcional Expansão'!B95,'Contratos assinados '!J:J,"Assinado por proprietário") -> 0 | I95: =SUM(E95:H95) -> 0 | J95: =IF(D95=0, "-", COUNTIFS('Base Lojas'!B:B, A95, 'Base Lojas'!G:G, ">500000")/D95) -> 0 | K95: 254394.16 | L95: 0.066099038 | M95: 11546045 | N95: 73720 | O95: =_xlfn.XLOOKUP(A95,Cidades!A:A,Cidades!D:D) -> Entre 50k e 100k | P95: =_xlfn.XLOOKUP(A95,'[1]1° RAIZ'!$A:$A,'[1]1° RAIZ'!$AH:$AH) -> Caçador | Q95: =_xlfn.XLOOKUP(A95,'[1]1° RAIZ'!$A:$A,'[1]1° RAIZ'!$AE:$AE) -> Caçador | R95: 3.1845702e-05 | S95: 0.0072186748 | T95: 33 | U95: 1 | V95: 69286.435 | W95: 3.7781178 | X95: 0.51860708 | Y95: 0.20239271 | Z95: 0.16966737 | AA95: 0.26936633 | AB95: =IF(B95="Capão do Leão","Erro IBGE", IF(AND(U95<=0,M95<=2000000),"Mercado insuficiente", IF(U95<=0,"Limite de expansão", IF(K95<500000,"Performance", IF(M95<=2000000,"Mercado insuficiente","Expansão") ) ) ) ) -> Performance | AC95: =IF(P95=B95,"Oportunidade","Validar") -> Oportunidade
A96: 411790 | B96: Palotina | C96: PR | D96: 1 | E96: =COUNTIFS('Contratos assinados '!F:F,'Direcional Expansão'!B96,'Contratos assinados '!J:J, "Assinado por ambos") -> 0 | F96: =COUNTIFS('Contratos assinados '!F:F,'Direcional Expansão'!B96,'Contratos assinados '!J:J,"Aquisição") -> 0 | G96: =COUNTIFS('Contratos assinados '!F:F,'Direcional Expansão'!B96,'Contratos assinados '!J:J,"Ampliação") -> 0 | H96: =COUNTIFS('Contratos assinados '!F:F,'Direcional Expansão'!B96,'Contratos assinados '!J:J,"Assinado por proprietário") -> 0 | I96: =SUM(E96:H96) -> 0 | J96: =IF(D96=0, "-", COUNTIFS('Base Lojas'!B:B, A96, 'Base Lojas'!G:G, ">500000")/D96) -> 0 | K96: 369936.78 | L96: 0.066029094 | M96: 5602633 | N96: 35011 | O96: =_xlfn.XLOOKUP(A96,Cidades!A:A,Cidades!D:D) -> Entre 30k e 50k | P96: =_xlfn.XLOOKUP(A96,'[1]1° RAIZ'!$A:$A,'[1]1° RAIZ'!$AH:$AH) -> Toledo | Q96: =_xlfn.XLOOKUP(A96,'[1]1° RAIZ'!$A:$A,'[1]1° RAIZ'!$AE:$AE) -> Cascavel | R96: 0.00015428889 | S96: 0.017371634 | T96: 12 | U96: 1 | V96: 85463.307 | W96: 4.3798932 | X96: 0.24106953 | Y96: 1.0475339 | Z96: 0.13413421 | AA96: 0.26876106 | AB96: =IF(B96="Capão do Leão","Erro IBGE", IF(AND(U96<=0,M96<=2000000),"Mercado insuficiente", IF(U96<=0,"Limite de expansão", IF(K96<500000,"Performance", IF(M96<=2000000,"Mercado insuficiente","Expansão") ) ) ) ) -> Performance | AC96: =IF(P96=B96,"Oportunidade","Validar") -> Validar
A97: 420650 | B97: Guaramirim | C97: SC | D97: 2 | E97: =COUNTIFS('Contratos assinados '!F:F,'Direcional Expansão'!B97,'Contratos assinados '!J:J, "Assinado por ambos") -> 0 | F97: =COUNTIFS('Contratos assinados '!F:F,'Direcional Expansão'!B97,'Contratos assinados '!J:J,"Aquisição") -> 0 | G97: =COUNTIFS('Contratos assinados '!F:F,'Direcional Expansão'!B97,'Contratos assinados '!J:J,"Ampliação") -> 0 | H97: =COUNTIFS('Contratos assinados '!F:F,'Direcional Expansão'!B97,'Contratos assinados '!J:J,"Assinado por proprietário") -> 0 | I97: =SUM(E97:H97) -> 0 | J97: =IF(D97=0, "-", COUNTIFS('Base Lojas'!B:B, A97, 'Base Lojas'!G:G, ">500000")/D97) -> 0.5 | K97: 483745.64 | L97: 0.14473405 | M97: 6684614.3 | N97: 46711 | O97: =_xlfn.XLOOKUP(A97,Cidades!A:A,Cidades!D:D) -> Entre 30k e 50k | P97: =_xlfn.XLOOKUP(A97,'[1]1° RAIZ'!$A:$A,'[1]1° RAIZ'!$AH:$AH) -> Joinville | Q97: =_xlfn.XLOOKUP(A97,'[1]1° RAIZ'!$A:$A,'[1]1° RAIZ'!$AE:$AE) -> Joinville | R97: 0.00022033963 | S97: 0.022954154 | T97: 12 | U97: 1 | V97: 55347.751 | W97: 4.3406312 | X97: 0.30335537 | Y97: 0.96302878 | Z97: -0.22997069 | AA97: 0.24155625 | AB97: =IF(B97="Capão do Leão","Erro IBGE", IF(AND(U97<=0,M97<=2000000),"Mercado insuficiente", IF(U97<=0,"Limite de expansão", IF(K97<500000,"Performance", IF(M97<=2000000,"Mercado insuficiente","Expansão") ) ) ) ) -> Performance | AC97: =IF(P97=B97,"Oportunidade","Validar") -> Validar
A98: 420700 | B98: Içara | C98: SC | D98: 2 | E98: =COUNTIFS('Contratos assinados '!F:F,'Direcional Expansão'!B98,'Contratos assinados '!J:J, "Assinado por ambos") -> 0 | F98: =COUNTIFS('Contratos assinados '!F:F,'Direcional Expansão'!B98,'Contratos assinados '!J:J,"Aquisição") -> 0 | G98: =COUNTIFS('Contratos assinados '!F:F,'Direcional Expansão'!B98,'Contratos assinados '!J:J,"Ampliação") -> 0 | H98: =COUNTIFS('Contratos assinados '!F:F,'Direcional Expansão'!B98,'Contratos assinados '!J:J,"Assinado por proprietário") -> 0 | I98: =SUM(E98:H98) -> 0 | J98: =IF(D98=0, "-", COUNTIFS('Base Lojas'!B:B, A98, 'Base Lojas'!G:G, ">500000")/D98) -> 0.5 | K98: 400511.11 | L98: 0.090195385 | M98: 8880966.9 | N98: 59035 | O98: =_xlfn.XLOOKUP(A98,Cidades!A:A,Cidades!D:D) -> Entre 50k e 100k | P98: =_xlfn.XLOOKUP(A98,'[1]1° RAIZ'!$A:$A,'[1]1° RAIZ'!$AH:$AH) -> Criciúma | Q98: =_xlfn.XLOOKUP(A98,'[1]1° RAIZ'!$A:$A,'[1]1° RAIZ'!$AE:$AE) -> Criciúma | R98: 2.2969831e-06 | S98: 0.00018712365 | T98: 24 | U98: 1 | V98: 62315.892 | W98: 3.7750492 | X98: 0.35664862 | Y98: 0.10068176 | Z98: 0.23105011 | AA98: 0.19275898 | AB98: =IF(B98="Capão do Leão","Erro IBGE", IF(AND(U98<=0,M98<=2000000),"Mercado insuficiente", IF(U98<=0,"Limite de expansão", IF(K98<500000,"Performance", IF(M98<=2000000,"Mercado insuficiente","Expansão") ) ) ) ) -> Performance | AC98: =IF(P98=B98,"Oportunidade","Validar") -> Validar
A99: 420845 | B99: Itapoá | C99: SC | D99: 1 | E99: =COUNTIFS('Contratos assinados '!F:F,'Direcional Expansão'!B99,'Contratos assinados '!J:J, "Assinado por ambos") -> 0 | F99: =COUNTIFS('Contratos assinados '!F:F,'Direcional Expansão'!B99,'Contratos assinados '!J:J,"Aquisição") -> 0 | G99: =COUNTIFS('Contratos assinados '!F:F,'Direcional Expansão'!B99,'Contratos assinados '!J:J,"Ampliação") -> 0 | H99: =COUNTIFS('Contratos assinados '!F:F,'Direcional Expansão'!B99,'Contratos assinados '!J:J,"Assinado por proprietário") -> 0 | I99: =SUM(E99:H99) -> 0 | J99: =IF(D99=0, "-", COUNTIFS('Base Lojas'!B:B, A99, 'Base Lojas'!I:I, ">500000")/D99) -> 1 | K99: 683234.09 | L99: 0.14575353 | M99: 4687599.1 | N99: 30750 | O99: =_xlfn.XLOOKUP(A99,Cidades!A:A,Cidades!D:D) -> Entre 30k e 50k | P99: =_xlfn.XLOOKUP(A99,'[1]1° RAIZ'!$A:$A,'[1]1° RAIZ'!$AH:$AH) -> Joinville | Q99: =_xlfn.XLOOKUP(A99,'[1]1° RAIZ'!$A:$A,'[1]1° RAIZ'!$AE:$AE) -> Joinville | R99: 0.0005800074 | S99: 0.052847445 | T99: 23 | U99: 1 | V99: 52426.786 | W99: 3.5975478 | X99: 0.27074452 | Y99: 1.3649206 | Z99: -1.1030439 | AA99: 0.18584285 | AB99: =IF(B99="Capão do Leão","Erro IBGE", IF(AND(U99<=0,M99<=2000000),"Mercado insuficiente", IF(U99<=0,"Limite de expansão", IF(K99<500000,"Performance", IF(M99<=2000000,"Mercado insuficiente","Expansão") ) ) ) ) -> Expansão | AC99: =IF(P99=B99,"Oportunidade","Validar") -> Validar
A100: 412080 | B100: Quatro Barras | C100: PR | D100: 0 | E100: =COUNTIFS('Contratos assinados '!F:F,'Direcional Expansão'!B100,'Contratos assinados '!J:J, "Assinado por ambos") -> 0 | F100: =COUNTIFS('Contratos assinados '!F:F,'Direcional Expansão'!B100,'Contratos assinados '!J:J,"Aquisição") -> 0 | G100: =COUNTIFS('Contratos assinados '!F:F,'Direcional Expansão'!B100,'Contratos assinados '!J:J,"Ampliação") -> 0 | H100: =COUNTIFS('Contratos assinados '!F:F,'Direcional Expansão'!B100,'Contratos assinados '!J:J,"Assinado por proprietário") -> 0 | I100: =SUM(E100:H100) -> 0 | J100: =IF(D100=0, "-", COUNTIFS('Base Lojas'!B:B, A100, 'Base Lojas'!I:I, ">500000")/D100) -> - | K100: - | L100: 0 | M100: 3323597.8 | N100: 24191 | O100: =_xlfn.XLOOKUP(A100,Cidades!A:A,Cidades!D:D) -> Entre 20k e 30k | P100: =_xlfn.XLOOKUP(A100,'[1]1° RAIZ'!$A:$A,'[1]1° RAIZ'!$AH:$AH) -> Curitiba | Q100: =_xlfn.XLOOKUP(A100,'[1]1° RAIZ'!$A:$A,'[1]1° RAIZ'!$AE:$AE) -> Curitiba | R100: 0.00015582159 | S100: 0.019198648 | T100: 7 | U100: 1 | V100: 86266.737 | W100: 4.1322957 | X100: 0.091917166 | Y100: 0.90020468 | Z100: -0.10112297 | AA100: 0.15717585 | AB100: =IF(B100="Capão do Leão","Erro IBGE", IF(AND(U100<=0,M100<=2000000),"Mercado insuficiente", IF(U100<=0,"Limite de expansão", IF(K100<500000,"Performance", IF(M100<=2000000,"Mercado insuficiente","Expansão") ) ) ) ) -> Expansão | AC100: =IF(P100=B100,"Oportunidade","Validar") -> Validar
...

Sheet Expansão cidades Sem FSJ
A1: Cód | B1: Município | C1: UF | D1: N° FSJ | E1: Ass. por ambos | F1: Aquisição | G1: Ampliação | H1: Assinado por proprietário | I1: Contratos | J1: Venda > 500k | K1: Média Faturamento | L1: %Share | M1: Demanda | N1: População | O1: Porte da cidade | P1: REGIÃO GEOGRÁFICA IMEDIATA | Q1: REGIÃO GEOGRÁFICA INTERMEDIÁRIA | R1: Taxa Crescimento Pop | S1: Taxa Crescimento Dom | T1: Concorrência | U1: Lojas Cabem | V1: PIB | W1: Renda Média Domiciliar (SM) | X1: Fator 1 | Y1: Fator 2 | Z1: Fator 3 | AA1: Ranking | AB1: Status | AC1: Região Imediata
A2: 411990 | B2: Ponta Grossa | C2: PR | D2: 0 | E2: 0 | F2: 0 | G2: 0 | H2: 0 | I2: 0 | J2: - | K2: - | L2: 0 | M2: 52309124 | N2: 358367 | O2: Maior que 200k | P2: Ponta Grossa | Q2: Ponta Grossa | R2: 0.00010790575 | S2: 0.015582368 | T2: 109 | U2: 23 | V2: 58329.645 | W2: 4.495249 | X2: 3.9681546 | Y2: -0.78599628 | Z2: -0.73897544 | AA2: 1.4924571 | AB2: Expansão | AC2: Oportunidade
A3: 411820 | B3: Paranaguá | C3: PR | D3: 0 | E3: 0 | F3: 0 | G3: 0 | H3: 0 | I3: 0 | J3: - | K3: - | L3: 0 | M3: 19242219 | N3: 145829 | O3: Entre 100k e 150k | P3: Paranaguá | Q3: Curitiba | R3: 2.8951945e-05 | S3: 0.008228996 | T3: 42 | U3: 9 | V3: 102167.39 | W3: 4.1460404 | X3: 1.4326877 | Y3: 0.24780078 | Z3: 0.33226947 | AA3: 0.68375401 | AB3: Expansão | AC3: Oportunidade
A4: 411850 | B4: Pato Branco | C4: PR | D4: 0 | E4: 0 | F4: 0 | G4: 0 | H4: 0 | I4: 0 | J4: - | K4: - | L4: 0 | M4: 14520214 | N4: 91836 | O4: Entre 50k e 100k | P4: Pato Branco | Q4: Cascavel | R4: 0.00018489708 | S4: 0.0217162 | T4: 39 | U4: 6 | V4: 52187.733 | W4: 4.8692033 | X4: 1.0990737 | Y4: 0.64686753 | Z4: -0.77770716 | AA4: 0.47239709 | AB4: Expansão | AC4: Oportunidade
A5: 412710 | B5: Telêmaco Borba | C5: PR | D5: 0 | E5: 0 | F5: 0 | G5: 0 | H5: 0 | I5: 0 | J5: - | K5: - | L5: 0 | M5: 9914555.7 | N5: 75042 | O5: Entre 50k e 100k | P5: Telêmaco Borba | Q5: Ponta Grossa | R5: 5.4994585e-05 | S5: 0.009125936 | T5: 30 | U5: 5 | V5: 71362.289 | W5: 3.6791284 | X5: 0.68350388 | Y5: 0.024108936 | Z5: -0.16464125 | AA5: 0.27576468 | AB5: Expansão | AC5: Oportunidade
A6: 421480 | B6: Rio do Sul | C6: SC | D6: 0 | E6: 0 | F6: 0 | G6: 0 | H6: 0 | I6: 0 | J6: - | K6: - | L6: 0 | M6: 15402738 | N6: 72587 | O6: Entre 50k e 100k | P6: Rio do Sul | Q6: Blumenau | R6: 0.00013217669 | S6: 0.016087152 | T6: 42 | U6: 4 | V6: 53526.937 | W6: 5.3408019 | X6: 1.0136017 | Y6: 0.83875508 | Z6: -0.58173168 | AA6: 0.4859897 | AB6: Expansão | AC6: Oportunidade
A7: 421950 | B7: Xanxerê | C7: SC | D7: 0 | E7: 0 | F7: 0 | G7: 0 | H7: 0 | I7: 0 | J7: - | K7: - | L7: 0 | M7: 8584204.1 | N7: 51607 | O7: Entre 50k e 100k | P7: Xanxerê | Q7: Chapecó | R7: 0.00012161993 | S7: 0.017376071 | T7: 31 | U7: 3 | V7: 54797.374 | W7: 4.5281045 | X7: 0.59798918 | Y7: 0.55006792 | Z7: -0.55880519 | AA7: 0.27005269 | AB7: Expansão | AC7: Oportunidade
A8: 412410 | B8: Santo Antônio da Platina | C8: PR | D8: 0 | E8: 0 | F8: 0 | G8: 0 | H8: 0 | I8: 0 | J8: - | K8: - | L8: 0 | M8: 5928799.9 | N8: 44369 | O8: Entre 30k e 50k | P8: Santo Antônio da Platina | Q8: Londrina | R8: 2.9754315e-05 | S8: 0.0079185813 | T8: 16 | U8: 2 | V8: 37107.228 | W8: 3.8145906 | X8: 0.24885006 | Y8: -0.11564311 | Z8: -0.61233358 | AA8: 0.019428494 | AB8: Expansão | AC8: Oportunidade
A9: 420480 | B9: Curitibanos | C9: SC | D9: 0 | E9: 0 | F9: 0 | G9: 0 | H9: 0 | I9: 0 | J9: - | K9: - | L9: 0 | M9: 5670523.2 | N9: 40045 | O9: Entre 30k e 50k | P9: Curitibanos | Q9: Lages | R9: 4.5010832e-05 | S9: 0.0082179844 | T9: 15 | U9: 2 | V9: 50435.189 | W9: 3.4555052 | X9: 0.1838955 | Y9: -0.13127679 | Z9: -0.43063015 | AA9: 0.010259258 | AB9: Expansão | AC9: Oportunidade
A10: 411960 | B10: Pitanga | C10: PR | D10: 0 | E10: 0 | F10: 0 | G10: 0 | H10: 0 | I10: 0 | J10: - | K10: - | L10: 0 | M10: 4062805.8 | N10: 33567 | O10: Entre 30k e 50k | P10: Pitanga | Q10: Guarapuava | R10: 2.144738e-05 | S10: 0.0087584235 | T10: 13 | U10: 2 | V10: 37059.734 | W10: 3.1276303 | X10: 0.075794473 | Y10: -0.43821235 | Z10: -0.61899937 | AA10: -0.10146373 | AB10: Expansão | AC10: Oportunidade
A11: 411150 | B11: Ivaiporã | C11: PR | D11: 0 | E11: 0 | F11: 0 | G11: 0 | H11: 0 | I11: 0 | J11: - | K11: - | L11: 0 | M11: 5085950.4 | N11: 32720 | O11: Entre 30k e 50k | P11: Ivaiporã | Q11: Londrina | R11: 2.1671861e-05 | S11: 0.0068679234 | T11: 11 | U11: 2 | V11: 31748.302 | W11: 3.078098 | X11: 0.064012535 | Y11: -0.53133035 | Z11: -0.68875576 | AA11: -0.12784838 | AB11: Expansão | AC11: Oportunidade
A12: 420850 | B12: Ituporanga | C12: SC | D12: 0 | E12: 0 | F12: 0 | G12: 0 | H12: 0 | I12: 0 | J12: - | K12: - | L12: 0 | M12: 4636897.9 | N12: 26525 | O12: Entre 20k e 30k | P12: Ituporanga | Q12: Blumenau | R12: 0.00013593172 | S12: 0.016513956 | T12: 20 | U12: 1 | V12: 55182.749 | W12: 4.269716 | X12: 0.2273939 | Y12: 0.57000236 | Z12: -0.54207804 | AA12: 0.11700263 | AB12: Expansão | AC12: Oportunidade
A13: 410970 | B13: Ibaiti | C13: PR | D13: 0 | E13: 0 | F13: 0 | G13: 0 | H13: 0 | I13: 0 | J13: - | K13: - | L13: 0 | M13: 3843194.1 | N13: 28830 | O13: Entre 20k e 30k | P13: Ibaiti | Q13: Londrina | R13: 2.8070769e-06 | S13: 0.0050148489 | T13: 10 | U13: 1 | V13: 33569.07 | W13: 3.9221118 | X13: 0.072477997 | Y13: -0.092448073 | Z13: -0.58826772 | AA13: -0.049598682 | AB13: Expansão | AC13: Oportunidade
... A32: 411125 | B32: Itaperuçu | C32: PR | D32: 0 | E32: 0 | F32: 0 | G32: 0 | H32: 0 | I32: 0 | J32: - | K32: - | L32: 0 | M32: 3716137.4 | N32: 31217 | O32: Entre 30k e 50k | P32: Curitiba | Q32: Curitiba | R32: 0.00020760736 | S32: 0.024760696 | T32: 9 | U32: 2 | V32: 21112.528 | W32: 2.5430769 | X32: -0.019039875 | Y32: -0.453112 | Z32: -1.3072743 | AA32: -0.22257227 | AB32: Expansão | AC32: Validar

Sheet Expansão cidades Com FSJ
A1: Cód | B1: Município | C1: UF | D1: N° FSJ | E1: Ass. por ambos | F1: Aquisição | G1: Ampliação | H1: Assinado por proprietário | I1: Contratos | J1: Venda > 500k | K1: Média Faturamento | L1: %Share | M1: Demanda | N1: População | O1: Porte da cidade | P1: REGIÃO GEOGRÁFICA IMEDIATA | Q1: REGIÃO GEOGRÁFICA INTERMEDIÁRIA | R1: Taxa Crescimento Pop | S1: Taxa Crescimento Dom | T1: Concorrência | U1: Lojas Cabem | V1: PIB | W1: Renda Média Domiciliar (SM) | X1: Fator 1 | Y1: Fator 2 | Z1: Fator 3 | AA1: Ranking | AB1: Status | AC1: Região Imediata
A2: 410690 | B2: Curitiba | C2: PR | D2: 4 | E2: 0 | F2: 0 | G2: 0 | H2: 0 | I2: 0 | J2: 0.5 | K2: 529473.24 | L2: 0.006059215 | M2: 3.4953256e+08 | N2: 1773733 | O2: Maior que 200k | P2: Curitiba | Q2: Curitiba | R2: 1.1734469e-05 | S2: 0.0061701967 | T2: 760 | U2: 113 | V2: 59976.102 | W2: 7.4815934 | X2: 23.530133 | Y2: -6.6132887 | Z2: -1.4440723 | AA2: 8.9042361 | AB2: Expansão | AC2: Oportunidade
A3: 420540 | B3: Florianópolis | C3: SC | D3: 18 | E3: 0 | F3: 0 | G3: 0 | H3: 0 | I3: 0 | J3: 0.77777778 | K3: 884907.8 | L3: 0.12015389 | M3: 1.3256616e+08 | N3: 537213 | O3: Maior que 200k | P3: Florianópolis | Q3: Florianópolis | R3: 0.00018890029 | S3: 0.020340133 | T3: 237 | U3: 17 | V3: 44854.646 | W3: 8.0222292 | X3: 6.879443 | Y3: 0.53207887 | Z3: -0.33951717 | AA3: 2.9676422 | AB3: Expansão | AC3: Oportunidade
A4: 420820 | B4: Itajaí | C4: SC | D4: 8 | E4: 0 | F4: 0 | G4: 1 | H4: 0 | I4: 1 | J4: 0.75 | K4: 639106.45 | L4: 0.10154863 | M4: 50348798 | N4: 264054 | O4: Maior que 200k | P4: Itajaí | Q4: Blumenau | R4: 0.00028439155 | S4: 0.027286013 | T4: 105 | U4: 9 | V4: 181166.23 | W4: 5.0486227 | X4: 2.9610387 | Y4: 1.7575112 | Z4: 1.4836989 | AA4: 1.6834055 | AB4: Expansão | AC4: Oportunidade
A5: 410180 | B5: Araucária | C5: PR | D5: 1 | E5: 0 | F5: 0 | G5: 0 | H5: 0 | I5: 0 | J5: 1 | K5: 511004.74 | L5: 0.024332456 | M5: 21000952 | N5: 151666 | O5: Entre 150k e 200k | P5: Curitiba | Q5: Curitiba | R5: 0.00018697202 | S5: 0.022555882 | T5: 40 | U5: 9 | V5: 174727.8 | W5: 4.2958383 | X5: 1.5297908 | Y5: 1.4227987 | Z5: 1.2175216 | AA5: 0.99529999 | AB5: Expansão | AC5: Validar
A6: 412770 | B6: Toledo | C6: PR | D6: 4 | E6: 0 | F6: 0 | G6: 0 | H6: 0 | I6: 0 | J6: 0.75 | K6: 716649.98 | L6: 0.1224696 | M6: 23406623 | N6: 150470 | O6: Entre 150k e 200k | P6: Toledo | Q6: Cascavel | R6: 0.00017981152 | S6: 0.020328581 | T6: 79 | U6: 6 | V6: 52230.744 | W6: 4.2036522 | X6: 1.6689317 | Y6: 0.2588927 | Z6: -0.31793843 | AA6: 0.71173209 | AB6: Expansão | AC6: Oportunidade
A7: 432300 | B7: Viamão | C7: RS | D7: 10 | E7: 0 | F7: 0 | G7: 0 | H7: 0 | I7: 0 | J7: 0.7 | K7: 570796.94 | L7: 0.15236613 | M7: 37462192 | N7: 224116 | O7: Maior que 200k | P7: Porto Alegre | Q7: Porto Alegre | R7: -5.0088274e-05 | S7: 0.00022813512 | T7: 70 | U7: 4 | V7: 20862.851 | W7: 3.515079 | X7: 1.7963636 | Y7: -0.92158162 | Z7: -0.1053324 | AA7: 0.6203581 | AB7: Expansão | AC7: Validar
A8: 410430 | B8: Campo Mourão | C8: PR | D8: 2 | E8: 0 | F8: 0 | G8: 0 | H8: 0 | I8: 0 | J8: 0.5 | K8: 501535.03 | L8: 0.066502735 | M8: 15083140 | N8: 99432 | O8: Entre 50k e 100k | P8: Campo Mourão | Q8: Maringá | R8: 0.00010071336 | S8: 0.014473581 | T8: 43 | U8: 4 | V8: 55545.374 | W8: 4.0864536 | X8: 0.94905437 | Y8: 0.22828438 | Z8: -0.26698713 | AA8: 0.40656196 | AB8: Expansão | AC8: Oportunidade
A9: 421580 | B9: São Bento do Sul | C9: SC | D9: 1 | E9: 0 | F9: 0 | G9: 0 | H9: 0 | I9: 0 | J9: 1 | K9: 512968.37 | L9: 0.037645221 | M9: 13626387 | N9: 83275 | O9: Entre 50k e 100k | P9: São Bento do Sul - Rio Negrinho | Q9: Joinville | R9: 8.2934794e-05 | S9: 0.010469137 | T9: 29 | U9: 4 | V9: 60201.782 | W9: 4.5119363 | X9: 0.8119954 | Y9: 0.44217743 | Z9: -0.2334116 | AA9: 0.38281201 | AB9: Expansão | AC9: Validar
A10: 420230 | B10: Biguaçu | C10: SC | D10: 1 | E10: 0 | F10: 0 | G10: 0 | H10: 0 | I10: 0 | J10: 1 | K10: 585500.34 | L10: 0.047204778 | M10: 12403413 | N10: 76773 | O10: Entre 50k e 100k | P10: Florianópolis | Q10: Florianópolis | R10: 0.00021482493 | S10: 0.024773486 | T10: 23 | U10: 4 | V10: 35795.643 | W10: 3.8421526 | X10: 0.65656665 | Y10: 0.23090534 | Z10: -0.92760609 | AA10: 0.20695604 | AB10: Expansão | AC10: Validar
A11: 410150 | B11: Arapongas | C11: PR | D11: 4 | E11: 0 | F11: 0 | G11: 0 | H11: 0 | I11: 0 | J11: 0.75 | K11: 788656.4 | L11: 0.18596729 | M11: 16963336 | N11: 119138 | O11: Entre 100k e 150k | P11: Londrina | Q11: Londrina | R11: 0.00010387791 | S11: 0.014334252 | T11: 39 | U11: 3 | V11: 44594.278 | W11: 4.1987978 | X11: 0.98118364 | Y11: 0.34545532 | Z11: -0.013044911 | AA11: 0.46610158 | AB11: Expansão | AC11: Validar
A12: 410370 | B12: Cambé | C12: PR | D12: 4 | E12: 0 | F12: 0 | G12: 0 | H12: 0 | I12: 0 | J12: 0.5 | K12: 550069.37 | L12: 0.14686239 | M12: 14981899 | N12: 107208 | O12: Entre 100k e 150k | P12: Londrina | Q12: Londrina | R12: 7.9386989e-05 | S12: 0.012573596 | T12: 36 | U12: 3 | V12: 50622.432 | W12: 3.580381 | X12: 0.80368738 | Y12: 0.021607386 | Z12: -0.0072267783 | AA12: 0.34455932 | AB12: Expansão | AC12: Validar
A13: 420430 | B13: Concórdia | C13: SC | D13: 3 | E13: 0 | F13: 0 | G13: 0 | H13: 0 | I13: 0 | J13: 1 | K13: 804404.14 | L13: 0.16205937 | M13: 14890916 | N13: 81646 | O13: Entre 50k e 100k | P13: Concórdia | Q13: Chapecó | R13: 0.00013451732 | S13: 0.013985945 | T13: 31 | U13: 2 | V13: 58741.407 | W13: 4.7257446 | X13: 0.78275861 | Y13: 0.85532761 | Z13: 0.09883149 | AA13: 0.46775918 | AB13: Expansão | AC13: Oportunidade
... A27: 420940 | B27: Laguna | C27: SC | D27: 1 | E27: 0 | F27: 0 | G27: 0 | H27: 0 | I27: 0 | J27: 1 | K27: 621599.68 | L27: 0.087175445 | M27: 7130444.6 | N27: 42785 | O27: Entre 30k e 50k | P27: Tubarão | Q27: Criciúma | R27: -0.00014239357 | S27: -0.011475407 | T27: 28 | U27: 1 | V27: 27869.889 | W27: 3.2306668 | X27: 0.2107188 | Y27: -0.82053085 | Z27: -0.019615153 | AA27: -0.030605012 | AB27: Expansão | AC27: Validar

Sheet Critérios de filtros
Q1: Critério expansão
D2: 1° | E2: Expansão | H2: 1° | I2: Expansão | K2: 1° | L2: Expansão | Q2: População superior a 15 mil Hab. | R2: Expansão
D3: 2° | E3: Ass. Ambos = 0 | H3: 2° | I3: Ass. Ambos = 0 | K3: 2° | L3: Ass. Ambos = 0 | Q3: Demanda Farma maior ou igual 2MM
D4: 3° | E4: Lojas FSJ = 0 | H4: 3° | I4: Lojas FSJ = 0 | K4: 3° | L4: Lojas FSJ > 0 | Q4: Quantidade de lojas por Hab. maior do que "ZERO"
D5: 4° | E5: Região Imediata (Oportunidade) | H5: 4° | I5: Região Imediata (Validar)
H6: 5°

Sheet Cidades
A1: CÓD. MUNICÍPIO | B1: Município | C1: UF | D1: Porte de Cidades | E1: Índice de Competição da Cidade | F1: Mesorregião
A2: 410010 | B2: Abatiá | C2: PR | D2: Menor que 10k | E2: - | F2: Norte Pioneiro Paranaense
A3: 420005 | B3: Abdon Batista | C3: SC | D3: Menor que 10k | E3: - | F3: Serrana
A4: 420010 | B4: Abelardo Luz | C4: SC | D4: Entre 10k e 20k | E4: - | F4: Oeste Catarinense
A5: 430003 | B5: Aceguá | C5: RS | D5: Menor que 10k | E5: - | F5: Sudoeste Rio-grandense
A6: 410020 | B6: Adrianópolis | C6: PR | D6: Menor que 10k | E6: - | F6: Metropolitana de Curitiba
A7: 420020 | B7: Agrolândia | C7: SC | D7: Entre 10k e 20k | E7: - | F7: Vale do Itajaí
A8: 420030 | B8: Agronômica | C8: SC | D8: Menor que 10k | E8: - | F8: Vale do Itajaí
A9: 420040 | B9: Água Doce | C9: SC | D9: Menor que 10k | E9: - | F9: Oeste Catarinense
A10: 430005 | B10: Água Santa | C10: RS | D10: Menor que 10k | E10: - | F10: Noroeste Rio-grandense
A11: 420050 | B11: Águas de Chapecó | C11: SC | D11: Menor que 10k | E11: - | F11: Oeste Catarinense
A12: 420055 | B12: Águas Frias | C12: SC | D12: Menor que 10k | E12: - | F12: Oeste Catarinense
A13: 420060 | B13: Águas Mornas | C13: SC | D13: Menor que 10k | E13: - | F13: Grande Florianópolis
... A1192: 421985 | B1192: Zortéa | C1192: SC | D1192: Menor que 10k | E1192: - | F1192: Serrana

Sheet Base Lojas
A1: ID_LOJA | B1: ID_CIDADE | C1: DIRETOR | D1: DISTRITAL | E1: DATA DE ABERTURA | F1: LOJAS | G1: VENDA FEV'26 | H1: DRE JAN´26 | I1: MÉDIA FATURAMENTO DE FEV'25 ATÉ JAN'26 | J1: DRE_AC JAN/26
A2: 1 | B2: 431330 | C2: Laerti Siqueira | D2: Fábio Baldasso | E2: 35254 | F2: Nova Prata 1 | G2: 820028.96 | H2: 0.082073498 | I2: 871765.6 | J2: 0.11116296
A3: 2 | B3: 431180 | C3: Cintia Silva | D3: Fais Abdalla | E3: 36355 | F3: Marau 1 | G3: 1282852.8 | H3: 0.11686734 | I3: 1371424.5 | J3: 0.12491347
A4: 3 | B4: 431370 | C4: Cintia Silva | D4: Fais Abdalla | E4: 36495 | F4: Palmeira 1 | G4: 766453.18 | H4: 0.13343376 | I4: 843302.27 | J4: 0.10552584
A5: 4 | B5: 432280 | C5: Laerti Siqueira | D5: Fábio Baldasso | E5: 36447 | F5: Veranopolis 1 | G5: 1191484.1 | H5: 0.12947075 | I5: 1332132.6 | J5: 0.1265764
A6: 5 | B6: 432190 | C6: Cintia Silva | D6: Fais Abdalla | E6: 36516 | F6: Tres Passos 1 | G6: 375427.81 | H6: 0.071832849 | I6: 457036 | J6: 0.067359964
A7: 9 | B7: 430470 | C7: Cintia Silva | D7: Fais Abdalla | E7: 37026 | F7: Carazinho 1 | G7: 295979.33 | H7: 0.059309091 | I7: 305208.25 | J7: 0.041726291
A8: 10 | B8: 430700 | C8: Cintia Silva | D8: Fais Abdalla | E8: 37081 | F8: Erechim 2 | G8: 332119.72 | H8: -0.073262337 | I8: 337675.07 | J8: -0.029746121
A9: 11 | B9: 431410 | C9: Cintia Silva | D9: Fais Abdalla | E9: 42261 | F9: PF - Vera Cruz 3 | G9: 452735.31 | H9: 0.12642191 | I9: 501549.22 | J9: 0.13420805
A10: 12 | B10: 431410 | C10: Cintia Silva | D10: Fais Abdalla | E10: 37459 | F10: PF - Petropolis | G10: 1671678.2 | H10: 0.15357976 | I10: 1781445.5 | J10: 0.15845352
A11: 13 | B11: 432010 | C11: Cintia Silva | D11: Fais Abdalla | E11: 37571 | F11: Sarandi 1 | G11: 841552.7 | H11: 0.10845711 | I11: 772229.65 | J11: 0.069121717
A12: 14 | B12: 431410 | C12: Cintia Silva | D12: Fais Abdalla | E12: 37510 | F12: PF - General Neto | G12: 633474.48 | H12: 0.14688741 | I12: 695376.87 | J12: 0.13691073
A13: 16 | B13: 431410 | C13: Cintia Silva | D13: Fais Abdalla | E13: 37713 | F13: PF - Cap. Eleuterio | G13: 437965.29 | H13: 0.038398599 | I13: 489250.14 | J13: 0.055377426
... A1229: 1583 | B1229: 430460 | C1229: Laerti Siqueira | D1229: Andre Jaime | E1229: 45730 | F1229: Canoas 37 | G1229: 762747.93 | H1229: 0.04367861 | I1229: 773733.53 | J1229: 0.052623201
A1230: 1650 | B1230: 430545 | C1230: Laerti Siqueira | D1230: Andre Jaime | E1230: 42704 | F1230: Cidreira - Nova | G1230: 951757.81 | H1230: - | I1230: 475902.41 | J1230: -
A1231: 1083 | B1231: 430770 | C1231: Laerti Siqueira | D1231: Andre Jaime | E1231: 45843 | F1231: Esteio 7 | G1231: 704012.72 | H1231: 0.10336433 | I1231: 622929.03 | J1231: 0.073677964
A1232: 1552 | B1232: 432150 | C1232: Laerti Siqueira | D1232: Andre Jaime | E1232: 45688 | F1232: Torres 9 | G1232: 576926.49 | H1232: 0.1606704 | I1232: 486541.38 | J1232: 0.096137781
A1233: 1504 | B1233: 430520 | C1233: Cintia Silva | D1233: Juliano Petrarca | E1233: 45707 | F1233: Cerro Largo | G1233: 863154.53 | H1233: 0.083554752 | I1233: 831969.87 | J1233: 0.07776691
A1234: 1541 | B1234: 431740 | C1234: Cintia Silva | D1234: Juliano Petrarca | E1234: 45722 | F1234: Santiago 4 | G1234: 671853.48 | H1234: 0.10954882 | I1234: 632504.46 | J1234: 0.08300487
A1235: 1581 | B1235: 430920 | C1235: Laerti Siqueira | D1235: Luiz Kuhn | E1235: 45898 | F1235: Gravatai 19 | G1235: 568968.01 | H1235: 0.11819259 | I1235: 544914.75 | J1235: 0.08160891
A1236: 1492 | B1236: 430460 | C1236: Laerti Siqueira | D1236: Andre Jaime | E1236: 45784 | F1236: Canoas 33 | G1236: 669607.94 | H1236: 0.10404145 | I1236: 703473.03 | J1236: 0.097112346
A1237: 1515 | B1237: 431240 | C1237: Laerti Siqueira | D1237: Luiz Kuhn | E1237: 45747 | F1237: Montenegro 7 | G1237: 617272.3 | H1237: 0.086333933 | I1237: 591190.58 | J1237: 0.097218315
A1238: 1588 | B1238: 430760 | C1238: Laerti Siqueira | D1238: Luiz Kuhn | E1238: 45745 | F1238: Estancia Velha 9 | G1238: 595644.33 | H1238: 0.091981538 | I1238: 609803.06 | J1238: 0.10474842
A1239: 1663 | B1239: 420570 | C1239: Laerti Siqueira | D1239: Cleiton Lima | E1239: 46021 | F1239: Garopaba 2 - Nova | G1239: 637323.35 | H1239: 0.12449051 | I1239: 553542.52 | J1239: 0.1761872

Sheet Contratos assinados 
B1: ID | C1: Cod. Loja | D1: Loja | E1: UF | F1: Cidade | G1: Apelido/Loja | H1: Data de recebimento | I1: Solicitante | J1: Status | K1: Data de último status | L1: Lat-Long | M1: Endereço | N1: Transferência | O1: Posição Solar 15h | P1: Ponto | Q1: Aprovado | R1: Responsável de Estudo | S1: Potencial Calculado | T1: OBJETIVO DE VENDA LOJA | U1: Enviado p/ solicitante | V1: Data de Execução de Estudo | W1: Data de envio p/ solicitante | X1: Número de concorrentes próximos | Y1: FSJ mais próxima | Z1: População do estudo | AA1: Distãncia FSJ (KM) | AB1: Apontamento | AC1: Link (Ponto) | AD1: Link (Vídeo) | AE1: Link (Estudo) | AF1: Observação Estudo | AG1: Responsável por projeto | AH1: Data de pedido de proposta | AI1: Tipo de Obra | AJ1: Tipo de Obra Agrupado | AK1: Valor total do orçamento | AL1: Área Construida Total: | AM1: Área Interna Total: | AN1: Mezanino | AO1: Vagas | AP1: 3D de projeto | AQ1: Responsável de contrato | AR1: Responsável Negociação | AS1: Data de início de negóciação/minuta | AT1: Data de assinatura do proprietário | AU1: Data de assinatura Sr. Pedro | AV1: Aluguel/Aquisição | AW1: Prazo de Locação | AX1: Vigência | AY1: Multa de contrato | AZ1: Custo F. São João | BA1: Custo Investidor | BB1: Possuí Inquilino | BC1: Projeção de Vendas 1° mês | BD1: Projeção de Vendas 2° mês | BE1: Projeção de Vendas 3° mês | BF1: Projeção de Vendas 4° mês | BG1: Projeção de Vendas 5° mês | BH1: Projeção de Vendas 6° mês | BI1: Projeção de Vendas 12° meses | BJ1: Observação Negociação e Contrato | BK1: Data de Abertura | BL1: Data de Fechamento da Loja
B2: 294 | C2: - | D2: Bagé 7 | E2: RS | F2: Bagé | G2: Hospital | H2: 45597 | I2: B. Empreendimentos | J2: Aquisição | K2: 45775 | L2: -31.32611824214506, -54.11067217339977 | M2: R. Gomes Carneiro, 1355 - Centro, Bagé - RS, 96400-130 (-31.32611824214506, -54.11067217339977) | Q2: Aprovado | R2: Eduardo | S2: 572242.65 | U2: Felt | V2: 45608 | W2: 45608 | X2: 30 | Y2: Bagé 01 | Z2: 9738 | AF2: Estudo refeito, potencial anterior R$570.193,11 | AI2: Aquisição | AJ2: Aquisição | AS2: 45110 | AT2: 45110 | AU2: 45110 | AV2: Brair Empreendimentos | AW2: aquisição | AX2: aquisição
B3: 295 | C3: 1473 | D3: Canela 6 | E3: RS | F3: Canela | G3: Canela 6 | H3: 45582 | I3: B. Empreendimentos | J3: Aquisição | K3: 45474 | L3: -29.354830331, -50.800551943 | M3: R. João Pessoa - Canelinha, Canela - RS, 95680-000 (-29.354830331, -50.800551943) | Q3: Aprovado | R3: Eduardo | S3: 506523.51 | U3: B. Empreendimentos | V3: 45582 | W3: 45582 | X3: 4 | Y3: Canela 4 | AF3: Espelho canela 4 e Canela 1 | AG3: Arq. Bárbara Marcon | AH3: 45338 | AI3: Aquisição | AJ3: Aquisição | AK3: aquisição | AL3: 458m² | AM3: 262,82m² salão de vendas | AN3: _ | AO3: 6 | AP3: Não se aplica | AQ3: Marina | AR3: Tatiana Brair | AS3: 45474 | AT3: 45474 | AU3: 45474 | AV3: 1156200 | AW3: aquisição | AX3: aquisição
B4: 296 | C4: - | E4: RS | F4: Canoas | G4: Jardim do lago - aquisição aguardando definição | H4: 45569 | I4: B. Empreendimentos | J4: Aquisição | K4: 45566 | M4: R. Dona Rafaela, 343 - Mal. Rondon, Canoas - RS, 92020-030 | Q4: Aprovado | R4: Eduardo | S4: 565480.95 | U4: B. Empreendimentos | V4: 45576 | W4: 45576 | X4: 10 | Y4: Canoas 28 | AF4: Aquisição aguardando definição | AG4: Arq. Henrique Terres | AH4: 45168 | AI4: Aquisição | AJ4: Aquisição | AK4: aquisição | AO4: 16 | AP4: Realizado | AQ4: Ricardo | AR4: André Jaime | AS4: 45474 | AT4: 45474 | AU4: 45565 | AV4: aquisição | AW4: aquisição | AX4: aquisição
B5: 299 | C5: - | E5: RS | F5: Horizontina | G5: TR- Endereço - Horizontina 1 | H5: 45562 | I5: B. Empreendimentos | J5: Aquisição | L5: -27.628232328, -54.308113678 | M5: 1254 R. Uruguai- centro (-27.628232328, -54.308113678) | N5: Horizontina 1 | Q5: Aprovado | R5: Felipe | S5: 1396867.3 | U5: B. Empreendimentos | V5: 45565 | W5: 45565 | AC5: https://maps.app.goo.gl/dRGADH4mNp3gLYMM6 | AI5: Aquisição | AJ5: Aquisição | AQ5: Lucas Schwingel | AR5: Tatiana Brair | AS5: 45141 | AT5: 45141 | AU5: 45141 | AV5: Brair Empreedimentos | AW5: aquisição | AX5: aquisição | AY5: Brair Empreendimentos | BA5: Brair Empreendimentos | BJ5: data de ass corforme a data de aquisição.
B6: 300 | C6: - | E6: RS | F6: Pelotas | G6: Vespeiro - aquisição aguardando definição | H6: 45569 | I6: B. Empreendimentos | J6: Aquisição | K6: 45474 | L6: -31.739794657991244, -52.357933344401076 | M6: Av. Francisco Caruccio, 1128 - Tres Vendas, Pelotas - RS, 96020-450 (-31.739794657991244, -52.357933344401076) | Q6: Aprovado | R6: Eduardo | S6: 452128.93 | U6: Felt | V6: 45597 | W6: 45597 | X6: 7 | Y6: Pelotas 09 | Z6: 18091 | AF6: Não foi encontrado parâmetros para utilização das lojas espelhos, potencial do estudo antigo era de R$478.842,03 | AG6: Arq. Henrique Terres | AH6: 45346 | AI6: Aquisição | AJ6: Aquisição | AK6: aquisição | AO6: _ | AP6: Não se aplica | AQ6: Lucas Schwingel | AR6: Tatiana Brair | AS6: 45474 | AT6: 45474 | AU6: 45474 | AV6: Brair Empreendimentos | AW6: Brair Empreendimentos | AX6: Brair Empreendimentos | AY6: Brair Empreendimentos
B7: 310 | C7: - | D7: Balneário 6 | E7: SC | F7: Balneário Camboriú | G7: Praia dos amores - Balneário Camboriú 6 | H7: 45597 | I7: Quadro | J7: Assinado por ambos | K7: 45597 | L7: -26.955519353, -48.637717211 | M7: Av. Carlos Drummond de Andrade, 770 - Praia dos Amores, Balneário Camboriú - SC, 88306-830 (-26.955519353, -48.637717211) | Q7: Aprovado | R7: Eduardo | S7: 522890.05 | U7: Renan Walker | V7: 45597 | W7: 45597 | X7: 5 | Y7: Itajaí 01 | AF7: Estudo precisa ser atualizado antes de enviar para a controladoria. Teve inauguração de uma concorrente antecipando e o contrato é de 2023. | AG7: Arq. Henrique Terres | AH7: 45064 | AI7: Investidor | AJ7: BTS | AK7: 1.290.626.05 | AL7: 795 | AM7: 320m² | AO7: 17 | AP7: Realizado | AQ7: Lucas Machado | AR7: Cleiton de Lima | AS7: 45078 | AT7: 45103 | AU7: 45103 | AV7: R$38.000 no primeiro ano e R$40.000 após o segundo ano | AW7: 180 meses
B8: 319 | C8: - | E8: RS | F8: Passo Fundo | G8: Redondão - aquisição | H8: 45558 | I8: B. Empreendimentos | J8: Aquisição | K8: 45474 | M8: R. Uruguai, 1550 - Centro, Passo Fundo /RS, 99010-111 | Q8: Aprovado | R8: Pendente profissional | U8: B. Empreendimentos | AF8: Contrato assinado | AI8: Aquisição | AJ8: Aquisição | AQ8: Gabriel | AR8: Gabriel Zayaeskoski | AS8: 45277 | AT8: 45556 | AU8: 45556 | AV8: 1175000 | AW8: aquisição | AY8: 03 aluguéis proporcionais | BC8: não se aplica | BD8: não se aplica | BE8: não se aplica | BF8: não se aplica | BG8: não se aplica | BH8: não se aplica | BJ8: Aquisição
B9: 344 | C9: 1669 | E9: SC | F9: São José | G9: Bosque das Mansões | H9: 45569 | I9: Cleiton de Lima | J9: Assinado por ambos | K9: 45972 | L9: -27.585216260, -48.619495618 | M9: Av. Osvaldo José do Amaral, 940 - Real Parque, São José - SC, 88113-335 (-27.585216260, -48.619495618) | Q9: Reprovado | R9: Pablo | S9: 515989.23 | T9: 826039.51 | U9: Cleiton de Lima | V9: 45574 | W9: 45574 | X9: 10 | Y9: São José 06 | Z9: 33744 | AA9: 1.98 | AB9: Não | AC9: https://maps.app.goo.gl/Fw2wNLHHi34AFaqp8 | AE9: Link do estudo | AF9: - | AG9: Arq. Henrique Terres | AH9: 45967 | AI9: Investidor/ FSJ | AJ9: BTS A | AK9: 1614155.5 | AL9: 405m² | AM9: 327m² de térreo e 78m² de mezanino | AN9: 78m² | AO9: 13 | AP9: Realizado | AQ9: Lucas Machado | AR9: Luan Pessoa | AS9: 45966 | AT9: 45966 | AU9: 45972 | AV9: R$ 25.000,00 1° ano; R$ 27.000,00 2° ano; R$ 30.000,00 3° ano. | AW9: 144 meses | AX9: Inauguração | AY9: Entrega do imóvel no 1° ano = 48 aluguéis proporcionais; Entrega do imóvel no 2° ano = 36 aluguéis proporcionais; Entrega do imóvel no 3° ano = 24 aluguéis proporcionais; Entrega do imóvel no 4° ano = 12 aluguéis proporcionais e, por fim, após o 5° ano = 3 aluguéis proporcionais. | AZ9: 414155.52 | BA9: 1200000 | BC9: 415000 | BD9: 425000 | BE9: 440000 | BF9: 450000 | BG9: 465000 | BH9: 475000 | BI9: 530000 | BJ9: Investidor aporta até R$ 1.200.000,00 (um milhão e duzentos mil reais). Pelo orçamento teremos um custo de mais R$ 414.155,52 de investimento pela FSJ. Imóveis possui necessidade de retirar árvores, fazer contenções e fundações com hélice continua. Reajuste a partir do 37° mês de vigência pela média do IGP-M e IPCA.
B10: 384 | C10: - | D10: - | E10: RS | F10: Tramandaí | G10: "Hospital" | H10: 45581 | I10: Laerti Siqueira | J10: Assinado por ambos | K10: 46107 | L10: -29.992052991, -50.140901308 | M10: Av. Emancipação, 1357 - Centro, Tramandaí - RS, 95590-000 (-29.992052991, -50.140901308) | O10: Boa | Q10: Aprovado | R10: Pablo | S10: 555426.53 | T10: 889174.1 | U10: Laerti Siqueira | V10: 46078 | W10: 46078 | X10: 15 | Y10: Tramandaí 2 | Z10: 10153 | AA10: 0.289 | AB10: Não | AC10: https://maps.app.goo.gl/uiL7QDZmyhqqH7yg9 | AE10: https://farmaciassaojoao.sharepoint.com/:b:/s/expansao/IQAiSUE6wL_dSLyk_5Gh4zsuAY5ixHtmMaSSnL0UC5o2cZQ?e=uOX86Z | AF10: (1° Estudo refeito, potencial anterior R$461.353,00) (2° Estudo refeito, potencial anterior R$ 525.828,72) | AG10: Arq. Henrique Terres | AH10: 46070 | AI10: Investidor/ FSJ | AJ10: BTS A | AK10: 1757166.8 | AL10: 528m² | AM10: 312m² de térreo e 76m² de mezanino | AN10: 76m² | AO10: 12 | AP10: Realizado | AQ10: Gabriel | AR10: Laerti Siqueira | AS10: 46078 | AT10: 46107 | AV10: 27000 | AW10: 120 meses | AX10: Inauguração da loja | AY10: Até o 2° ano = 6 aluguéis proporcionais. Após, 3 aluguéis proporcionais. | AZ10: 144636 | BA10: 1612530.8 | BB10: Não | BJ10: Reajuste pela média do IGP-M e IPCA. Investidor irá construir a loja para nós, ficou acertado de pagarmos 50% da elétrica e a fachada toda (ACM + Comunicação visual). Entrega 30/11/2026.
B11: 392 | C11: 328 | D11: S.Fran Paula 2 | E11: RS | F11: São Francisco de Paula | G11: Ampliação | H11: 45581 | I11: Fabio Baldasso | J11: Ampliação | K11: 45593 | L11: -29.447991059, -50.582049367 | M11: Avenida Julio de Castilhos, nº 341, Bairro: Centro, São Francisco de Paula | Q11: Aprovado | R11: Kauê | S11: 0 | U11: Quadro | V11: 45597 | W11: 45597 | X11: 0 | Y11: São F. de Paula 3 | Z11: 0 | AF11: Não foi feito estudo, apenas reforma da loja! | AG11: Arq. Priscila Polese | AH11: 45552 | AI11: Ampliação | AJ11: Reforma FSJ | AK11: 534557.73 | AM11: 456m² de terreno, 291m² de área interna total, e | AO11: 4 | AP11: Realizado | AQ11: Ricardo | AR11: Fabio Baldasso | AS11: 45580 | AT11: 45580 | AU11: 45593 | AV11: 20000 | AW11: 180 meses | AX11: 45580 | AY11: 03 aluguéis proporcionais | BB11: Não | BC11: 500000 | BD11: 550000 | BE11: 550000 | BF11: 510000 | BG11: 530000 | BH11: 550000
B12: 494 | C12: 1584 | D12: Poa 127 | E12: RS | F12: Porto Alegre | G12: POA 127 - PUC/RS | H12: 45607 | I12: Laerti Siqueira | J12: Assinado por ambos | K12: 45610 | L12: -30.055266000, -51.169366244 | M12: Porto Alegre - Av. Ipiranga, 6924 - Partenon, RS, 90160-091 (-30.055266000, -51.169366244) | Q12: Aprovado | R12: Pablo | S12: 569316.21 | U12: Karin Moraes | V12: 45608 | W12: 45608 | X12: 9 | Y12: Porto Alegre 74 | Z12: 13198 | AF12: Estudo refeito. | AG12: Terceiro(a) | AH12: 45560 | AI12: Investidor/ FSJ | AJ12: BTS A | AM12: 586,69m² Terreno | AO12: _ | AP12: Não se aplica | AQ12: Pedro | AR12: Laerti Siqueira | AS12: 45530 | AT12: 45604 | AU12: 45610 | AV12: R$25.000 com 5 meses de carência total no valor do aluguel e do 6° mês ao 12° carência de 50% no valor do aluguel. com reajuste pelo indice do IPCA. | AW12: 59 meses sem direito a renovatória - sem inicio de vigência | AY12: MULTA LOCADOR - iniciando em 900k do 60° ao 71° mês, 750k do 72° a 83° , 600k do 84° ao 95°, 450k do 96° ao 107°, 300k do 108° ao 120°. MULTA LOCATÁRIO - 3 aluguéis porporcionais | AZ12: Locação de Superficie | BA12: 0.00 | BB12: Não
B13: 565 | C13: 1659 | D13: Castro 1 | E13: PR | F13: Castro | G13: Rótula condor | H13: 45622 | I13: Controladoria | J13: Assinado por ambos | K13: 45622 | L13: -24.795820928, -49.999424181 | M13: Castro - R. Santos Dumont, 36 - Vila Rio Branco, PR, 84172-260 (-24.795820928, -49.999424181) | Q13: Aprovado | R13: Eduardo | S13: 473317.83 | U13: Controladoria | V13: 45625 | W13: 45625 | X13: 10 | Y13: Piraí do Sul 01 | Z13: 8130 | AF13: Estudo refeito, potencial anterior R$617.355,15 | AG13: Arq. Henrique Terres | AH13: 45547 | AI13: Investidor | AJ13: BTS | AM13: 258m² | AO13: 14 | AP13: Realizado | AQ13: Pedro | AR13: Rodrigo Ferreira | AS13: 45555 | AT13: 45561 | AU13: 45562 | AV13: 24000 | AW13: 180 meses | AY13: BTS 50 meses | BA13: 1221475.8 | BB13: Não | BC13: 500000 | BD13: 520000 | BE13: 540000 | BF13: 560000 | BG13: 580000 | BH13: 600000
B14: 566 | C14: - | D14: - | E14: SC | F14: Porto Belo | G14: Posto 4 Ilhas | H14: 45622 | I14: Cleiton de Lima | J14: Assinado por ambos | K14: 46006 | L14: -27.158887773, -48.567193841 | M14: Porto Belo - Av. Gov. Celso Ramos, 184 - Perequê, SC, 88210-000 (27°09'32.0"S 48°34'01.9"W) | Q14: Reprovado | R14: Pablo | S14: 577664.11 | T14: 924773.91 | U14: Cleiton de Lima | V14: 45995 | W14: 45995 | X14: 3 | Y14: Porto Belo 1 | Z14: 11312 | AA14: 1.49 | AB14: Não | AC14: https://maps.app.goo.gl/H1FfJSiWdrBMsAdH6 | AD14: https://farmaciassaojoao.sharepoint.com/:v:/s/expansao/IQDZxL5oetLfSY4AtCDdiLIRAYSYkxo7upmyyJKAPl3dV94?e=LhF8J0 | AE14: https://farmaciassaojoao.sharepoint.com/:b:/s/expansao/IQAHYwuSsCloTK1JDAqghEteAc0LK44sp3kWV3w9zWuIY7Y?e=uKhw2o | AF14: Refeito estudo, potencial anterior R$351.229,76 (Vai ser visitado novamente. "Entrega pronto") | AQ14: Lucas Machado | AR14: Cleiton de Lima | AS14: 45842 | AT14: 45995 | AU14: 46006 | AV14: 24000 | AW14: 180 meses
B15: 576 | C15: 1585 | D15: Porto Alegre128 | E15: RS | F15: Porto Alegre | G15: Porto Alegre 128 / Ari Tarragô (Aquisição) | H15: 45628 | I15: Naudal Almeida | J15: Aquisição | K15: 45947 | L15: -30.042328154, -51.135510050 | M15: Av. Protásio Alves, 7568 - Morro Santana, Porto Alegre - RS, 90410-006 (-30.042270934670185, -51.135473352318655) | N15: Talvez TR da 92 | Q15: Aprovado | R15: Eduardo | S15: 436437.27 | U15: Naudal Almeida | V15: 45628 | W15: 45628 | X15: 6 | Y15: Porto Alegre 22 | Z15: 17648 | AA15: 1.06 | AB15: Não | AC15: https://maps.app.goo.gl/8nx1Ekhc6NRCeM4s8 | AF15: Estudo refeito, potencial anteriror R$620.620,77 | AG15: Arq. Priscila Polese | AH15: 45573 | AI15: Investidor/ FSJ | AJ15: BTS A | AK15: 1141793.4 | AL15: 270 | AN15: 74 | AO15: 13 | AP15: Realizado | AQ15: Gabriel | AR15: Naudal Almeida | AS15: 45568 | AT15: 45625 | AU15: 45629 | AV15: 18000 | AW15: 120 meses | AX15: Inauguração (aguardando aditivo ) | AY15: Até o 2° ano = 6 aluguéis proporcionais. Após, 3 aluguéis proporcionais. | AZ15: 16675 | BA15: 1124998 | BB15: Não | BC15: 335000 | BD15: 368500 | BE15: 405350 | BF15: 445885 | BG15: 490473.5 | BH15: 539520.85 | BJ15: Investidor constrói e entrega a sala. Apenas não faz a comunicação visual que foi orçada em R$ 16.500 (custo FSJ). Reajuste pela média do IPCA e IGP-M.
B16: 581 | C16: 741 | D16: Estância Velha 6 | E16: RS | F16: Estância Velha | G16: Estância Velha 6 NOVA | H16: 45629 | I16: Quadro | J16: Assinado por ambos | K16: 45929 | L16: -29.669433916, -51.146329957 | M16: Estância Velha - R. Rincão, 311 - Rincão dos Ilhéus, RS, 93600-000 (-29.669433916, -51.146329957) | N16: Estância Velha 6 | Q16: Aprovado | R16: Eduardo | S16: 591297.06 | U16: Luiz Kuhn | V16: 45929 | W16: 45929 | X16: 7 | Y16: Estância Velha 02 | Z16: 8766 | AA16: 0.95 | AB16: Não | AC16: https://maps.app.goo.gl/iZaSKspcBUTHyg6v6 | AE16: Link do estudo | AF16: Estudo refeito, potencial anterior R$540.168,35 | AG16: Arq. Mariane Adorian | AH16: 45602 | AI16: Investidor/ FSJ | AJ16: BTS A | AK16: 1072365.9 | AL16: 340m² | AM16: 267m² | AN16: 44m² | AO16: 10 | AP16: Aguardando | AQ16: Marina | AR16: Luiz kuhn | AS16: 45548 | AT16: 45548 | AU16: 45548 | AV16: 15500 | AW16: 120 | AX16: Inauguração (aguardando aditivo ) | AY16: sendo cumprido o prazo de 12 (doze) meses pagará uma multa equivalente a 36 (trinta e seis) meses de aluguel vigente a época; sendo cumprido o prazo de 24 (vinte e quatro) meses pagará uma multa equivalente a 24 (vinte e quatro) meses de aluguel vigente a época; sendo cumprido o prazo de 36 (trinta e seis) meses pagará uma multa equivalente a 12 (doze) meses de aluguel vigente a época; sendo cumprido o prazo de 48 (quarenta e oito) meses pagará uma multa equivalente a 06 (seis) meses de aluguel vigente a época; A partir do cumprimento de 60 (sessenta) meses, pagará uma multa de 3 (três) meses. | BB16: não | BC16: 549870.43 | BD16: 580000 | BE16: 600000 | BF16: 630000 | BG16: 680000 | BH16: 700000
B17: 645 | C17: 1366 | D17: Forquilhinha 1 | E17: SC | F17: Forquilhinha | G17: - | H17: 45643 | I17: Controladoria | J17: Assinado por ambos | K17: 46073 | L17: -28.751593194, -49.472923647 | M17: Av. 25 de Julho, 2487 - Centro, Forquilhinha - SC, 88850-000 (-28.751593194, -49.472923647) | O17: Ruim | Q17: Não visitado | R17: Pablo | S17: 477880 | T17: 765031.01 | U17: Controladoria | V17: 46074 | W17: 46074 | X17: 13 | Y17: Criciuma 5 | Z17: 19891 | AA17: 10.12 | AB17: Eduardo | AC17: https://maps.app.goo.gl/Gb32ciUUGjA5VCnj6 | AE17: https://farmaciassaojoao.sharepoint.com/:b:/s/expansao/IQBrZyxcfNXlTb6b-BeIPnYKAQcX8_Co0Z66zQ6umlcuhmI?e=a1LVxT | AF17: Estudo refeito, potencial anterior R$465.764,99. | AG17: Arq. Henrique Terres | AH17: 45365 | AI17: Investidor | AJ17: BTS | AL17: 289 | AN17: 69m² | AO17: 15 | AQ17: Gabriel | AR17: Naudal Almeida | AS17: 44987 | AT17: 44999 | AU17: 44999 | AV17: 15000 | AW17: 240 meses | AY17: Até o 2° ano = 6 aluguéis proporcionais. Após, 3 aluguéis proporcionais.
B18: 701 | C18: - | E18: RS | F18: Vacaria | G18: Dr. Flores - Possivel TR da Vacaria 8 | H18: 45670 | I18: Lucas Machado | J18: Aquisição | K18: 45681 | L18: -28.503804493, -50.938834969 | M18: Vacaria - R. Dr. Flores, 453 - Centro, RS, 95200-000 (-28.503804493, -50.938834969) | Q18: Não visitado | R18: Pablo | S18: 718116 | U18: Lucas Machado | V18: 45680 | W18: 45680 | X18: 30 | Y18: Vacaria 2 | Z18: 12400 | AA18: 0.09 | AB18: Não | AC18: https://maps.app.goo.gl/gcBHxV5RA39gn6nGA | AF18: Estudo feito, Considerando TR da 8 | AG18: Arq. Henrique Terres | AH18: 45677 | AI18: Aquisição | AJ18: Aquisição | AK18: aquisição | AO18: 8 | AP18: Não se aplica | AQ18: Lucas Machado | AR18: Lucas Machado | AS18: 45679 | AT18: 45681 | AU18: 45693 | AV18: 3000000 | AW18: aquisição | AX18: aquisição | AY18: aquisição | AZ18: aquisição | BA18: aquisição | BB18: não
B19: 776 | C19: - | E19: RS | F19: Caçapava do Sul | G19: Ampliação Caçapava 3 | H19: 45680 | I19: Laercio Becker | J19: Assinado por ambos | K19: 45680 | L19: -30.51427964457042, -53.484911064322105 | M19: R. Benjamim Constant,1275 (-30.51427964457042, -53.484911064322105) | Q19: Aprovado | R19: Pablo | S19: 1007000 | U19: Contrato | V19: 45680 | W19: 45680 | X19: 6 | Y19: Cacapava do sul 1 | Z19: 18150 | AA19: 0.74 | AB19: Não | AC19: https://maps.app.goo.gl/ZTfFqMxj9VVjoJX99 | AF19: Não foi feito PDF por se tratar de uma ampliação. Foi considerado um aumento na captura do mercado que impactara em 7% na venda final da loja. | AG19: Arq. Henrique Terres | AH19: 45666 | AI19: Reforma FSJ | AJ19: Reforma FSJ | AO19: 17 | AP19: Realizado | AQ19: Gabriel | AR19: Laercio Becker | AS19: 45680 | AT19: 45680 | AU19: 45680 | AV19: 13000 | AW19: Ampliação | AX19: Ampliação | AY19: Ampliação | BB19: - | BC19: 1100000 | BD19: 1150000 | BE19: 120000 | BF19: 1250000 | BG19: 130000 | BH19: 1400000 | BJ19: -
B20: 954 | C20: - | E20: RS | F20: Jaguarão | G20: Mercado Dona | H20: 45664 | I20: Juliano Petrarca | J20: Assinado por ambos | K20: 45735 | L20: -32.566608641, -53.380880476 | M20: R. Uruguai, 184, Jaguarão - RS, 96300-000 (-32.566608641, -53.380880476) | Q20: Não visitado | R20: Pablo | S20: 695790.27 | U20: Juliano Petrarca | V20: 45665 | W20: 45665 | X20: 15 | Y20: Jaguarão 2 | Z20: 26494 | AA20: 0.41 | AB20: Próximo Pablo | AC20: https://maps.app.goo.gl/NFFoiKSdtfF74rFm8 | AF20: Contrato assinado - Documentação (Iphan) está pra sair em torno de 15 dias. Pessoal do obras já está organizando questões de pré-moldados e etc. | AG20: Arq. Adeline Saggiorato | AH20: 45729 | AI20: Reforma FSJ | AJ20: Reforma FSJ | AL20: 505,04m² | AO20: 19 | AP20: Solicitado | AQ20: Marina | AR20: Juliano Petrarca | AS20: 45674 | AT20: 45727 | AU20: 45735 | AV20: 25000 | AW20: 120 meses | AX20: Inauguração (aguardando aditivo ) | AY20: 3 alugueis proporcionais | BB20: _ | BJ20: Carência de 4 meses
B21: 997 | C21: - | E21: RS | F21: Santa Clara do Sul | G21: - | H21: 45740 | I21: Tiago Machado | J21: Assinado por ambos | K21: 46003 | L21: -29.468269769, -52.086302131 | M21: R. Alberto Schabbach, 223, Santa Clara do Sul - RS, 95915-000 (-29.468269769, -52.086302131) | Q21: Não visitado | R21: Pablo | S21: 447343.36 | T21: 716145.35 | U21: Laercio Becker | V21: 46002 | W21: 46002 | X21: 2 | Y21: Lajeado 8 | Z21: 4519 | AA21: 9.09 | AB21: Não | AC21: https://maps.app.goo.gl/1nHtuojdG5urjjNd7 | AE21: https://farmaciassaojoao.sharepoint.com/:b:/s/expansao/IQCTJFz6zof4SKrUJtDXo3jsAb_lXwdhWCOqFzDMOhDJ1o4?e=ECkmAs | AF21: Estudo refeito, potencial anterior R$388.741,86. Local já tinha sido trazido pelo Tiago Machado e foi recusado por o estudo ter dado muito baixo. | AQ21: Lucas Machado | AR21: Laercio Becker | AS21: 46002 | AT21: 46002 | AU21: 46003 | AV21: 13500 | AW21: 240 meses | BB21: não | BC21: 400000 | BD21: 425000 | BE21: 450000 | BF21: 500000 | BG21: 525000 | BH21: 550000
B22: 1008 | C22: 410 | D22: Santa Cruz 8 | E22: RS | F22: Santa Cruz do Sul | G22: TR STA CRUZ 8/DELEGACIA | H22: 45743 | I22: Laercio Becker | J22: Assinado por ambos | K22: 45792 | L22: -29.719890371, -52.432375253 | M22: Rua Fernando Abott, 789 - Goiás, Santa Cruz do Sul - RS, 96810-148 (-29.71972741844415, -52.43235811832986) | N22: STA CRUZ 8 | Q22: Não visitado | R22: Pablo | S22: 553769.89 | U22: Laercio Becker | V22: 45748 | W22: 45748 | X22: 38 | Y22: Santa Cruz 8 | Z22: 20949 | AA22: 0.3 | AB22: Não | AC22: https://maps.app.goo.gl/1RxjWS91bdmhA5P29 | AE22: https://farmaciassaojoao.sharepoint.com/:b:/s/expansao/IQCmfsdu-F4MSpj9XCPlLoehAdgconXHVzZsLb4wgmqMBjA?e=odQK5v | AF22: Contrato assinado em 06/01/26 pelo proprietário para inclusão da delegacia no segundo andar. | AG22: Arq. Priscila Polese | AH22: 45792 | AI22: Investidor | AJ22: BTS | AL22: 900 | AM22: 365 | AO22: 16 | AP22: Realizado | AQ22: Lucas Machado | AR22: Laercio Becker | AS22: 45777 | AT22: 45790 | AU22: 45792 | AV22: 20000 | AW22: 120 meses | AX22: inauguraçao da loja ou max 20 dias apos conclusao das obras | AY22: Bts 5 anos | AZ22: acima de 1m | BA22: 1000000 | BB22: sim, 60 dias | BC22: 650000 | BD22: 675000 | BE22: 700000 | BF22: 750000 | BG22: 800000 | BH22: 850000 | BJ22: NOSSOS PRESTADORES - APORTE DE 1M
B23: 1087 | C23: - | E23: RS | F23: Bento Gonçalves | G23: Escolinha (Rua Xingú) | H23: 45779 | I23: Eduardo Brand | J23: Assinado por ambos | K23: 46006 | L23: -29.170540836, -51.509960200 | M23: R. Tietê, 167 - São Bento, Bento Gonçalves - RS, 95700-000 (-29.170540836, -51.509960200) | Q23: Não visitado | R23: Eduardo | S23: 560872.58 | T23: 897892.6 | U23: Eduardo Brand | V23: 45995 | W23: 45995 | X23: 25 | Y23: Bento Gonçalves 2 | Z23: 24500 | AA23: 0.76 | AB23: Não | AC23: https://maps.app.goo.gl/mk2jJD75LiPWHqr17 | AE23: https://farmaciassaojoao.sharepoint.com/:b:/s/expansao/IQC-S2zLlNwKS6vYFWqz0Rc3AYcNldRwJpH5Jn410OHJQVk?e=FyYgbZ | AF23: Estudo refeito, potencial anterior R$405.073,74 | AQ23: Lucas Machado | AR23: Fabio Baldasso | AS23: 45847 | AT23: 46006 | AU23: 46006 | AV23: 28000 | AW23: 180 meses | BB23: sim | BJ23: FSJ fica com a responsabilidade do custo da fachada.
B24: 1220 | C24: - | E24: RS | F24: Farroupilha | G24: Engenharia do corpo | H24: 45846 | I24: Juliano Ghellere | J24: Assinado por ambos | K24: 45987 | L24: -29.219192106, -51.345803248 | M24: Av. Santa Rita, 472 - Planalto, Farroupilha - RS, 95172-000 (-29.219192106, -51.345803248) | Q24: Não visitado | R24: Pablo | S24: 524621.96 | T24: 839859.52 | U24: Juliano Ghellere | V24: 45971 | W24: 45971 | X24: 22 | Y24: Farroupilha 2 | Z24: 14360 | AA24: 0.8 | AB24: Próximo Pablo | AC24: https://maps.app.goo.gl/CsEyjMsapyXe78wW8 | AE24: Link do estudo | AF24: Estudo refeito, potêncial anterior R$471.518,71 ~Pablo "Ponto com acesso limitado." | AG24: Arq. Henrique Terres | AH24: 45852 | AI24: Investidor | AJ24: BTS | AK24: 1454557.7 | AL24: 373m² térreo | AM24: 373m² térreo | AO24: 13 | AP24: Realizado | AQ24: Lucas Machado | AR24: Juliano Ghellere | AS24: 45973 | AT24: 45983 | AU24: 45988 | AV24: R$ 16.500,00 no 1° ano; R$ 18.000,00 no 2° ano. | AW24: 180 meses | AX24: Inauguração | AY24: Até o 3° ano de contrato = 6 aluguéis proporcionais. Após, 3 aluguéis proporcionais. | BB24: Sim | BJ24: Reajuste após o 24° mês pela média do IGP-M e IPCA. Caso não se consiga idealizar a abetura dos acessos por ambas as vias, possuímos a faculdade de rescindir o contrato de locação.
B25: 1237 | C25: 1640 | D25: Pelotas 13 | E25: RS | F25: Pelotas | G25: Arco Íris- TR da 13 | H25: 45846 | I25: Juliano Petrarca | J25: Assinado por ambos | K25: 45910 | L25: -31.717471737, -52.309399400 | M25: Av. Engenheiro Ildefonso Simões Lopes, 2628 - Três Vendas, Pelotas - RS, 96060-290 (-31.717471737, -52.309399400) | N25: TR da 13 | Q25: Não visitado | R25: Eduardo | S25: 504295.74 | U25: Juliano Petrarca | V25: 45852 | W25: 45852 | X25: 0 | Y25: Pelotas 18 | Z25: 6512 | AA25: 3.28 | AB25: Não | AC25: https://maps.app.goo.gl/i4CkozPNEvPWYVJo7 | AE25: Link do estudo | AF25: - | AG25: Arq. Henrique Terres | AH25: 45861 | AI25: Investidor | AJ25: BTS | AL25: 615m² | AQ25: Marina | AR25: Juliano Petrarca | AS25: 45862 | AT25: 45863 | AU25: 45910 | AV25: 15000 | AW25: 240 meses | AY25: 03 locativos proporcionais | BA25: 1000000 | BC25: 450000 | BD25: 500000 | BE25: 520000 | BF25: 480000 | BG25: 520000 | BH25: 550000 | BI25: 650000 | BJ25: Aluguel de R$15k no primeiro ano, segundo R$18k
B26: 1285 | C26: - | D26: Criciuma 2 | E26: SC | F26: Criciúma | G26: - | H26: 45869 | I26: Naudal Almeida | J26: Assinado por ambos | K26: 46006 | L26: -28.668824678, -49.422586521 | M26: Av. dos Imigrantes, 1866 - Rio Maina, Criciúma - SC, 88818-400 (-28.668824678, -49.422586521) | Q26: Não visitado | R26: Eduardo | S26: 433755.12 | T26: 694392.14 | U26: Naudal Almeida | V26: 45876 | W26: 45876 | X26: 10 | Y26: Criciúma 8 | Z26: 11534 | AA26: 3.77 | AB26: Não | AC26: https://maps.app.goo.gl/6pRFL6AdvTyqEZrC9 | AE26: https://farmaciassaojoao.sharepoint.com/:b:/s/expansao/IQCWq4_eU8HJSatn7oPBAtF8AUC_OwnC5TgiHZSgHuzvycU?e=uglgfC | AH26: 45974 | AQ26: Lucas Machado | AR26: Naudal Almeida | AT26: 46002 | AU26: 46006
B27: 1290 | C27: - | D27: - | E27: SC | F27: Itapema | G27: Churrascaria Osmari | H27: 45873 | I27: Cleiton de Lima | J27: Assinado por ambos | K27: 45964 | L27: -27.100425656, -48.615568519 | M27: Av. Nereu Ramos, 610 - Centro, Itapema - SC, 88220-000 (-27.100425656, -48.615568519) | Q27: Reprovado | R27: Eduardo | S27: 553382.69 | T27: 885902.15 | U27: Cleiton de Lima | V27: 45873 | W27: 45873 | X27: 11 | Y27: Itapema 3 | Z27: 18655 | AA27: 0.39 | AB27: Não | AC27: https://maps.app.goo.gl/YMnbjVBVWsm7DvMeA | AE27: https://farmaciassaojoao.sharepoint.com/:b:/s/expansao/IQBYcU8KZic-QrP36y6aAo0UAYECaeAAC0dGyaA1ucxsVIQ?e=8fgipw | AH27: 45932 | AI27: Reforma FSJ | AJ27: Reforma FSJ | AK27: 0 | AL27: 354.1 | AM27: 203.82 | AN27: 0 | AO27: 9 | AP27: Realizado | AQ27: Lucas Machado | AR27: Cleiton de Lima | AS27: 45932 | AT27: 45961 | AU27: 45964 | AV27: 25000 | AW27: 60 meses | AY27: 3 meses proporcionais | AZ27: não possui orçamento | BA27: - | BB27: não | BC27: 450000 | BD27: 460000 | BE27: 475000 | BF27: 490000 | BG27: 500000 | BH27: 515000 | BI27: 580000 | BJ27: Aluguel 1° ano: R$ 25k / 2° ano: R$ 27k / 3° ano: R$ 30k
B28: 1301 | C28: - | E28: PR | F28: Quedas do Iguaçu | G28: Ampliação | H28: 45881 | I28: Rodrigo Ferreira | J28: Assinado por ambos | K28: 46099 | L28: -25.451636601, -52.910068881 | M28: R. Jacarandá, 530 - Centro, Quedas do Iguaçu - PR, 85460-000 (-25.451636601, -52.910068881) | Q28: Não visitado | R28: Pendente profissional | AC28: https://maps.app.goo.gl/Pb1BgTJjQGV97ydC8 | AH28: 45881 | AQ28: Gabriel | AR28: Rodrigo Ferreira | AS28: 46086 | AT28: 46086 | AU28: 46099 | AV28: 6000 | AW28: 120 meses | AX28: na posse (30 dias após a assinatura do contrato ou seja, 05/04) | AY28: 3 aluguéis proporcinais | BA28: - | BB28: sim | BJ28: Caso seja preciso mais prazo para desocupação do local as partes voltarão a conversar para definição da nova data de entrega.
B29: 1346 | C29: 1627 | E29: RS | F29: Canoas | G29: Esquina com a rua Araça | H29: 45910 | I29: Eduardo Barbizan | J29: Assinado por ambos | K29: 46006 | L29: -29.923780336, -51.183975116 | M29: R. Dr. Barcelos, 1397 - Centro, Canoas - RS, 92310-200 ( -29.923780336, -51.183975116 ) | Q29: Não visitado | R29: Eduardo | S29: 541340.74 | U29: Renan Walker | V29: 45910 | W29: 45910 | X29: 13 | Y29: Canoas 25 | Z29: 19345 | AA29: 0.84 | AB29: Não | AC29: https://maps.app.goo.gl/5cFx5tS9rmAvf6vA6 | AH29: 45919 | AK29: 1100000 | AQ29: Gabriel | AR29: Eduardo Barbizan | AS29: 45985 | AT29: 46003 | AU29: 46006 | AV29: R$ 26.000,00 1° ano; R$ 27.000,00 2° ano | AW29: 240 meses | AZ29: 500.000 + 380.000 | BA29: 600000 | BC29: 400000 | BD29: 450000 | BE29: 500 | BF29: 550000 | BG29: 550000 | BH29: 700000
B30: 1365 | C30: - | D30: Gravataí 10 | E30: RS | F30: Gravataí | G30: Av Rondon x Rua Aquino | H30: 45917 | I30: Naudal Almeida | J30: Assinado por ambos | K30: 45950 | L30: -29.917566821, -51.069569709 | M30: Av. Mal. Rondon, 1575 - Morada do Vale I, Gravataí - RS, 94080-500 ( -29.917566821, -51.069569709 ) | Q30: Não visitado | R30: Eduardo | S30: 597731.71 | U30: Naudal Almeida | V30: 45932 | W30: 45932 | X30: 9 | Y30: Gravataí 6 | Z30: 32541 | AA30: 1.22 | AB30: Não | AC30: https://maps.app.goo.gl/pjmM1mX3oV1QkZWk7 | AE30: Link do estudo | AF30: - | AG30: Arq. Henrique Terres | AH30: 45932 | AI30: Investidor | AJ30: BTS | AK30: 1422085.2 | AL30: 421m² | AM30: 328m² térreo e 93m² de mezanino | AN30: 93m² mezanino | AO30: 8 | AP30: Realizado | AQ30: Gabriel | AR30: Naudal Almeida | AS30: 45932 | AT30: 45944 | AU30: 45948 | AV30: 1° ano R$ 17.000,00; 2° ano R$ 18.000,00; 3° ano R$ 19.000,00; 4° ano R$ 20.000,00 | AW30: 240 meses | AX30: Inauguração (aguardando aditivo) | AY30: antes do prazo de 36 meses, 06 locativos proporcionais, após 3 meses prop. | AZ30: R$ - | BA30: 1422085.2 | BB30: Sim | BJ30: Após o 4° ano de vigência, reajuste pela média do IGP-M e IPCA.
B31: 1431 | C31: 1653 | D31: Maringá 6 | E31: PR | F31: Maringá | G31: Terreno antiga loja Ingá | H31: 45960 | I31: Renan Walker | J31: Assinado por ambos | K31: 45982 | L31: -23.381578822, -51.937948162 | M31: Av. das Palmeiras, 406 - Parque Palmeiras, Maringá - PR, 87023-160 ( -23.381578822, -51.937948162 ) | Q31: Não visitado | R31: Luísa | S31: 582011.72 | U31: Renan Walker | V31: 45960 | W31: 45960 | X31: 7 | Y31: Maringa 16 | Z31: 27523 | AA31: 1.67 | AB31: Não | AC31: https://maps.app.goo.gl/YnATPBH1vPBxorto9 | AE31: Link do estudo | AG31: Arq. Henrique Terres | AH31: 45961 | AI31: Investidor | AJ31: BTS | AK31: 1488290 | AL31: 344m² de térreo e 82m² de mezanino | AM31: 344m² de térreo e 82m² de mezanino | AN31: 82m² | AO31: 12 | AP31: Realizado | AQ31: Gabriel | AR31: Rodrigo Ferreira | AS31: 45968 | AT31: 45980 | AU31: 45982 | AV31: 15mil ou 3% do faturamento | AW31: 180 meses | AX31: Inauguração | AY31: BTS de 36 meses. Após, 3 aluguéis proporcionais. | AZ31: R$ - | BA31: 1488290 | BB31: Não | BC31: 350000 | BD31: 360000 | BE31: 370000 | BF31: 380000 | BG31: 390000 | BH31: 400000 | BI31: 500000 | BJ31: Investidor entrega a sala pronta. Reajuste pela média do IGP-M e IPCA.
B32: 1443 | C32: - | E32: SC | F32: Blumenau | G32: Muniz | H32: 45965 | I32: Luan Pessoa | J32: Assinado por ambos | K32: 45982 | L32: -26.906831376, -49.074350406 | M32: R. São Paulo, 1046 - Victor Konder, Blumenau - SC, 89012-000 ( -26.906831376, -49.074350406 ) | Q32: Não visitado | R32: Eduardo | S32: 456019.7 | T32: 730035.18 | U32: Luan Pessoa | V32: 45967 | W32: 45967 | X32: 8 | Y32: Blumenau 4 | Z32: 19931 | AA32: 2.93 | AB32: Não | AC32: https://maps.app.goo.gl/NWrzqfpkYNnb8vXC8 | AE32: Link do estudo | AG32: Arq. Adeline Saggiorato | AH32: 45966 | AI32: Investidor/ FSJ | AJ32: BTS A | AK32: 1595961.3 | AL32: 314.65 | AM32: 240.36 | AN32: 82.15 | AO32: 19 | AP32: Realizado | AQ32: Lucas Machado | AR32: Luan Pessoa | AS32: 45978 | AT32: 45980 | AU32: 45982 | AV32: 1° ano 25k - 2° 28k - 3° 30k | AW32: 120 meses | AX32: a partir da abertura da loja | AY32: 1° ano: 48 alugueís proporcionais - 2° ano: 36 alugueís proporcionais - 3° ano: 24 alugueís proporcionais - 4° ano: 12 alugueís proporcionais - a partir do 5° ano: 3 alugueís proporcionais | AZ32: 246000 | BA32: investirá até R$ 1.350M | BB32: sim, prazo de saída: 90 dias após notificação | BC32: 450000 | BD32: 460000 | BE32: 475000 | BF32: 490000 | BG32: 500000 | BH32: 515000 | BI32: 580000 | BJ32: Jan: 630.000,00
BJ33: Fev: 600.000,00
B34: 1445 | C34: 1664 | D34: Montenegro 8 | E34: RS | F34: Montenegro | G34: Amor Saúde | H34: 45966 | I34: Luiz Kuhn | J34: Assinado por ambos | K34: 46006 | L34: -29.678938332, -51.464648900 | M34: R. Ramiro Barcelos, 2825 - Centro, Montenegro - RS, 92510-275 (-29.678938332, -51.464648900) | Q34: Não visitado | R34: Eduardo | S34: 578703.35 | T34: 926437.61 | U34: Luiz Kuhn | V34: 45967 | W34: 45967 | X34: 6 | Y34: Montenegro 5 | Z34: 14942 | AA34: 0.65 | AB34: Não | AC34: https://maps.app.goo.gl/YSKCkiJBQSgYZSaBA | AE34: https://farmaciassaojoao.sharepoint.com/sites/expansao/Documentos Compartilhados/1- CONTRATOS & CONTROLES MÊS/../../../../:b:/s/expansao/ETu2xF9iuhJDtCCYo7uKI3YBktMKUFVfjFr1HqycWu5hcA?e=tSkI9y | AH34: 45966 | AQ34: Gabriel | AR34: Laercio Becker | AS34: 45988 | AT34: 46001 | AU34: 46006 | AV34: R$ 18.000,00 no 1° ano; R$ 20.000,00 no 2° ano e R$ 22.000,00 no 3° ano. | AW34: 180 meses | AX34: Inauguração | AY34: BTS de 60 meses. Após, 3 aluguéis proporcionais.
B35: 1456 | C35: - | E35: SC | F35: Palhoça | G35: ponta do papagaio | H35: 45968 | I35: Luan Pessoa | J35: Assinado por ambos | K35: 46014 | L35: -27.844311817, -48.594989811 | M35: Rod. Evádio Paulo Broering - Ponta do Papagaio, Palhoça - SC, 88139-315 (-27.844311817, -48.594989811) | Q35: Não visitado | R35: Eduardo | S35: 314315.63 | T35: 503183.23 | U35: Luan Pessoa | V35: 45973 | W35: 45973 | X35: 0 | Y35: Palhoça 1 | Z35: 6752 | AA35: 25.74 | AB35: Não | AC35: https://maps.app.goo.gl/pn6cNUYLpajCpkC38 | AE35: Link do estudo | AH35: 45968 | AQ35: Lucas Machado | AR35: Luan Pessoa | AS35: 45989 | AT35: 46010 | AU35: 46014
B36: 1464 | C36: - | E36: SC | F36: São Francisco do Sul | G36: Praia de Ubatuba | H36: 45973 | I36: Luan Pessoa | J36: Assinado por ambos | K36: 46017 | L36: -26.222487395, -48.521780143 | M36: Rod. Duque de Caxias, 763 - Do Ubatuba, São Francisco do Sul - SC, 89240-000 (-26.222487395, -48.521780143) | Q36: Não visitado | R36: Pablo | S36: 443004.87 | T36: 709199.93 | U36: Luan Pessoa | V36: 45973 | W36: 45973 | X36: 3 | Y36: Joinville 4 | Z36: 7940 | AA36: 54.66 | AB36: Não | AC36: https://maps.app.goo.gl/xhDsKJriCFzA6w6p9 | AE36: Link do estudo | AF36: Foi considerado no estudo o deslocamento de 5 min do carro. Pois a geografia do local não permite a utilização de raios. | AQ36: Lucas Machado | AR36: Luan Pessoa | AS36: 45996 | AT36: 46015 | AU36: 46017 | AV36: R$18.500,00 primeiro ano / R$ 20.000,00 segundo ano | AW36: 120 meses | AX36: a partir da data de inauguração | BA36: 1200000
B37: 1475 | C37: 1651 | D37: Caxias 76 | E37: RS | F37: Caxias do Sul | H37: 45982 | I37: Tatiana Brair | J37: Aquisição | K37: 45982 | L37: -29.126565188, -51.174828898 | M37: R. Vicente Acylino de Oliveira, 100 - Nossa Sra. de Fátima, Caxias do Sul - RS, 95043-241 (-29.126564447, -51.174827202) | N37: Caxias 76 | Q37: Não visitado | R37: Eduardo | S37: 623415.99 | T37: 998017.42 | U37: Tatiana Brair | V37: 45985 | W37: 45985 | X37: 3 | Y37: Caxias 74 | Z37: 29154 | AA37: 1 | AB37: Não | AC37: https://maps.app.goo.gl/gLDzVkuqFP89sWpG6 | AE37: Link do estudo | AI37: Aquisição | AJ37: Aquisição | AQ37: Lucas Schwingel | AR37: Tatiana Brair | AT37: 45498 | AU37: 46059 | AV37: aquisição | AW37: aquisição | AX37: Brair empreendimentos | BJ37: Está sendo adquirido as casas existentes no terreno e sendo demolidas pra posteriormente ser edificada a nova loja.
B38: 1481 | C38: 1638 | D38: Guarapuava 3 | E38: PR | F38: Guarapuava | G38: Rótula Padaria | H38: 45986 | I38: Juliano Ghellere | J38: Assinado por ambos | K38: 46036 | L38: -25.378408091, -51.485145173 | M38: Rua Padre Honorino João Muraro, 275 - Vila Carli, Guarapuava - PR, 85040-180 (-25.378408091, -51.485145173) | Q38: Não visitado | R38: Luísa | S38: 398270.97 | T38: 637586.09 | U38: Juliano Ghellere | V38: 45987 | W38: 45987 | X38: 3 | Y38: Guarapuava | Z38: 17645 | AA38: 2.72 | AB38: Pablo | AC38: https://maps.app.goo.gl/fF3xnZ6bdsWqq2RM6 | AE38: Link do estudo | AG38: Arq. Henrique Terres | AH38: 46031 | AI38: Investidor | AJ38: BTS | AK38: 1454544 | AL38: 360m² de térreo | AM38: 360m² térreo | AO38: 17 | AP38: Realizado | AQ38: Lucas Machado | AR38: Juliano Ghellere | AT38: 46036 | AU38: 46036 | AV38: 18000 | AW38: 180 meses | AX38: Inauguração | AY38: BTS 36 meses. Após, 3 aluguéis proporcionais. | AZ38: R$ - | BA38: 1454544 | BJ38: Reajuste pela média do IGP-M e IPCA. Investidor entrega pronto a loja. Investidor irá adquirir o imóvel.
B39: 1523 | C39: 1668 | D39: Santa Cruz 2 | E39: RS | F39: Santa Cruz do Sul | H39: 45994 | I39: Laercio Becker | J39: Assinado por ambos | K39: 46003 | L39: -29.721362125, -52.434236093 | M39: R. Sen. Pinheiro Machado, 1203 - Centro, Santa Cruz do Sul - RS, 96810-136 (-29.721362125, -52.434236093) | Q39: Não visitado | R39: Luísa | S39: 738735.28 | T39: 1182630.4 | U39: Laercio Becker | V39: 45996 | W39: 45996 | X39: 29 | Y39: Santa Cruz 15 | Z39: 17009 | AA39: 0.403 | AB39: Não | AC39: https://maps.app.goo.gl/sSzfpwqoWgRUyB6N6 | AE39: Link do estudo | AQ39: Lucas Machado | AR39: Laercio Becker | AS39: 46000 | AT39: 46003 | AU39: 46003 | AV39: 18000 | AW39: 120 meses | AY39: antes do prazo de 48 meses, multa no valor dos locativos faltantes para completar o período | BC39: 425000 | BD39: 450000 | BE39: 500000 | BF39: 525000 | BG39: 550000 | BH39: 600000
B40: 1562 | C40: - | E40: RS | F40: Uruguaiana | G40: Ampliação da 7 | H40: 46009 | I40: Juliano Petrarca | J40: Ampliação | K40: 46009 | L40: -29.758487007, -57.075838500 | M40: Av. Pres. Vargas, 3734 - São João, Uruguaiana - RS, 97510-130 (-29.758487007, -57.075838500) | Q40: Não visitado | R40: Pendente profissional | AB40: Não | AC40: https://maps.app.goo.gl/B5sJCZB7pQvbMPms6 | AH40: 46009 | AI40: Ampliação | AJ40: Reforma FSJ | AS40: 44340 | AT40: 44340 | AU40: 44340 | AW40: 60 meses | AY40: 10 x o valor do aluguel
B41: 1612 | C41: - | D41: - | E41: RS | F41: Pinheiro Machado | G41: Ampliação da 1 | H41: 46034 | I41: Juliano Petrarca | J41: Ampliação | K41: 46034 | L41: -31.578840336, -53.381979079 | M41: R. Dutra de Andrade, 776 - CENTRO, Pinheiro Machado - RS, 96470-000 (-31.578840336, -53.381979079) | Q41: Não visitado | R41: Pendente profissional | AH41: 46034 | AI41: Ampliação | AJ41: Reforma FSJ
B42: 1616 | C42: - | D42: - | E42: SC | F42: Balneário Camboriú | G42: Ampliação da 1 | H42: 46035 | I42: Cleiton de Lima | J42: Ampliação | K42: 46035 | L42: -26.985963343, -48.635632143 | M42: Rua 511, 200 - Centro, Balneário Camboriú - SC, 88330-702 (-26.985963343, -48.635632143) | Q42: Não visitado | R42: Luísa | AB42: Não | AC42: https://maps.app.goo.gl/1bV1R3oJgoPRQ2tQ9 | AD42: https://farmaciassaojoao.sharepoint.com/:v:/s/expansao/IQDnJ1pgamqtRLmR7mQ9EDgKAfE9tUXiqzJiHFNQF4jEpOI?e=BZ0kjA | AH42: 46035 | AI42: Ampliação | AJ42: Reforma FSJ
B43: 1638 | C43: - | D43: - | E43: RS | F43: Farroupilha | G43: Posto Ipiranga | H43: 46042 | I43: Tatiana Brair | J43: Assinado por ambos | K43: 46085 | L43: -29.231488250, -51.342548805 | M43: R. Júlio de Castilhos, 384 - Centro, Farroupilha - RS, 95180-000 (-29.231488250, -51.342548805) | N43: TR da filial 7 | Q43: Não visitado | R43: Pablo | S43: 539963.61 | T43: 864419.74 | U43: Tatiana Brair | V43: 46045 | W43: 46045 | X43: 27 | Y43: Farroupilha 1 | Z43: 13421 | AA43: 0.773 | AB43: Não | AC43: https://maps.app.goo.gl/ouscpPJozTk8x1VdA | AE43: https://farmaciassaojoao.sharepoint.com/:b:/s/expansao/IQBwPJ6CbbSpT6QAeFOVgTX5Abt3rSAZqbZn7G2lQm1Rcrg?e=mIA3jR | AH43: 46042 | AQ43: Lucas Schwingel | AS43: 46080 | AT43: 46083 | AU43: 46085 | AV43: R$ 23.000,00 primeiro ano e R$ 25.000,00 segundo ano | AW43: 120 meses | AX43: conforme aditivo | AY43: antes do prazo de 48 meses, pgto de multa correspondente ao valor dos locativos faltantes para completar o período, após 3 proporcionais.
B44: 1669 | C44: - | D44: - | E44: SC | F44: Itajaí | G44: Ampliação da 1 | H44: 46050 | I44: Cleiton de Lima | J44: Ampliação | K44: 46050 | L44: -26.947463771, -48.639449054 | M44: Av. Osvaldo Reis, 2751 - Praia Brava, Itajaí - SC, 88306-001 (-26.947463771, -48.639449054) | Q44: Não visitado | R44: Pendente profissional | AB44: Não | AC44: https://maps.app.goo.gl/8BpyBFHfpYT53okC8 | AD44: https://farmaciassaojoao.sharepoint.com/:v:/s/expansao/IQAm8u24spbGSr7H1Tseu8EqAWi58xiZ63fkltVMFZHAItQ?e=RaxSaS | AH44: 46050 | AI44: Ampliação | AJ44: Reforma FSJ
B45: 1691 | C45: - | D45: - | E45: RS | F45: São Borja | G45: Aquisição terreno | H45: 46056 | I45: B. Empreendimentos | J45: Aquisição | K45: 46056 | L45: -28.657617128, -56.004347443 | M45: R. Olinto Arami Silva, 930 - Centro, São Borja - RS, 97670-000 (-28.657617128, -56.004347443) | Q45: Aprovado | R45: Pablo | S45: 578612.39 | T45: 926292 | U45: Quadro | V45: 46063 | W45: 46063 | X45: 15 | Y45: São Borja 1 | Z45: 20399 | AA45: 0.287 | AB45: Não | AC45: https://maps.app.goo.gl/34cJe8AJpvFsuUjh8 | AE45: https://farmaciassaojoao.sharepoint.com/:b:/s/expansao/IQBY9QjrQaL5QYG_U5wk5VlMATTZmoS_3BzYHGucF3bG8jM?e=DMNaRc | AF45: O estudo apresenta alto risco de canibalização. Foi considerado um crescimento de 5% no share da cidade, com a canibalização a loja tem projeção de venda de R$578.612,39. | AI45: Aquisição | AJ45: Aquisição | AQ45: Lucas Schwingel | AR45: Tatiana Brair | AS45: 40564 | AT45: 40564 | AU45: 45553 | AV45: aquisição | AW45: aquisição | AX45: aquisição
B46: 1697 | C46: - | D46: - | E46: RS | F46: Cachoeira do Sul | G46: Ampliação da Cachoeira 6 | H46: 46056 | I46: Laercio Becker | J46: Ampliação | K46: 46056 | L46: -30.040041183, -52.898330073 | M46: Av. Júlio de Castilhos, 149 - 01 - Centro, Cachoeira do Sul - RS, 96501-000 (-30.040041183, -52.898330073) | Q46: Não visitado | R46: Pendente profissional | AB46: Não | AC46: https://maps.app.goo.gl/JgwGep2WnfRhDhbt9 | AF46: Ampliação da loja e do estacionamento | AI46: Ampliação | AJ46: Reforma FSJ | AQ46: Lucas Machado | AR46: Laercio Becker | AS46: 46050 | AT46: 46056 | AU46: 46056 | AV46: R$ 7.000,00 no primeiro ano e R$ 8.000,00 no segundo ano | AW46: 120 meses | AY46: valor locativos faltantes para completar o período de | BA46: até R$150.000,00 | BB46: Sim | BJ46: a LOCADORA disponibilizará a quantia de até
AY47: 36 meses. | BJ47: R$ 150.000,00 (cento e cinquenta mil reais) demolição do imóvel atual e pavimentação (material
BJ48: e mão de obra), caso ultrapasse o valor, ficará por conta da FSJ.
B49: 1703 | C49: - | D49: - | E49: RS | F49: Serafina Corrêa | G49: Ampliação da 1 | H49: 46057 | I49: Renan Walker | J49: Ampliação | K49: 46057 | L49: -28.709747001, -51.934672164 | M49: Av. Miguel Soccol, 2721 - Centro, Serafina Corrêa - RS, 99250-000 (-28.709747001, -51.934672164) | Q49: Não visitado | R49: Pendente profissional | AB49: Não | AC49: https://maps.app.goo.gl/ebJjT8JCdgoib5UY8 | AH49: 46057 | AI49: Ampliação | AJ49: Reforma FSJ
